Workbook

Sheet Results Analysis
B2: True Positives
B3: = Detected correctly by ESCOX, also included in manual annotation
B4: Threshold | C4: 0.5 | D4: 0.55 | E4: 0.6 | F4: 0.65
B5: Absolute counts | C5: 19 | D5: 16 | E5: 11 | F5: 4
B7: False Positives
B8: = Detected by ESCOX, not included in manual annotation
B9: Threshold | C9: 0.5 | D9: 0.55 | E9: 0.6 | F9: 0.65
B10: Absolute counts | C10: 13 | D10: 7 | E10: 5 | F10: 2
B12: False Negatives
B13: = Not detected by ESCOX, but included in manual annotation
B14: Threshold | C14: 0.5 | D14: 0.55 | E14: 0.6 | F14: 0.65
B15: Absolute counts | C15: 7 | D15: 10 | E15: 15 | F15: 22
B17: Precision
B18: Threshold | C18: 0.5 | D18: 0.55 | E18: 0.6 | F18: 0.65
B19: Precision | C19: =C5/(C5+C10) -> 0.59375 | D19: =D5/(D5+D10) -> 0.69565217 | E19: =E5/(E5+E10) -> 0.6875 | F19: =F5/(F5+F10) -> 0.66666667
B21: Recall
B22: Threshold | C22: 0.5 | D22: 0.55 | E22: 0.6 | F22: 0.65
B23: Recall | C23: =C5/(C5+C15) -> 0.73076923 | D23: =D5/(D5+D15) -> 0.61538462 | E23: =E5/(E5+E15) -> 0.42307692 | F23: =F5/(F5+F15) -> 0.15384615
B25: F1
B26: Threshold | C26: 0.5 | D26: 0.55 | E26: 0.6 | F26: 0.65
B27: F1 | C27: =2*(C19*C23)/(C19+C23) -> 0.65517241 | D27: =2*(D19*D23)/(D19+D23) -> 0.65306122 | E27: =2*(E19*E23)/(E19+E23) -> 0.52380952 | F27: =2*(F19*F23)/(F19+F23) -> 0.25

Sheet Manual Reference An. Broad
A1: Module Title | B1: ESCO Skill URI | C1: ESCO Skill | D1: 0.5 detected | E1: 0.55 detected | F1: 0.6 detected | G1: 0.65 detected | H1: check if in ESCO_skills_allowed_data_domain | I1: broad skill uri | J1: broad skill name
A2: Introduction to Data Science | B2: http://data.europa.eu/esco/skill/edebd83d-35f6-4ed5-a940-6c203d178c01 | C2: data science | D2: Yes | E2: No | F2: No | G2: No | H2: =VLOOKUP(B2,data_skills!A:C,2,FALSE) -> data science | I2: =VLOOKUP(B2,'broaderSkills wo groups'!B:F,4,FALSE) -> #N/A
A3: Introduction to Data Science | B3: http://data.europa.eu/esco/skill/97bd1c21-66b2-4b7e-ad0f-e3cda590e378 | C3: data analytics | D3: Yes | E3: Yes | F3: Yes | G3: Yes | H3: =VLOOKUP(B3,data_skills!A:C,2,FALSE) -> data analytics | I3: =VLOOKUP(B3,'broaderSkills wo groups'!B:F,4,FALSE) -> #N/A
A4: Introduction to Data Science | B4: http://data.europa.eu/esco/skill/7ee4c2ea-b349-4bd2-81a3-ec31475d4833 | C4: statistics | D4: No | E4: No | F4: No | G4: No | H4: =VLOOKUP(B4,data_skills!A:C,2,FALSE) -> statistics | I4: =VLOOKUP(B4,'broaderSkills wo groups'!B:F,4,FALSE) -> #N/A
A5: Introduction to Data Science | B5: http://data.europa.eu/esco/skill/3a2d5b45-56e4-4f5a-a55a-4a4a65afdc43 | C5: machine learning | D5: No | E5: No | F5: No | G5: No | H5: =VLOOKUP(B5,data_skills!A:C,2,FALSE) -> machine learning | I5: =VLOOKUP(B5,'broaderSkills wo groups'!B:F,4,FALSE) -> http://data.europa.eu/esco/skill/e465a154-93f7-4973-9ce1-31659fe16dd2
A6: Introduction to Programming with Python | B6: http://data.europa.eu/esco/skill/ccd0a1d9-afda-43d9-b901-96344886e14d | C6: Python (computer programming) | D6: Yes | E6: Yes | F6: No | G6: No | H6: =VLOOKUP(B6,data_skills!A:C,2,FALSE) -> Python (computer programming) | I6: =VLOOKUP(B6,'broaderSkills wo groups'!B:F,4,FALSE) -> http://data.europa.eu/esco/skill/21d2f96d-35f7-4e3f-9745-c533d2dd6e97
A7: Introduction to Programming with Python | B7: http://data.europa.eu/esco/skill/2522a6ce-3202-4ac8-9f5b-b9cb5a3a83a1 | C7: debug software | D7: No | E7: No | F7: No | G7: No | H7: =VLOOKUP(B7,data_skills!A:C,2,FALSE) -> debug software | I7: =VLOOKUP(B7,'broaderSkills wo groups'!B:F,4,FALSE) -> #N/A
A8: Introduction to Programming with Python | B8: http://data.europa.eu/esco/skill/0c15aa34-6977-4da7-b1f0-2ba6a582ef1b | C8: monitor logging operations | D8: Yes | E8: Yes | F8: Yes | G8: No | H8: =VLOOKUP(B8,data_skills!A:C,2,FALSE) -> #N/A | I8: =VLOOKUP(B8,'broaderSkills wo groups'!B:F,4,FALSE) -> #N/A
A9: Introduction to Programming with Python | B9: http://data.europa.eu/esco/skill/797a4416-0b8d-44f3-8fcd-eb10bd0be6b4 | C9: develop software prototype | D9: No | E9: No | F9: No | G9: No | H9: =VLOOKUP(B9,data_skills!A:C,2,FALSE) -> develop software prototype | I9: =VLOOKUP(B9,'broaderSkills wo groups'!B:F,4,FALSE) -> #N/A
A10: Introduction to Academic Work for IT and Technology | B10: http://data.europa.eu/esco/skill/7a34b3d9-bd3b-4f4e-a0f6-f97439901cb7 | C10: apply scientific methods | D10: Yes | E10: Yes | F10: No | G10: No | H10: =VLOOKUP(B10,data_skills!A:C,2,FALSE) -> apply scientific methods | I10: =VLOOKUP(B10,'broaderSkills wo groups'!B:F,4,FALSE) -> #N/A
A11: Introduction to Academic Work for IT and Technology | B11: http://data.europa.eu/esco/skill/57b7804d-048b-4293-b8ac-a105d0468883 | C11: source criticism | D11: Yes | E11: Yes | F11: No | G11: No | H11: =VLOOKUP(B11,data_skills!A:C,2,FALSE) -> #N/A | I11: =VLOOKUP(B11,'broaderSkills wo groups'!B:F,4,FALSE) -> #N/A
A12: Database Modeling and Database Systems | B12: http://data.europa.eu/esco/skill/43ae58b9-5e56-4524-b45a-b422777a0576 | C12: database | D12: Yes | E12: Yes | F12: Yes | G12: Yes | H12: =VLOOKUP(B12,data_skills!A:C,2,FALSE) -> database | I12: =VLOOKUP(B12,'broaderSkills wo groups'!B:F,4,FALSE) -> #N/A
A13: Database Modeling and Database Systems | B13: http://data.europa.eu/esco/skill/598de5b0-5b58-4ea7-8058-a4bc4d18c742 | C13: SQL | D13: Yes | E13: Yes | F13: Yes | G13: No | H13: =VLOOKUP(B13,data_skills!A:C,2,FALSE) -> SQL | I13: =VLOOKUP(B13,'broaderSkills wo groups'!B:F,4,FALSE) -> http://data.europa.eu/esco/skill/9cf681c7-89ec-470c-b651-7fe03786f586
... A30: Exploratory Data Analysis and Visualization | B30: http://data.europa.eu/esco/skill/ccd0a1d9-afda-43d9-b901-96344886e14d | C30: Python (computer programming) | D30: No | E30: No | F30: No | G30: No | H30: =VLOOKUP(B30,data_skills!A:C,2,FALSE) -> Python (computer programming) | I30: =VLOOKUP(B30,'broaderSkills wo groups'!B:F,4,FALSE) -> http://data.europa.eu/esco/skill/21d2f96d-35f7-4e3f-9745-c533d2dd6e97

Sheet Manual Reference Annotation
A1: Module Title | B1: ESCO Skill URI | C1: ESCO Skill | D1: 0.5 detected | E1: 0.55 detected | F1: 0.6 detected | G1: 0.65 detected | H1: check if in ESCO_skills_allowed_data_domain
A2: Introduction to Data Science | B2: http://data.europa.eu/esco/skill/edebd83d-35f6-4ed5-a940-6c203d178c01 | C2: data science | D2: Yes | E2: No | F2: No | G2: No | H2: =VLOOKUP(B2,data_skills!A:C,2,FALSE) -> data science
A3: Introduction to Data Science | B3: http://data.europa.eu/esco/skill/97bd1c21-66b2-4b7e-ad0f-e3cda590e378 | C3: data analytics | D3: Yes | E3: Yes | F3: Yes | G3: Yes | H3: =VLOOKUP(B3,data_skills!A:C,2,FALSE) -> data analytics
A4: Introduction to Data Science | B4: http://data.europa.eu/esco/skill/7ee4c2ea-b349-4bd2-81a3-ec31475d4833 | C4: statistics | D4: No | E4: No | F4: No | G4: No | H4: =VLOOKUP(B4,data_skills!A:C,2,FALSE) -> statistics
A5: Introduction to Data Science | B5: http://data.europa.eu/esco/skill/3a2d5b45-56e4-4f5a-a55a-4a4a65afdc43 | C5: machine learning | D5: No | E5: No | F5: No | G5: No | H5: =VLOOKUP(B5,data_skills!A:C,2,FALSE) -> machine learning
A6: Introduction to Programming with Python | B6: http://data.europa.eu/esco/skill/ccd0a1d9-afda-43d9-b901-96344886e14d | C6: Python (computer programming) | D6: Yes | E6: Yes | F6: No | G6: No | H6: =VLOOKUP(B6,data_skills!A:C,2,FALSE) -> Python (computer programming)
A7: Introduction to Programming with Python | B7: http://data.europa.eu/esco/skill/2522a6ce-3202-4ac8-9f5b-b9cb5a3a83a1 | C7: debug software | D7: No | E7: No | F7: No | G7: No | H7: =VLOOKUP(B7,data_skills!A:C,2,FALSE) -> debug software
A8: Introduction to Programming with Python | B8: http://data.europa.eu/esco/skill/0c15aa34-6977-4da7-b1f0-2ba6a582ef1b | C8: monitor logging operations | D8: Yes | E8: Yes | F8: Yes | G8: No | H8: =VLOOKUP(B8,data_skills!A:C,2,FALSE) -> #N/A
A9: Introduction to Programming with Python | B9: http://data.europa.eu/esco/skill/797a4416-0b8d-44f3-8fcd-eb10bd0be6b4 | C9: develop software prototype | D9: No | E9: No | F9: No | G9: No | H9: =VLOOKUP(B9,data_skills!A:C,2,FALSE) -> develop software prototype
A10: Introduction to Academic Work for IT and Technology | B10: http://data.europa.eu/esco/skill/7a34b3d9-bd3b-4f4e-a0f6-f97439901cb7 | C10: apply scientific methods | D10: Yes | E10: Yes | F10: No | G10: No | H10: =VLOOKUP(B10,data_skills!A:C,2,FALSE) -> apply scientific methods
A11: Introduction to Academic Work for IT and Technology | B11: http://data.europa.eu/esco/skill/57b7804d-048b-4293-b8ac-a105d0468883 | C11: source criticism | D11: Yes | E11: Yes | F11: No | G11: No | H11: =VLOOKUP(B11,data_skills!A:C,2,FALSE) -> #N/A
A12: Database Modeling and Database Systems | B12: http://data.europa.eu/esco/skill/43ae58b9-5e56-4524-b45a-b422777a0576 | C12: database | D12: Yes | E12: Yes | F12: Yes | G12: Yes | H12: =VLOOKUP(B12,data_skills!A:C,2,FALSE) -> database
A13: Database Modeling and Database Systems | B13: http://data.europa.eu/esco/skill/598de5b0-5b58-4ea7-8058-a4bc4d18c742 | C13: SQL | D13: Yes | E13: Yes | F13: Yes | G13: No | H13: =VLOOKUP(B13,data_skills!A:C,2,FALSE) -> SQL
... A30: Exploratory Data Analysis and Visualization | B30: http://data.europa.eu/esco/skill/ccd0a1d9-afda-43d9-b901-96344886e14d | C30: Python (computer programming) | D30: No | E30: No | F30: No | G30: No | H30: =VLOOKUP(B30,data_skills!A:C,2,FALSE) -> Python (computer programming)

Sheet ESCOX thresholds results
A1: Module Code | B1: Module Title | C1: URI | D1: Threshold | E1: VLookupManualRefAnnotation | F1: SkillName | G1: Correctly detected | H1: check if in ESCO_skills_allowed_data_domain | I1: broaderSKillName
A2: DLBDSIDS-01 | B2: Introduction to Data Science | C2: http://data.europa.eu/esco/skill/0d6714c6-720e-4985-9791-5ab85d28da79 | D2: 0.5 | E2: =E9=VLOOKUP(C2,'Manual Reference Annotation'!B$2:B$5,1,FALSE) -> #N/A | F2: =VLOOKUP(E2,'Manual Reference Annotation'!B:C,2,FALSE) -> #N/A | G2: =IF(ISNA(E2),FALSE,TRUE) -> FALSE | H2: =VLOOKUP(C2,data_skills!A:B,1,FALSE) -> http://data.europa.eu/esco/skill/0d6714c6-720e-4985-9791-5ab85d28da79 | I2: =VLOOKUP(C2,'broaderSkills wo groups'!B:F,5,FALSE) -> use data processing techniques
A3: DLBDSIDS-01 | B3: Introduction to Data Science | C3: http://data.europa.eu/esco/skill/97bd1c21-66b2-4b7e-ad0f-e3cda590e378 | D3: 0.5 | E3: =VLOOKUP(C3,'Manual Reference Annotation'!B$2:B$5,1,FALSE) -> http://data.europa.eu/esco/skill/97bd1c21-66b2-4b7e-ad0f-e3cda590e378 | F3: =VLOOKUP(E3,'Manual Reference Annotation'!B:C,2,FALSE) -> data analytics | G3: =IF(ISNA(E3),FALSE,TRUE) -> TRUE | H3: =VLOOKUP(C3,data_skills!A:B,1,FALSE) -> http://data.europa.eu/esco/skill/97bd1c21-66b2-4b7e-ad0f-e3cda590e378 | I3: =VLOOKUP(C3,'broaderSkills wo groups'!B:F,5,FALSE) -> #N/A
A4: DLBDSIDS-01 | B4: Introduction to Data Science | C4: http://data.europa.eu/esco/skill/edebd83d-35f6-4ed5-a940-6c203d178c01 | D4: 0.5 | E4: =VLOOKUP(C4,'Manual Reference Annotation'!B$2:B$5,1,FALSE) -> http://data.europa.eu/esco/skill/edebd83d-35f6-4ed5-a940-6c203d178c01 | F4: =VLOOKUP(E4,'Manual Reference Annotation'!B:C,2,FALSE) -> data science | G4: =IF(ISNA(E4),FALSE,TRUE) -> TRUE | H4: =VLOOKUP(C4,data_skills!A:B,1,FALSE) -> http://data.europa.eu/esco/skill/edebd83d-35f6-4ed5-a940-6c203d178c01 | I4: =VLOOKUP(C4,'broaderSkills wo groups'!B:F,5,FALSE) -> #N/A
A5: DLBDSIDS-01 | B5: Introduction to Data Science | C5: http://data.europa.eu/esco/skill/97bd1c21-66b2-4b7e-ad0f-e3cda590e378 | D5: 0.55 | E5: =VLOOKUP(C5,'Manual Reference Annotation'!B$2:B$5,1,FALSE) -> http://data.europa.eu/esco/skill/97bd1c21-66b2-4b7e-ad0f-e3cda590e378 | F5: =VLOOKUP(E5,'Manual Reference Annotation'!B:C,2,FALSE) -> data analytics | G5: =IF(ISNA(E5),FALSE,TRUE) -> TRUE | H5: =VLOOKUP(C5,data_skills!A:B,1,FALSE) -> http://data.europa.eu/esco/skill/97bd1c21-66b2-4b7e-ad0f-e3cda590e378 | I5: =VLOOKUP(C5,'broaderSkills wo groups'!B:F,5,FALSE) -> #N/A
A6: DLBDSIDS-01 | B6: Introduction to Data Science | C6: http://data.europa.eu/esco/skill/edebd83d-35f6-4ed5-a940-6c203d178c01 | D6: 0.55 | E6: =VLOOKUP(C6,'Manual Reference Annotation'!B$2:B$5,1,FALSE) -> http://data.europa.eu/esco/skill/edebd83d-35f6-4ed5-a940-6c203d178c01 | F6: =VLOOKUP(E6,'Manual Reference Annotation'!B:C,2,FALSE) -> data science | G6: =IF(ISNA(E6),FALSE,TRUE) -> TRUE | H6: =VLOOKUP(C6,data_skills!A:B,1,FALSE) -> http://data.europa.eu/esco/skill/edebd83d-35f6-4ed5-a940-6c203d178c01 | I6: =VLOOKUP(C6,'broaderSkills wo groups'!B:F,5,FALSE) -> #N/A
A7: DLBDSIDS-01 | B7: Introduction to Data Science | C7: http://data.europa.eu/esco/skill/97bd1c21-66b2-4b7e-ad0f-e3cda590e378 | D7: 0.6 | E7: =VLOOKUP(C7,'Manual Reference Annotation'!B$2:B$5,1,FALSE) -> http://data.europa.eu/esco/skill/97bd1c21-66b2-4b7e-ad0f-e3cda590e378 | F7: =VLOOKUP(E7,'Manual Reference Annotation'!B:C,2,FALSE) -> data analytics | G7: =IF(ISNA(E7),FALSE,TRUE) -> TRUE | H7: =VLOOKUP(C7,data_skills!A:B,1,FALSE) -> http://data.europa.eu/esco/skill/97bd1c21-66b2-4b7e-ad0f-e3cda590e378 | I7: =VLOOKUP(C7,'broaderSkills wo groups'!B:F,5,FALSE) -> #N/A
A8: DLBDSIDS-01 | B8: Introduction to Data Science | C8: http://data.europa.eu/esco/skill/edebd83d-35f6-4ed5-a940-6c203d178c01 | D8: 0.6 | E8: =VLOOKUP(C8,'Manual Reference Annotation'!B$2:B$5,1,FALSE) -> http://data.europa.eu/esco/skill/edebd83d-35f6-4ed5-a940-6c203d178c01 | F8: =VLOOKUP(E8,'Manual Reference Annotation'!B:C,2,FALSE) -> data science | G8: =IF(ISNA(E8),FALSE,TRUE) -> TRUE | H8: =VLOOKUP(C8,data_skills!A:B,1,FALSE) -> http://data.europa.eu/esco/skill/edebd83d-35f6-4ed5-a940-6c203d178c01 | I8: =VLOOKUP(C8,'broaderSkills wo groups'!B:F,5,FALSE) -> #N/A
A9: DLBDSIPWP | B9: Introduction to Programming with Python | C9: http://data.europa.eu/esco/skill/0c15aa34-6977-4da7-b1f0-2ba6a582ef1b | D9: 0.5 | E9: =VLOOKUP(C9,'Manual Reference Annotation'!B$6:B$9,1,FALSE) -> http://data.europa.eu/esco/skill/0c15aa34-6977-4da7-b1f0-2ba6a582ef1b | F9: =VLOOKUP(E9,'Manual Reference Annotation'!B:C,2,FALSE) -> monitor logging operations | G9: =IF(ISNA(E9),FALSE,TRUE) -> TRUE | H9: =VLOOKUP(C9,data_skills!A:B,1,FALSE) -> #N/A | I9: =VLOOKUP(C9,'broaderSkills wo groups'!B:F,5,FALSE) -> #N/A
A10: DLBDSIPWP | B10: Introduction to Programming with Python | C10: http://data.europa.eu/esco/skill/ccd0a1d9-afda-43d9-b901-96344886e14d | D10: 0.5 | E10: =VLOOKUP(C10,'Manual Reference Annotation'!B$6:B$9,1,FALSE) -> http://data.europa.eu/esco/skill/ccd0a1d9-afda-43d9-b901-96344886e14d | F10: =VLOOKUP(E10,'Manual Reference Annotation'!B:C,2,FALSE) -> Python (computer programming) | G10: =IF(ISNA(E10),FALSE,TRUE) -> TRUE | H10: =VLOOKUP(C10,data_skills!A:B,1,FALSE) -> http://data.europa.eu/esco/skill/ccd0a1d9-afda-43d9-b901-96344886e14d | I10: =VLOOKUP(C10,'broaderSkills wo groups'!B:F,5,FALSE) -> computer programming
A11: DLBDSIPWP | B11: Introduction to Programming with Python | C11: http://data.europa.eu/esco/skill/d0245e61-204f-48ca-911b-45e564732682 | D11: 0.5 | E11: =VLOOKUP(C11,'Manual Reference Annotation'!B$6:B$9,1,FALSE) -> #N/A | F11: =VLOOKUP(E11,'Manual Reference Annotation'!B:C,2,FALSE) -> #N/A | G11: =IF(ISNA(E11),FALSE,TRUE) -> FALSE | H11: =VLOOKUP(C11,data_skills!A:B,1,FALSE) -> #N/A | I11: =VLOOKUP(C11,'broaderSkills wo groups'!B:F,5,FALSE) -> #N/A
A12: DLBDSIPWP | B12: Introduction to Programming with Python | C12: http://data.europa.eu/esco/skill/edebd83d-35f6-4ed5-a940-6c203d178c01 | D12: 0.5 | E12: =VLOOKUP(C12,'Manual Reference Annotation'!B$6:B$9,1,FALSE) -> #N/A | F12: =VLOOKUP(E12,'Manual Reference Annotation'!B:C,2,FALSE) -> #N/A | G12: =IF(ISNA(E12),FALSE,TRUE) -> FALSE | H12: =VLOOKUP(C12,data_skills!A:B,1,FALSE) -> http://data.europa.eu/esco/skill/edebd83d-35f6-4ed5-a940-6c203d178c01 | I12: =VLOOKUP(C12,'broaderSkills wo groups'!B:F,5,FALSE) -> #N/A
A13: DLBDSIPWP | B13: Introduction to Programming with Python | C13: http://data.europa.eu/esco/skill/0c15aa34-6977-4da7-b1f0-2ba6a582ef1b | D13: 0.55 | E13: =VLOOKUP(C13,'Manual Reference Annotation'!B$6:B$9,1,FALSE) -> http://data.europa.eu/esco/skill/0c15aa34-6977-4da7-b1f0-2ba6a582ef1b | F13: =VLOOKUP(E13,'Manual Reference Annotation'!B:C,2,FALSE) -> monitor logging operations | G13: =IF(ISNA(E13),FALSE,TRUE) -> TRUE | H13: =VLOOKUP(C13,data_skills!A:B,1,FALSE) -> #N/A | I13: =VLOOKUP(C13,'broaderSkills wo groups'!B:F,5,FALSE) -> #N/A
A14: DLBDSIPWP | B14: Introduction to Programming with Python | C14: http://data.europa.eu/esco/skill/ccd0a1d9-afda-43d9-b901-96344886e14d | D14: 0.55 | E14: =VLOOKUP(C14,'Manual Reference Annotation'!B$6:B$9,1,FALSE) -> http://data.europa.eu/esco/skill/ccd0a1d9-afda-43d9-b901-96344886e14d | F14: =VLOOKUP(E14,'Manual Reference Annotation'!B:C,2,FALSE) -> Python (computer programming) | G14: =IF(ISNA(E14),FALSE,TRUE) -> TRUE | H14: =VLOOKUP(C14,data_skills!A:B,1,FALSE) -> http://data.europa.eu/esco/skill/ccd0a1d9-afda-43d9-b901-96344886e14d | I14: =VLOOKUP(C14,'broaderSkills wo groups'!B:F,5,FALSE) -> computer programming
A15: DLBDSIPWP | B15: Introduction to Programming with Python | C15: http://data.europa.eu/esco/skill/edebd83d-35f6-4ed5-a940-6c203d178c01 | D15: 0.55 | E15: =VLOOKUP(C15,'Manual Reference Annotation'!B$6:B$9,1,FALSE) -> #N/A | F15: =VLOOKUP(E15,'Manual Reference Annotation'!B:C,2,FALSE) -> #N/A | G15: =IF(ISNA(E15),FALSE,TRUE) -> FALSE | H15: =VLOOKUP(C15,data_skills!A:B,1,FALSE) -> http://data.europa.eu/esco/skill/edebd83d-35f6-4ed5-a940-6c203d178c01 | I15: =VLOOKUP(C15,'broaderSkills wo groups'!B:F,5,FALSE) -> #N/A
A16: DLBDSIPWP | B16: Introduction to Programming with Python | C16: http://data.europa.eu/esco/skill/0c15aa34-6977-4da7-b1f0-2ba6a582ef1b | D16: 0.6 | E16: =VLOOKUP(C16,'Manual Reference Annotation'!B$6:B$9,1,FALSE) -> http://data.europa.eu/esco/skill/0c15aa34-6977-4da7-b1f0-2ba6a582ef1b | F16: =VLOOKUP(E16,'Manual Reference Annotation'!B:C,2,FALSE) -> monitor logging operations | G16: =IF(ISNA(E16),FALSE,TRUE) -> TRUE | H16: =VLOOKUP(C16,data_skills!A:B,1,FALSE) -> #N/A | I16: =VLOOKUP(C16,'broaderSkills wo groups'!B:F,5,FALSE) -> #N/A
A17: DLBDSIPWP | B17: Introduction to Programming with Python | C17: http://data.europa.eu/esco/skill/edebd83d-35f6-4ed5-a940-6c203d178c01 | D17: 0.6 | E17: =VLOOKUP(C17,'Manual Reference Annotation'!B$6:B$9,1,FALSE) -> #N/A | F17: =VLOOKUP(E17,'Manual Reference Annotation'!B:C,2,FALSE) -> #N/A | G17: =IF(ISNA(E17),FALSE,TRUE) -> FALSE | H17: =VLOOKUP(C17,data_skills!A:B,1,FALSE) -> http://data.europa.eu/esco/skill/edebd83d-35f6-4ed5-a940-6c203d178c01 | I17: =VLOOKUP(C17,'broaderSkills wo groups'!B:F,5,FALSE) -> #N/A
A18: DLBIAWITT | B18: Introduction to Academic Work for IT and Technology | C18: http://data.europa.eu/esco/skill/00b9a3aa-7070-4bb5-8020-f228a97cf42f | D18: 0.5 | E18: =VLOOKUP(C18,'Manual Reference Annotation'!B$10:B$11,1,FALSE) -> #N/A | F18: =VLOOKUP(E18,'Manual Reference Annotation'!B:C,2,FALSE) -> #N/A | G18: =IF(ISNA(E18),FALSE,TRUE) -> FALSE | H18: =VLOOKUP(C18,data_skills!A:B,1,FALSE) -> http://data.europa.eu/esco/skill/00b9a3aa-7070-4bb5-8020-f228a97cf42f | I18: =VLOOKUP(C18,'broaderSkills wo groups'!B:F,5,FALSE) -> #N/A
A19: DLBIAWITT | B19: Introduction to Academic Work for IT and Technology | C19: http://data.europa.eu/esco/skill/02e22093-3436-46a8-8dc5-b041bc4800cc | D19: 0.5 | E19: =VLOOKUP(C19,'Manual Reference Annotation'!B$10:B$11,1,FALSE) -> #N/A | F19: =VLOOKUP(E19,'Manual Reference Annotation'!B:C,2,FALSE) -> #N/A | G19: =IF(ISNA(E19),FALSE,TRUE) -> FALSE | H19: =VLOOKUP(C19,data_skills!A:B,1,FALSE) -> #N/A | I19: =VLOOKUP(C19,'broaderSkills wo groups'!B:F,5,FALSE) -> #N/A
A20: DLBIAWITT | B20: Introduction to Academic Work for IT and Technology | C20: http://data.europa.eu/esco/skill/055192dc-f16c-4855-835d-19cac6ff20aa | D20: 0.5 | E20: =VLOOKUP(C20,'Manual Reference Annotation'!B$10:B$11,1,FALSE) -> #N/A | F20: =VLOOKUP(E20,'Manual Reference Annotation'!B:C,2,FALSE) -> #N/A | G20: =IF(ISNA(E20),FALSE,TRUE) -> FALSE | H20: =VLOOKUP(C20,data_skills!A:B,1,FALSE) -> http://data.europa.eu/esco/skill/055192dc-f16c-4855-835d-19cac6ff20aa | I20: =VLOOKUP(C20,'broaderSkills wo groups'!B:F,5,FALSE) -> #N/A
A21: DLBIAWITT | B21: Introduction to Academic Work for IT and Technology | C21: http://data.europa.eu/esco/skill/57b7804d-048b-4293-b8ac-a105d0468883 | D21: 0.5 | E21: =VLOOKUP(C21,'Manual Reference Annotation'!B$10:B$11,1,FALSE) -> http://data.europa.eu/esco/skill/57b7804d-048b-4293-b8ac-a105d0468883 | F21: =VLOOKUP(E21,'Manual Reference Annotation'!B:C,2,FALSE) -> source criticism | G21: =IF(ISNA(E21),FALSE,TRUE) -> TRUE | H21: =VLOOKUP(C21,data_skills!A:B,1,FALSE) -> #N/A | I21: =VLOOKUP(C21,'broaderSkills wo groups'!B:F,5,FALSE) -> #N/A
A22: DLBIAWITT | B22: Introduction to Academic Work for IT and Technology | C22: http://data.europa.eu/esco/skill/72f9d741-7696-43d2-bccb-d46f9463eecb | D22: 0.5 | E22: =VLOOKUP(C22,'Manual Reference Annotation'!B$10:B$11,1,FALSE) -> #N/A | F22: =VLOOKUP(E22,'Manual Reference Annotation'!B:C,2,FALSE) -> #N/A | G22: =IF(ISNA(E22),FALSE,TRUE) -> FALSE | H22: =VLOOKUP(C22,data_skills!A:B,1,FALSE) -> #N/A | I22: =VLOOKUP(C22,'broaderSkills wo groups'!B:F,5,FALSE) -> #N/A
A23: DLBIAWITT | B23: Introduction to Academic Work for IT and Technology | C23: http://data.europa.eu/esco/skill/7a34b3d9-bd3b-4f4e-a0f6-f97439901cb7 | D23: 0.5 | E23: =VLOOKUP(C23,'Manual Reference Annotation'!B$10:B$11,1,FALSE) -> http://data.europa.eu/esco/skill/7a34b3d9-bd3b-4f4e-a0f6-f97439901cb7 | F23: =VLOOKUP(E23,'Manual Reference Annotation'!B:C,2,FALSE) -> apply scientific methods | G23: =IF(ISNA(E23),FALSE,TRUE) -> TRUE | H23: =VLOOKUP(C23,data_skills!A:B,1,FALSE) -> http://data.europa.eu/esco/skill/7a34b3d9-bd3b-4f4e-a0f6-f97439901cb7 | I23: =VLOOKUP(C23,'broaderSkills wo groups'!B:F,5,FALSE) -> #N/A
A24: DLBIAWITT | B24: Introduction to Academic Work for IT and Technology | C24: http://data.europa.eu/esco/skill/81a2db2c-7e55-44d0-9cd9-74c25147d7cd | D24: 0.5 | E24: =VLOOKUP(C24,'Manual Reference Annotation'!B$10:B$11,1,FALSE) -> #N/A | F24: =VLOOKUP(E24,'Manual Reference Annotation'!B:C,2,FALSE) -> #N/A | G24: =IF(ISNA(E24),FALSE,TRUE) -> FALSE | H24: =VLOOKUP(C24,data_skills!A:B,1,FALSE) -> #N/A | I24: =VLOOKUP(C24,'broaderSkills wo groups'!B:F,5,FALSE) -> evaluate data, information and digital content
A25: DLBIAWITT | B25: Introduction to Academic Work for IT and Technology | C25: http://data.europa.eu/esco/skill/ddc3119d-1d6e-4324-9125-a3380d299ac5 | D25: 0.5 | E25: =VLOOKUP(C25,'Manual Reference Annotation'!B$10:B$11,1,FALSE) -> #N/A | F25: =VLOOKUP(E25,'Manual Reference Annotation'!B:C,2,FALSE) -> #N/A | G25: =IF(ISNA(E25),FALSE,TRUE) -> FALSE | H25: =VLOOKUP(C25,data_skills!A:B,1,FALSE) -> http://data.europa.eu/esco/skill/ddc3119d-1d6e-4324-9125-a3380d299ac5 | I25: =VLOOKUP(C25,'broaderSkills wo groups'!B:F,5,FALSE) -> #N/A
A26: DLBIAWITT | B26: Introduction to Academic Work for IT and Technology | C26: http://data.europa.eu/esco/skill/02e22093-3436-46a8-8dc5-b041bc4800cc | D26: 0.55 | E26: =VLOOKUP(C26,'Manual Reference Annotation'!B$10:B$11,1,FALSE) -> #N/A | F26: =VLOOKUP(E26,'Manual Reference Annotation'!B:C,2,FALSE) -> #N/A | G26: =IF(ISNA(E26),FALSE,TRUE) -> FALSE | H26: =VLOOKUP(C26,data_skills!A:B,1,FALSE) -> #N/A | I26: =VLOOKUP(C26,'broaderSkills wo groups'!B:F,5,FALSE) -> #N/A
A27: DLBIAWITT | B27: Introduction to Academic Work for IT and Technology | C27: http://data.europa.eu/esco/skill/055192dc-f16c-4855-835d-19cac6ff20aa | D27: 0.55 | E27: =VLOOKUP(C27,'Manual Reference Annotation'!B$10:B$11,1,FALSE) -> #N/A | F27: =VLOOKUP(E27,'Manual Reference Annotation'!B:C,2,FALSE) -> #N/A | G27: =IF(ISNA(E27),FALSE,TRUE) -> FALSE | H27: =VLOOKUP(C27,data_skills!A:B,1,FALSE) -> http://data.europa.eu/esco/skill/055192dc-f16c-4855-835d-19cac6ff20aa | I27: =VLOOKUP(C27,'broaderSkills wo groups'!B:F,5,FALSE) -> #N/A
A28: DLBIAWITT | B28: Introduction to Academic Work for IT and Technology | C28: http://data.europa.eu/esco/skill/57b7804d-048b-4293-b8ac-a105d0468883 | D28: 0.55 | E28: =VLOOKUP(C28,'Manual Reference Annotation'!B$10:B$11,1,FALSE) -> http://data.europa.eu/esco/skill/57b7804d-048b-4293-b8ac-a105d0468883 | F28: =VLOOKUP(E28,'Manual Reference Annotation'!B:C,2,FALSE) -> source criticism | G28: =IF(ISNA(E28),FALSE,TRUE) -> TRUE | H28: =VLOOKUP(C28,data_skills!A:B,1,FALSE) -> #N/A | I28: =VLOOKUP(C28,'broaderSkills wo groups'!B:F,5,FALSE) -> #N/A
A29: DLBIAWITT | B29: Introduction to Academic Work for IT and Technology | C29: http://data.europa.eu/esco/skill/72f9d741-7696-43d2-bccb-d46f9463eecb | D29: 0.55 | E29: =VLOOKUP(C29,'Manual Reference Annotation'!B$10:B$11,1,FALSE) -> #N/A | F29: =VLOOKUP(E29,'Manual Reference Annotation'!B:C,2,FALSE) -> #N/A | G29: =IF(ISNA(E29),FALSE,TRUE) -> FALSE | H29: =VLOOKUP(C29,data_skills!A:B,1,FALSE) -> #N/A | I29: =VLOOKUP(C29,'broaderSkills wo groups'!B:F,5,FALSE) -> #N/A
... A31: DLBIAWITT | B31: Introduction to Academic Work for IT and Technology | C31: http://data.europa.eu/esco/skill/ddc3119d-1d6e-4324-9125-a3380d299ac5 | D31: 0.55 | E31: =VLOOKUP(C31,'Manual Reference Annotation'!B$10:B$11,1,FALSE) -> #N/A | F31: =VLOOKUP(E31,'Manual Reference Annotation'!B:C,2,FALSE) -> #N/A | G31: =IF(ISNA(E31),FALSE,TRUE) -> FALSE | H31: =VLOOKUP(C31,data_skills!A:B,1,FALSE) -> http://data.europa.eu/esco/skill/ddc3119d-1d6e-4324-9125-a3380d299ac5 | I31: =VLOOKUP(C31,'broaderSkills wo groups'!B:F,5,FALSE) -> #N/A
A32: DLBCSDMDS | B32: Database Modeling and Database Systems | C32: http://data.europa.eu/esco/skill/2f4f78ac-0246-4c59-907d-9fcb46f8fb77 | D32: 0.5 | E32: =VLOOKUP(C32,'Manual Reference Annotation'!B$12:B$18,1,FALSE) -> #N/A | F32: =VLOOKUP(E32,'Manual Reference Annotation'!B:C,2,FALSE) -> #N/A | G32: =IF(ISNA(E32),FALSE,TRUE) -> FALSE | H32: =VLOOKUP(C32,data_skills!A:B,1,FALSE) -> #N/A | I32: =VLOOKUP(C32,'broaderSkills wo groups'!B:F,5,FALSE) -> #N/A
A33: DLBCSDMDS | B33: Database Modeling and Database Systems | C33: http://data.europa.eu/esco/skill/3fc5a30d-d493-44ed-a2b5-ff9a50f84de3 | D33: 0.5 | E33: =VLOOKUP(C33,'Manual Reference Annotation'!B$12:B$18,1,FALSE) -> #N/A | F33: =VLOOKUP(E33,'Manual Reference Annotation'!B:C,2,FALSE) -> #N/A | G33: =IF(ISNA(E33),FALSE,TRUE) -> FALSE | H33: =VLOOKUP(C33,data_skills!A:B,1,FALSE) -> #N/A | I33: =VLOOKUP(C33,'broaderSkills wo groups'!B:F,5,FALSE) -> create solutions to problems
A34: DLBCSDMDS | B34: Database Modeling and Database Systems | C34: http://data.europa.eu/esco/skill/43ae58b9-5e56-4524-b45a-b422777a0576 | D34: 0.5 | E34: =VLOOKUP(C34,'Manual Reference Annotation'!B$12:B$18,1,FALSE) -> http://data.europa.eu/esco/skill/43ae58b9-5e56-4524-b45a-b422777a0576 | F34: =VLOOKUP(E34,'Manual Reference Annotation'!B:C,2,FALSE) -> database | G34: =IF(ISNA(E34),FALSE,TRUE) -> TRUE | H34: =VLOOKUP(C34,data_skills!A:B,1,FALSE) -> http://data.europa.eu/esco/skill/43ae58b9-5e56-4524-b45a-b422777a0576 | I34: =VLOOKUP(C34,'broaderSkills wo groups'!B:F,5,FALSE) -> #N/A
A35: DLBCSDMDS | B35: Database Modeling and Database Systems | C35: http://data.europa.eu/esco/skill/598de5b0-5b58-4ea7-8058-a4bc4d18c742 | D35: 0.5 | E35: =VLOOKUP(C35,'Manual Reference Annotation'!B$12:B$18,1,FALSE) -> http://data.europa.eu/esco/skill/598de5b0-5b58-4ea7-8058-a4bc4d18c742 | F35: =VLOOKUP(E35,'Manual Reference Annotation'!B:C,2,FALSE) -> SQL | G35: =IF(ISNA(E35),FALSE,TRUE) -> TRUE | H35: =VLOOKUP(C35,data_skills!A:B,1,FALSE) -> http://data.europa.eu/esco/skill/598de5b0-5b58-4ea7-8058-a4bc4d18c742 | I35: =VLOOKUP(C35,'broaderSkills wo groups'!B:F,5,FALSE) -> query languages
A36: DLBCSDMDS | B36: Database Modeling and Database Systems | C36: http://data.europa.eu/esco/skill/6c08403c-a5bb-4868-b8c2-b7d039c0e511 | D36: 0.5 | E36: =VLOOKUP(C36,'Manual Reference Annotation'!B$12:B$18,1,FALSE) -> http://data.europa.eu/esco/skill/6c08403c-a5bb-4868-b8c2-b7d039c0e511 | F36: =VLOOKUP(E36,'Manual Reference Annotation'!B:C,2,FALSE) -> design database scheme | G36: =IF(ISNA(E36),FALSE,TRUE) -> TRUE | H36: =VLOOKUP(C36,data_skills!A:B,1,FALSE) -> http://data.europa.eu/esco/skill/6c08403c-a5bb-4868-b8c2-b7d039c0e511 | I36: =VLOOKUP(C36,'broaderSkills wo groups'!B:F,5,FALSE) -> manage database
A37: DLBCSDMDS | B37: Database Modeling and Database Systems | C37: http://data.europa.eu/esco/skill/7369f779-4b71-4aab-8836-48b69c676eec | D37: 0.5 | E37: =VLOOKUP(C37,'Manual Reference Annotation'!B$12:B$18,1,FALSE) -> http://data.europa.eu/esco/skill/7369f779-4b71-4aab-8836-48b69c676eec | F37: =VLOOKUP(E37,'Manual Reference Annotation'!B:C,2,FALSE) -> operate relational database management system | G37: =IF(ISNA(E37),FALSE,TRUE) -> TRUE | H37: =VLOOKUP(C37,data_skills!A:B,1,FALSE) -> http://data.europa.eu/esco/skill/7369f779-4b71-4aab-8836-48b69c676eec | I37: =VLOOKUP(C37,'broaderSkills wo groups'!B:F,5,FALSE) -> #N/A
A38: DLBCSDMDS | B38: Database Modeling and Database Systems | C38: http://data.europa.eu/esco/skill/76ef6ed3-1658-4a1a-9593-204d799c6d0c | D38: 0.5 | E38: =VLOOKUP(C38,'Manual Reference Annotation'!B$12:B$18,1,FALSE) -> http://data.europa.eu/esco/skill/76ef6ed3-1658-4a1a-9593-204d799c6d0c | F38: =VLOOKUP(E38,'Manual Reference Annotation'!B:C,2,FALSE) -> NoSQL | G38: =IF(ISNA(E38),FALSE,TRUE) -> TRUE | H38: =VLOOKUP(C38,data_skills!A:B,1,FALSE) -> http://data.europa.eu/esco/skill/76ef6ed3-1658-4a1a-9593-204d799c6d0c | I38: =VLOOKUP(C38,'broaderSkills wo groups'!B:F,5,FALSE) -> database management systems
A39: DLBCSDMDS | B39: Database Modeling and Database Systems | C39: http://data.europa.eu/esco/skill/787cc6d2-d3e1-4e9a-8664-787ac7f1d15b | D39: 0.5 | E39: =VLOOKUP(C39,'Manual Reference Annotation'!B$12:B$18,1,FALSE) -> #N/A | F39: =VLOOKUP(E39,'Manual Reference Annotation'!B:C,2,FALSE) -> #N/A | G39: =IF(ISNA(E39),FALSE,TRUE) -> FALSE | H39: =VLOOKUP(C39,data_skills!A:B,1,FALSE) -> #N/A | I39: =VLOOKUP(C39,'broaderSkills wo groups'!B:F,5,FALSE) -> #N/A
A40: DLBCSDMDS | B40: Database Modeling and Database Systems | C40: http://data.europa.eu/esco/skill/84f58e3d-8669-4d83-8c1d-5dd1e73a654f | D40: 0.5 | E40: =VLOOKUP(C40,'Manual Reference Annotation'!B$12:B$18,1,FALSE) -> #N/A | F40: =VLOOKUP(E40,'Manual Reference Annotation'!B:C,2,FALSE) -> #N/A | G40: =IF(ISNA(E40),FALSE,TRUE) -> FALSE | H40: =VLOOKUP(C40,data_skills!A:B,1,FALSE) -> http://data.europa.eu/esco/skill/84f58e3d-8669-4d83-8c1d-5dd1e73a654f | I40: =VLOOKUP(C40,'broaderSkills wo groups'!B:F,5,FALSE) -> manage database
A41: DLBCSDMDS | B41: Database Modeling and Database Systems | C41: http://data.europa.eu/esco/skill/b87f6102-5bab-4e99-a5d8-11b6be1b99c2 | D41: 0.5 | E41: =VLOOKUP(C41,'Manual Reference Annotation'!B$12:B$18,1,FALSE) -> #N/A | F41: =VLOOKUP(E41,'Manual Reference Annotation'!B:C,2,FALSE) -> #N/A | G41: =IF(ISNA(E41),FALSE,TRUE) -> FALSE | H41: =VLOOKUP(C41,data_skills!A:B,1,FALSE) -> #N/A | I41: =VLOOKUP(C41,'broaderSkills wo groups'!B:F,5,FALSE) -> report facts
A42: DLBCSDMDS | B42: Database Modeling and Database Systems | C42: http://data.europa.eu/esco/skill/cb5cccc9-abe4-4b11-abe6-d27e5cd85fb1 | D42: 0.5 | E42: =VLOOKUP(C42,'Manual Reference Annotation'!B$12:B$18,1,FALSE) -> http://data.europa.eu/esco/skill/cb5cccc9-abe4-4b11-abe6-d27e5cd85fb1 | F42: =VLOOKUP(E42,'Manual Reference Annotation'!B:C,2,FALSE) -> manage standards for data exchange | G42: =IF(ISNA(E42),FALSE,TRUE) -> TRUE | H42: =VLOOKUP(C42,data_skills!A:B,1,FALSE) -> http://data.europa.eu/esco/skill/cb5cccc9-abe4-4b11-abe6-d27e5cd85fb1 | I42: =VLOOKUP(C42,'broaderSkills wo groups'!B:F,5,FALSE) -> #N/A
A43: DLBCSDMDS | B43: Database Modeling and Database Systems | C43: http://data.europa.eu/esco/skill/fecf8a0d-62c4-4e71-9b03-0f4fc2ad7bf5 | D43: 0.5 | E43: =VLOOKUP(C43,'Manual Reference Annotation'!B$12:B$18,1,FALSE) -> http://data.europa.eu/esco/skill/fecf8a0d-62c4-4e71-9b03-0f4fc2ad7bf5 | F43: =VLOOKUP(E43,'Manual Reference Annotation'!B:C,2,FALSE) -> data models | G43: =IF(ISNA(E43),FALSE,TRUE) -> TRUE | H43: =VLOOKUP(C43,data_skills!A:B,1,FALSE) -> http://data.europa.eu/esco/skill/fecf8a0d-62c4-4e71-9b03-0f4fc2ad7bf5 | I43: =VLOOKUP(C43,'broaderSkills wo groups'!B:F,5,FALSE) -> #N/A
... A58: DLBCSDMDS | B58: Database Modeling and Database Systems | C58: http://data.europa.eu/esco/skill/fecf8a0d-62c4-4e71-9b03-0f4fc2ad7bf5 | D58: 0.65 | E58: =VLOOKUP(C58,'Manual Reference Annotation'!B$12:B$18,1,FALSE) -> http://data.europa.eu/esco/skill/fecf8a0d-62c4-4e71-9b03-0f4fc2ad7bf5 | F58: =VLOOKUP(E58,'Manual Reference Annotation'!B:C,2,FALSE) -> data models | G58: =IF(ISNA(E58),FALSE,TRUE) -> TRUE | H58: =VLOOKUP(C58,data_skills!A:B,1,FALSE) -> http://data.europa.eu/esco/skill/fecf8a0d-62c4-4e71-9b03-0f4fc2ad7bf5 | I58: =VLOOKUP(C58,'broaderSkills wo groups'!B:F,5,FALSE) -> #N/A
A59: DLBDSPBDM | B59: Project: Build a Data Mart in SQL | C59: http://data.europa.eu/esco/skill/0d11711b-870f-4701-be93-fa175b6e4002 | D59: 0.5 | E59: =VLOOKUP(C59,'Manual Reference Annotation'!B$19:B$20,1,FALSE) -> #N/A | F59: =VLOOKUP(E59,'Manual Reference Annotation'!B:C,2,FALSE) -> #N/A | G59: =IF(ISNA(E59),FALSE,TRUE) -> FALSE | H59: =VLOOKUP(C59,data_skills!A:B,1,FALSE) -> #N/A | I59: =VLOOKUP(C59,'broaderSkills wo groups'!B:F,5,FALSE) -> promote ideas, products, services
A60: DLBDSPBDM | B60: Project: Build a Data Mart in SQL | C60: http://data.europa.eu/esco/skill/3ec2e4d6-7000-4905-bf1a-c5b1679416de | D60: 0.5 | E60: =VLOOKUP(C60,'Manual Reference Annotation'!B$19:B$20,1,FALSE) -> http://data.europa.eu/esco/skill/3ec2e4d6-7000-4905-bf1a-c5b1679416de | F60: =VLOOKUP(E60,'Manual Reference Annotation'!B:C,2,FALSE) -> data warehouse | G60: =IF(ISNA(E60),FALSE,TRUE) -> TRUE | H60: =VLOOKUP(C60,data_skills!A:B,1,FALSE) -> http://data.europa.eu/esco/skill/3ec2e4d6-7000-4905-bf1a-c5b1679416de | I60: =VLOOKUP(C60,'broaderSkills wo groups'!B:F,5,FALSE) -> #N/A
A61: DLBDSPBDM | B61: Project: Build a Data Mart in SQL | C61: http://data.europa.eu/esco/skill/b87f6102-5bab-4e99-a5d8-11b6be1b99c2 | D61: 0.5 | E61: =VLOOKUP(C61,'Manual Reference Annotation'!B$19:B$20,1,FALSE) -> #N/A | F61: =VLOOKUP(E61,'Manual Reference Annotation'!B:C,2,FALSE) -> #N/A | G61: =IF(ISNA(E61),FALSE,TRUE) -> FALSE | H61: =VLOOKUP(C61,data_skills!A:B,1,FALSE) -> #N/A | I61: =VLOOKUP(C61,'broaderSkills wo groups'!B:F,5,FALSE) -> report facts
A62: DLBDSPBDM | B62: Project: Build a Data Mart in SQL | C62: http://data.europa.eu/esco/skill/bc5deb5a-5b54-4241-b52e-68389d9a1e92 | D62: 0.5 | E62: =VLOOKUP(C62,'Manual Reference Annotation'!B$19:B$20,1,FALSE) -> #N/A | F62: =VLOOKUP(E62,'Manual Reference Annotation'!B:C,2,FALSE) -> #N/A | G62: =IF(ISNA(E62),FALSE,TRUE) -> FALSE | H62: =VLOOKUP(C62,data_skills!A:B,1,FALSE) -> #N/A | I62: =VLOOKUP(C62,'broaderSkills wo groups'!B:F,5,FALSE) -> create sketches
A63: DLBDSPBDM | B63: Project: Build a Data Mart in SQL | C63: http://data.europa.eu/esco/skill/3ec2e4d6-7000-4905-bf1a-c5b1679416de | D63: 0.55 | E63: =VLOOKUP(C63,'Manual Reference Annotation'!B$19:B$20,1,FALSE) -> http://data.europa.eu/esco/skill/3ec2e4d6-7000-4905-bf1a-c5b1679416de | F63: =VLOOKUP(E63,'Manual Reference Annotation'!B:C,2,FALSE) -> data warehouse | G63: =IF(ISNA(E63),FALSE,TRUE) -> TRUE | H63: =VLOOKUP(C63,data_skills!A:B,1,FALSE) -> http://data.europa.eu/esco/skill/3ec2e4d6-7000-4905-bf1a-c5b1679416de | I63: =VLOOKUP(C63,'broaderSkills wo groups'!B:F,5,FALSE) -> #N/A
A64: DLBDSMLSL | B64: Machine Learning - Supervised Learning | C64: http://data.europa.eu/esco/skill/3a2d5b45-56e4-4f5a-a55a-4a4a65afdc43 | D64: 0.5 | E64: =VLOOKUP(C64,'Manual Reference Annotation'!B$21:B$21,1,FALSE) -> http://data.europa.eu/esco/skill/3a2d5b45-56e4-4f5a-a55a-4a4a65afdc43 | F64: =VLOOKUP(E64,'Manual Reference Annotation'!B:C,2,FALSE) -> machine learning | G64: =IF(ISNA(E64),FALSE,TRUE) -> TRUE | H64: =VLOOKUP(C64,data_skills!A:B,1,FALSE) -> http://data.europa.eu/esco/skill/3a2d5b45-56e4-4f5a-a55a-4a4a65afdc43 | I64: =VLOOKUP(C64,'broaderSkills wo groups'!B:F,5,FALSE) -> principles of artificial intelligence
A65: DLBDSMLSL | B65: Machine Learning - Supervised Learning | C65: http://data.europa.eu/esco/skill/49812c2d-3a36-4be8-bd41-8c0be3db7c6d | D65: 0.5 | E65: =VLOOKUP(C65,'Manual Reference Annotation'!B$21:B$21,1,FALSE) -> #N/A | F65: =VLOOKUP(E65,'Manual Reference Annotation'!B:C,2,FALSE) -> #N/A | G65: =IF(ISNA(E65),FALSE,TRUE) -> FALSE | H65: =VLOOKUP(C65,data_skills!A:B,1,FALSE) -> #N/A | I65: =VLOOKUP(C65,'broaderSkills wo groups'!B:F,5,FALSE) -> #N/A
A66: DLBDSMLSL | B66: Machine Learning - Supervised Learning | C66: http://data.europa.eu/esco/skill/9983816d-cc78-4d3f-9e3c-c7baa9ebc77a | D66: 0.5 | E66: =VLOOKUP(C66,'Manual Reference Annotation'!B$21:B$21,1,FALSE) -> #N/A | F66: =VLOOKUP(E66,'Manual Reference Annotation'!B:C,2,FALSE) -> #N/A | G66: =IF(ISNA(E66),FALSE,TRUE) -> FALSE | H66: =VLOOKUP(C66,data_skills!A:B,1,FALSE) -> #N/A | I66: =VLOOKUP(C66,'broaderSkills wo groups'!B:F,5,FALSE) -> product comprehension
A67: DLBDSMLSL | B67: Machine Learning - Supervised Learning | C67: http://data.europa.eu/esco/skill/3a2d5b45-56e4-4f5a-a55a-4a4a65afdc43 | D67: 0.55 | E67: =VLOOKUP(C67,'Manual Reference Annotation'!B$21:B$21,1,FALSE) -> http://data.europa.eu/esco/skill/3a2d5b45-56e4-4f5a-a55a-4a4a65afdc43 | F67: =VLOOKUP(E67,'Manual Reference Annotation'!B:C,2,FALSE) -> machine learning | G67: =IF(ISNA(E67),FALSE,TRUE) -> TRUE | H67: =VLOOKUP(C67,data_skills!A:B,1,FALSE) -> http://data.europa.eu/esco/skill/3a2d5b45-56e4-4f5a-a55a-4a4a65afdc43 | I67: =VLOOKUP(C67,'broaderSkills wo groups'!B:F,5,FALSE) -> principles of artificial intelligence
A68: DLBCSEBI2 | B68: Project: Business Intelligence | C68: http://data.europa.eu/esco/skill/143769cb-b61e-47d8-a61e-eedfbec1016c | D68: 0.5 | E68: =VLOOKUP(C68,'Manual Reference Annotation'!B$22:B$22,1,FALSE) -> http://data.europa.eu/esco/skill/143769cb-b61e-47d8-a61e-eedfbec1016c | F68: =VLOOKUP(E68,'Manual Reference Annotation'!B:C,2,FALSE) -> business intelligence | G68: =IF(ISNA(E68),FALSE,TRUE) -> TRUE | H68: =VLOOKUP(C68,data_skills!A:B,1,FALSE) -> http://data.europa.eu/esco/skill/143769cb-b61e-47d8-a61e-eedfbec1016c | I68: =VLOOKUP(C68,'broaderSkills wo groups'!B:F,5,FALSE) -> #N/A
A69: DLBCSEBI2 | B69: Project: Business Intelligence | C69: http://data.europa.eu/esco/skill/75f650d0-9096-4b8f-bbd6-ad05ee3f6121 | D69: 0.5 | E69: =VLOOKUP(C69,'Manual Reference Annotation'!B$22:B$23,1,FALSE) -> http://data.europa.eu/esco/skill/75f650d0-9096-4b8f-bbd6-ad05ee3f6121 | F69: =VLOOKUP(E69,'Manual Reference Annotation'!B:C,2,FALSE) -> document analysis results | G69: =IF(ISNA(E69),FALSE,TRUE) -> TRUE | H69: =VLOOKUP(C69,data_skills!A:B,1,FALSE) -> #N/A | I69: =VLOOKUP(C69,'broaderSkills wo groups'!B:F,5,FALSE) -> report facts
A70: DLBCSEBI2 | B70: Project: Business Intelligence | C70: http://data.europa.eu/esco/skill/f9b52e2d-56a7-48ca-b04d-2fc6436fcd4f | D70: 0.5 | E70: =VLOOKUP(C70,'Manual Reference Annotation'!B$22:B$23,1,FALSE) -> #N/A | F70: =VLOOKUP(E70,'Manual Reference Annotation'!B:C,2,FALSE) -> #N/A | G70: =IF(ISNA(E70),FALSE,TRUE) -> FALSE | H70: =VLOOKUP(C70,data_skills!A:B,1,FALSE) -> #N/A | I70: =VLOOKUP(C70,'broaderSkills wo groups'!B:F,5,FALSE) -> design prototypes
A71: DLBCSEBI2 | B71: Project: Business Intelligence | C71: http://data.europa.eu/esco/skill/143769cb-b61e-47d8-a61e-eedfbec1016c | D71: 0.55 | E71: =VLOOKUP(C71,'Manual Reference Annotation'!B$22:B$23,1,FALSE) -> http://data.europa.eu/esco/skill/143769cb-b61e-47d8-a61e-eedfbec1016c | F71: =VLOOKUP(E71,'Manual Reference Annotation'!B:C,2,FALSE) -> business intelligence | G71: =IF(ISNA(E71),FALSE,TRUE) -> TRUE | H71: =VLOOKUP(C71,data_skills!A:B,1,FALSE) -> http://data.europa.eu/esco/skill/143769cb-b61e-47d8-a61e-eedfbec1016c | I71: =VLOOKUP(C71,'broaderSkills wo groups'!B:F,5,FALSE) -> #N/A
A72: DLBCSEBI2 | B72: Project: Business Intelligence | C72: http://data.europa.eu/esco/skill/75f650d0-9096-4b8f-bbd6-ad05ee3f6121 | D72: 0.55 | E72: =VLOOKUP(C72,'Manual Reference Annotation'!B$22:B$23,1,FALSE) -> http://data.europa.eu/esco/skill/75f650d0-9096-4b8f-bbd6-ad05ee3f6121 | F72: =VLOOKUP(E72,'Manual Reference Annotation'!B:C,2,FALSE) -> document analysis results | G72: =IF(ISNA(E72),FALSE,TRUE) -> TRUE | H72: =VLOOKUP(C72,data_skills!A:B,1,FALSE) -> #N/A | I72: =VLOOKUP(C72,'broaderSkills wo groups'!B:F,5,FALSE) -> report facts
A73: DLBCSEBI2 | B73: Project: Business Intelligence | C73: http://data.europa.eu/esco/skill/143769cb-b61e-47d8-a61e-eedfbec1016c | D73: 0.6 | E73: =VLOOKUP(C73,'Manual Reference Annotation'!B$22:B$23,1,FALSE) -> http://data.europa.eu/esco/skill/143769cb-b61e-47d8-a61e-eedfbec1016c | F73: =VLOOKUP(E73,'Manual Reference Annotation'!B:C,2,FALSE) -> business intelligence | G73: =IF(ISNA(E73),FALSE,TRUE) -> TRUE | H73: =VLOOKUP(C73,data_skills!A:B,1,FALSE) -> http://data.europa.eu/esco/skill/143769cb-b61e-47d8-a61e-eedfbec1016c | I73: =VLOOKUP(C73,'broaderSkills wo groups'!B:F,5,FALSE) -> #N/A
A74: DLBCSEBI2 | B74: Project: Business Intelligence | C74: http://data.europa.eu/esco/skill/75f650d0-9096-4b8f-bbd6-ad05ee3f6121 | D74: 0.6 | E74: =VLOOKUP(C74,'Manual Reference Annotation'!B$22:B$23,1,FALSE) -> http://data.europa.eu/esco/skill/75f650d0-9096-4b8f-bbd6-ad05ee3f6121 | F74: =VLOOKUP(E74,'Manual Reference Annotation'!B:C,2,FALSE) -> document analysis results | G74: =IF(ISNA(E74),FALSE,TRUE) -> TRUE | H74: =VLOOKUP(C74,data_skills!A:B,1,FALSE) -> #N/A | I74: =VLOOKUP(C74,'broaderSkills wo groups'!B:F,5,FALSE) -> report facts
A75: DLBDSBDT | B75: Big Data Technologies | C75: http://data.europa.eu/esco/skill/46ec0033-3c71-415e-bcff-b065675ba2dc | D75: 0.5 | E75: =VLOOKUP(C75,'Manual Reference Annotation'!B$24:B$25,1,FALSE) -> http://data.europa.eu/esco/skill/46ec0033-3c71-415e-bcff-b065675ba2dc | F75: =VLOOKUP(E75,'Manual Reference Annotation'!B:C,2,FALSE) -> integrate ICT data | G75: =IF(ISNA(E75),FALSE,TRUE) -> TRUE | H75: =VLOOKUP(C75,data_skills!A:B,1,FALSE) -> http://data.europa.eu/esco/skill/46ec0033-3c71-415e-bcff-b065675ba2dc | I75: =VLOOKUP(C75,'broaderSkills wo groups'!B:F,5,FALSE) -> #N/A
A76: DLBDSBDT | B76: Big Data Technologies | C76: http://data.europa.eu/esco/skill/76ef6ed3-1658-4a1a-9593-204d799c6d0c | D76: 0.5 | E76: =VLOOKUP(C76,'Manual Reference Annotation'!B$24:B$25,1,FALSE) -> http://data.europa.eu/esco/skill/76ef6ed3-1658-4a1a-9593-204d799c6d0c | F76: =VLOOKUP(E76,'Manual Reference Annotation'!B:C,2,FALSE) -> NoSQL | G76: =IF(ISNA(E76),FALSE,TRUE) -> TRUE | H76: =VLOOKUP(C76,data_skills!A:B,1,FALSE) -> http://data.europa.eu/esco/skill/76ef6ed3-1658-4a1a-9593-204d799c6d0c | I76: =VLOOKUP(C76,'broaderSkills wo groups'!B:F,5,FALSE) -> database management systems
A77: DLBDSBDT | B77: Big Data Technologies | C77: http://data.europa.eu/esco/skill/83b493c8-4837-41e3-9800-cff1df06cf38 | D77: 0.5 | E77: =VLOOKUP(C77,'Manual Reference Annotation'!B$24:B$25,1,FALSE) -> #N/A | F77: =VLOOKUP(E77,'Manual Reference Annotation'!B:C,2,FALSE) -> #N/A | G77: =IF(ISNA(E77),FALSE,TRUE) -> FALSE | H77: =VLOOKUP(C77,data_skills!A:B,1,FALSE) -> #N/A | I77: =VLOOKUP(C77,'broaderSkills wo groups'!B:F,5,FALSE) -> #N/A
A78: DLBDSBDT | B78: Big Data Technologies | C78: http://data.europa.eu/esco/skill/9a58cd26-58eb-4a1c-b1b6-64037fe9cfa1 | D78: 0.5 | E78: =VLOOKUP(C78,'Manual Reference Annotation'!B$24:B$25,1,FALSE) -> #N/A | F78: =VLOOKUP(E78,'Manual Reference Annotation'!B:C,2,FALSE) -> #N/A | G78: =IF(ISNA(E78),FALSE,TRUE) -> FALSE | H78: =VLOOKUP(C78,data_skills!A:B,1,FALSE) -> http://data.europa.eu/esco/skill/9a58cd26-58eb-4a1c-b1b6-64037fe9cfa1 | I78: =VLOOKUP(C78,'broaderSkills wo groups'!B:F,5,FALSE) -> #N/A
A79: DLBDSBDT | B79: Big Data Technologies | C79: http://data.europa.eu/esco/skill/a8797f21-1af0-4c5e-98ca-bf1442929363 | D79: 0.5 | E79: =VLOOKUP(C79,'Manual Reference Annotation'!B$24:B$25,1,FALSE) -> #N/A | F79: =VLOOKUP(E79,'Manual Reference Annotation'!B:C,2,FALSE) -> #N/A | G79: =IF(ISNA(E79),FALSE,TRUE) -> FALSE | H79: =VLOOKUP(C79,data_skills!A:B,1,FALSE) -> http://data.europa.eu/esco/skill/a8797f21-1af0-4c5e-98ca-bf1442929363 | I79: =VLOOKUP(C79,'broaderSkills wo groups'!B:F,5,FALSE) -> use questioning techniques
A80: DLBDSBDT | B80: Big Data Technologies | C80: http://data.europa.eu/esco/skill/e2d44a9b-f28c-489e-9861-b654b5ded507 | D80: 0.5 | E80: =VLOOKUP(C80,'Manual Reference Annotation'!B$24:B$25,1,FALSE) -> #N/A | F80: =VLOOKUP(E80,'Manual Reference Annotation'!B:C,2,FALSE) -> #N/A | G80: =IF(ISNA(E80),FALSE,TRUE) -> FALSE | H80: =VLOOKUP(C80,data_skills!A:B,1,FALSE) -> #N/A | I80: =VLOOKUP(C80,'broaderSkills wo groups'!B:F,5,FALSE) -> #N/A
A81: DLBDSBDT | B81: Big Data Technologies | C81: http://data.europa.eu/esco/skill/46ec0033-3c71-415e-bcff-b065675ba2dc | D81: 0.55 | E81: =VLOOKUP(C81,'Manual Reference Annotation'!B$24:B$25,1,FALSE) -> http://data.europa.eu/esco/skill/46ec0033-3c71-415e-bcff-b065675ba2dc | F81: =VLOOKUP(E81,'Manual Reference Annotation'!B:C,2,FALSE) -> integrate ICT data | G81: =IF(ISNA(E81),FALSE,TRUE) -> TRUE | H81: =VLOOKUP(C81,data_skills!A:B,1,FALSE) -> http://data.europa.eu/esco/skill/46ec0033-3c71-415e-bcff-b065675ba2dc | I81: =VLOOKUP(C81,'broaderSkills wo groups'!B:F,5,FALSE) -> #N/A
A82: DLBDSBDT | B82: Big Data Technologies | C82: http://data.europa.eu/esco/skill/76ef6ed3-1658-4a1a-9593-204d799c6d0c | D82: 0.55 | E82: =VLOOKUP(C82,'Manual Reference Annotation'!B$24:B$25,1,FALSE) -> http://data.europa.eu/esco/skill/76ef6ed3-1658-4a1a-9593-204d799c6d0c | F82: =VLOOKUP(E82,'Manual Reference Annotation'!B:C,2,FALSE) -> NoSQL | G82: =IF(ISNA(E82),FALSE,TRUE) -> TRUE | H82: =VLOOKUP(C82,data_skills!A:B,1,FALSE) -> http://data.europa.eu/esco/skill/76ef6ed3-1658-4a1a-9593-204d799c6d0c | I82: =VLOOKUP(C82,'broaderSkills wo groups'!B:F,5,FALSE) -> database management systems
A83: DLBDSBDT | B83: Big Data Technologies | C83: http://data.europa.eu/esco/skill/a8797f21-1af0-4c5e-98ca-bf1442929363 | D83: 0.55 | E83: =VLOOKUP(C83,'Manual Reference Annotation'!B$24:B$25,1,FALSE) -> #N/A | F83: =VLOOKUP(E83,'Manual Reference Annotation'!B:C,2,FALSE) -> #N/A | G83: =IF(ISNA(E83),FALSE,TRUE) -> FALSE | H83: =VLOOKUP(C83,data_skills!A:B,1,FALSE) -> http://data.europa.eu/esco/skill/a8797f21-1af0-4c5e-98ca-bf1442929363 | I83: =VLOOKUP(C83,'broaderSkills wo groups'!B:F,5,FALSE) -> use questioning techniques
A84: DLBDSBDT | B84: Big Data Technologies | C84: http://data.europa.eu/esco/skill/e2d44a9b-f28c-489e-9861-b654b5ded507 | D84: 0.55 | E84: =VLOOKUP(C84,'Manual Reference Annotation'!B$24:B$25,1,FALSE) -> #N/A | F84: =VLOOKUP(E84,'Manual Reference Annotation'!B:C,2,FALSE) -> #N/A | G84: =IF(ISNA(E84),FALSE,TRUE) -> FALSE | H84: =VLOOKUP(C84,data_skills!A:B,1,FALSE) -> #N/A | I84: =VLOOKUP(C84,'broaderSkills wo groups'!B:F,5,FALSE) -> #N/A
A85: DLBDSBDT | B85: Big Data Technologies | C85: http://data.europa.eu/esco/skill/46ec0033-3c71-415e-bcff-b065675ba2dc | D85: 0.6 | E85: =VLOOKUP(C85,'Manual Reference Annotation'!B$24:B$25,1,FALSE) -> http://data.europa.eu/esco/skill/46ec0033-3c71-415e-bcff-b065675ba2dc | F85: =VLOOKUP(E85,'Manual Reference Annotation'!B:C,2,FALSE) -> integrate ICT data | G85: =IF(ISNA(E85),FALSE,TRUE) -> TRUE | H85: =VLOOKUP(C85,data_skills!A:B,1,FALSE) -> http://data.europa.eu/esco/skill/46ec0033-3c71-415e-bcff-b065675ba2dc | I85: =VLOOKUP(C85,'broaderSkills wo groups'!B:F,5,FALSE) -> #N/A
A86: DLBDSBDT | B86: Big Data Technologies | C86: http://data.europa.eu/esco/skill/76ef6ed3-1658-4a1a-9593-204d799c6d0c | D86: 0.6 | E86: =VLOOKUP(C86,'Manual Reference Annotation'!B$24:B$25,1,FALSE) -> http://data.europa.eu/esco/skill/76ef6ed3-1658-4a1a-9593-204d799c6d0c | F86: =VLOOKUP(E86,'Manual Reference Annotation'!B:C,2,FALSE) -> NoSQL | G86: =IF(ISNA(E86),FALSE,TRUE) -> TRUE | H86: =VLOOKUP(C86,data_skills!A:B,1,FALSE) -> http://data.europa.eu/esco/skill/76ef6ed3-1658-4a1a-9593-204d799c6d0c | I86: =VLOOKUP(C86,'broaderSkills wo groups'!B:F,5,FALSE) -> database management systems
... A89: DLBDSBDT | B89: Big Data Technologies | C89: http://data.europa.eu/esco/skill/a8797f21-1af0-4c5e-98ca-bf1442929363 | D89: 0.65 | E89: =VLOOKUP(C89,'Manual Reference Annotation'!B$24:B$25,1,FALSE) -> #N/A | F89: =VLOOKUP(E89,'Manual Reference Annotation'!B:C,2,FALSE) -> #N/A | G89: =IF(ISNA(E89),FALSE,TRUE) -> FALSE | H89: =VLOOKUP(C89,data_skills!A:B,1,FALSE) -> http://data.europa.eu/esco/skill/a8797f21-1af0-4c5e-98ca-bf1442929363 | I89: =VLOOKUP(C89,'broaderSkills wo groups'!B:F,5,FALSE) -> use questioning techniques
A90: DLBDSCC | B90: Cloud Computing | C90: http://data.europa.eu/esco/skill/0a52bed5-fd29-45fb-aba6-e32bccfda1c1 | D90: 0.5 | E90: =VLOOKUP(C90,'Manual Reference Annotation'!B$27:B$27,1,FALSE) -> #N/A | F90: =VLOOKUP(E90,'Manual Reference Annotation'!B:C,2,FALSE) -> #N/A | G90: =IF(ISNA(E90),FALSE,TRUE) -> FALSE | H90: =VLOOKUP(C90,data_skills!A:B,1,FALSE) -> http://data.europa.eu/esco/skill/0a52bed5-fd29-45fb-aba6-e32bccfda1c1 | I90: =VLOOKUP(C90,'broaderSkills wo groups'!B:F,5,FALSE) -> manage changes in ICT system
A91: DLBDSCC | B91: Cloud Computing | C91: http://data.europa.eu/esco/skill/3a2d5b45-56e4-4f5a-a55a-4a4a65afdc43 | D91: 0.5 | E91: =VLOOKUP(C91,'Manual Reference Annotation'!B$27:B$27,1,FALSE) -> #N/A | F91: =VLOOKUP(E91,'Manual Reference Annotation'!B:C,2,FALSE) -> #N/A | G91: =IF(ISNA(E91),FALSE,TRUE) -> FALSE | H91: =VLOOKUP(C91,data_skills!A:B,1,FALSE) -> http://data.europa.eu/esco/skill/3a2d5b45-56e4-4f5a-a55a-4a4a65afdc43 | I91: =VLOOKUP(C91,'broaderSkills wo groups'!B:F,5,FALSE) -> principles of artificial intelligence
A92: DLBDSCC | B92: Cloud Computing | C92: http://data.europa.eu/esco/skill/83218cac-3599-417e-93d2-26013cdccd98 | D92: 0.5 | E92: =VLOOKUP(C92,'Manual Reference Annotation'!B$27:B$27,1,FALSE) -> #N/A | F92: =VLOOKUP(E92,'Manual Reference Annotation'!B:C,2,FALSE) -> #N/A | G92: =IF(ISNA(E92),FALSE,TRUE) -> FALSE | H92: =VLOOKUP(C92,data_skills!A:B,1,FALSE) -> http://data.europa.eu/esco/skill/83218cac-3599-417e-93d2-26013cdccd98 | I92: =VLOOKUP(C92,'broaderSkills wo groups'!B:F,5,FALSE) -> #N/A
A93: DLBDSCC | B93: Cloud Computing | C93: http://data.europa.eu/esco/skill/bd14968e-e409-45af-b362-3495ed7b10e0 | D93: 0.5 | E93: =VLOOKUP(C93,'Manual Reference Annotation'!B$27:B$27,1,FALSE) -> http://data.europa.eu/esco/skill/bd14968e-e409-45af-b362-3495ed7b10e0 | F93: =VLOOKUP(E93,'Manual Reference Annotation'!B:C,2,FALSE) -> cloud technologies | G93: =IF(ISNA(E93),FALSE,TRUE) -> TRUE | H93: =VLOOKUP(C93,data_skills!A:B,1,FALSE) -> http://data.europa.eu/esco/skill/bd14968e-e409-45af-b362-3495ed7b10e0 | I93: =VLOOKUP(C93,'broaderSkills wo groups'!B:F,5,FALSE) -> #N/A
A94: DLBDSCC | B94: Cloud Computing | C94: http://data.europa.eu/esco/skill/edebd83d-35f6-4ed5-a940-6c203d178c01 | D94: 0.5 | E94: =VLOOKUP(C94,'Manual Reference Annotation'!B$27:B$27,1,FALSE) -> #N/A | F94: =VLOOKUP(E94,'Manual Reference Annotation'!B:C,2,FALSE) -> #N/A | G94: =IF(ISNA(E94),FALSE,TRUE) -> FALSE | H94: =VLOOKUP(C94,data_skills!A:B,1,FALSE) -> http://data.europa.eu/esco/skill/edebd83d-35f6-4ed5-a940-6c203d178c01 | I94: =VLOOKUP(C94,'broaderSkills wo groups'!B:F,5,FALSE) -> #N/A
A95: DLBDSCC | B95: Cloud Computing | C95: http://data.europa.eu/esco/skill/f4cd7802-123a-4bd5-9bfa-bf915a04e969 | D95: 0.5 | E95: =VLOOKUP(C95,'Manual Reference Annotation'!B$27:B$27,1,FALSE) -> #N/A | F95: =VLOOKUP(E95,'Manual Reference Annotation'!B:C,2,FALSE) -> #N/A | G95: =IF(ISNA(E95),FALSE,TRUE) -> FALSE | H95: =VLOOKUP(C95,data_skills!A:B,1,FALSE) -> #N/A | I95: =VLOOKUP(C95,'broaderSkills wo groups'!B:F,5,FALSE) -> #N/A
A96: DLBDSCC | B96: Cloud Computing | C96: http://data.europa.eu/esco/skill/83218cac-3599-417e-93d2-26013cdccd98 | D96: 0.55 | E96: =VLOOKUP(C96,'Manual Reference Annotation'!B$27:B$27,1,FALSE) -> #N/A | F96: =VLOOKUP(E96,'Manual Reference Annotation'!B:C,2,FALSE) -> #N/A | G96: =IF(ISNA(E96),FALSE,TRUE) -> FALSE | H96: =VLOOKUP(C96,data_skills!A:B,1,FALSE) -> http://data.europa.eu/esco/skill/83218cac-3599-417e-93d2-26013cdccd98 | I96: =VLOOKUP(C96,'broaderSkills wo groups'!B:F,5,FALSE) -> #N/A
A97: DLBDSCC | B97: Cloud Computing | C97: http://data.europa.eu/esco/skill/edebd83d-35f6-4ed5-a940-6c203d178c01 | D97: 0.55 | E97: =VLOOKUP(C97,'Manual Reference Annotation'!B$27:B$27,1,FALSE) -> #N/A | F97: =VLOOKUP(E97,'Manual Reference Annotation'!B:C,2,FALSE) -> #N/A | G97: =IF(ISNA(E97),FALSE,TRUE) -> FALSE | H97: =VLOOKUP(C97,data_skills!A:B,1,FALSE) -> http://data.europa.eu/esco/skill/edebd83d-35f6-4ed5-a940-6c203d178c01 | I97: =VLOOKUP(C97,'broaderSkills wo groups'!B:F,5,FALSE) -> #N/A
A98: DLBDSCC | B98: Cloud Computing | C98: http://data.europa.eu/esco/skill/83218cac-3599-417e-93d2-26013cdccd98 | D98: 0.6 | E98: =VLOOKUP(C98,'Manual Reference Annotation'!B$27:B$27,1,FALSE) -> #N/A | F98: =VLOOKUP(E98,'Manual Reference Annotation'!B:C,2,FALSE) -> #N/A | G98: =IF(ISNA(E98),FALSE,TRUE) -> FALSE | H98: =VLOOKUP(C98,data_skills!A:B,1,FALSE) -> http://data.europa.eu/esco/skill/83218cac-3599-417e-93d2-26013cdccd98 | I98: =VLOOKUP(C98,'broaderSkills wo groups'!B:F,5,FALSE) -> #N/A
A99: DLBDSCC | B99: Cloud Computing | C99: http://data.europa.eu/esco/skill/edebd83d-35f6-4ed5-a940-6c203d178c01 | D99: 0.6 | E99: =VLOOKUP(C99,'Manual Reference Annotation'!B$27:B$27,1,FALSE) -> #N/A | F99: =VLOOKUP(E99,'Manual Reference Annotation'!B:C,2,FALSE) -> #N/A | G99: =IF(ISNA(E99),FALSE,TRUE) -> FALSE | H99: =VLOOKUP(C99,data_skills!A:B,1,FALSE) -> http://data.europa.eu/esco/skill/edebd83d-35f6-4ed5-a940-6c203d178c01 | I99: =VLOOKUP(C99,'broaderSkills wo groups'!B:F,5,FALSE) -> #N/A
A100: DLBDSCC | B100: Cloud Computing | C100: http://data.europa.eu/esco/skill/83218cac-3599-417e-93d2-26013cdccd98 | D100: 0.65 | E100: =VLOOKUP(C100,'Manual Reference Annotation'!B$27:B$27,1,FALSE) -> #N/A | F100: =VLOOKUP(E100,'Manual Reference Annotation'!B:C,2,FALSE) -> #N/A | G100: =IF(ISNA(E100),FALSE,TRUE) -> FALSE | H100: =VLOOKUP(C100,data_skills!A:B,1,FALSE) -> http://data.europa.eu/esco/skill/83218cac-3599-417e-93d2-26013cdccd98 | I100: =VLOOKUP(C100,'broaderSkills wo groups'!B:F,5,FALSE) -> #N/A
A101: DLBDSEDAV | B101: Exploratory Data Analysis and Visualization | C101: http://data.europa.eu/esco/skill/348b74cd-49ce-4844-8bdf-ec188b497213 | D101: 0.5 | E101: =VLOOKUP(C101,'Manual Reference Annotation'!B$28:B$30,1,FALSE) -> #N/A | F101: =VLOOKUP(E101,'Manual Reference Annotation'!B:C,2,FALSE) -> #N/A | G101: =IF(ISNA(E101),FALSE,TRUE) -> FALSE | H101: =VLOOKUP(C101,data_skills!A:B,1,FALSE) -> http://data.europa.eu/esco/skill/348b74cd-49ce-4844-8bdf-ec188b497213 | I101: =VLOOKUP(C101,'broaderSkills wo groups'!B:F,5,FALSE) -> #N/A
A102: DLBDSEDAV | B102: Exploratory Data Analysis and Visualization | C102: http://data.europa.eu/esco/skill/65e58886-bd1e-4c5b-8ca5-8d9b353c8aa1 | D102: 0.5 | E102: =VLOOKUP(C102,'Manual Reference Annotation'!B$28:B$30,1,FALSE) -> http://data.europa.eu/esco/skill/65e58886-bd1e-4c5b-8ca5-8d9b353c8aa1 | F102: =VLOOKUP(E102,'Manual Reference Annotation'!B:C,2,FALSE) -> data visualisation software | G102: =IF(ISNA(E102),FALSE,TRUE) -> TRUE | H102: =VLOOKUP(C102,data_skills!A:B,1,FALSE) -> http://data.europa.eu/esco/skill/65e58886-bd1e-4c5b-8ca5-8d9b353c8aa1 | I102: =VLOOKUP(C102,'broaderSkills wo groups'!B:F,5,FALSE) -> #N/A
A103: DLBDSEDAV | B103: Exploratory Data Analysis and Visualization | C103: http://data.europa.eu/esco/skill/c3e36d05-8ae8-447f-bb2b-6f9409f85389 | D103: 0.5 | E103: =VLOOKUP(C103,'Manual Reference Annotation'!B$28:B$30,1,FALSE) -> http://data.europa.eu/esco/skill/c3e36d05-8ae8-447f-bb2b-6f9409f85389 | F103: =VLOOKUP(E103,'Manual Reference Annotation'!B:C,2,FALSE) -> deliver visual presentation of data | G103: =IF(ISNA(E103),FALSE,TRUE) -> TRUE | H103: =VLOOKUP(C103,data_skills!A:B,1,FALSE) -> http://data.europa.eu/esco/skill/c3e36d05-8ae8-447f-bb2b-6f9409f85389 | I103: =VLOOKUP(C103,'broaderSkills wo groups'!B:F,5,FALSE) -> #N/A
A104: DLBDSEDAV | B104: Exploratory Data Analysis and Visualization | C104: http://data.europa.eu/esco/skill/348b74cd-49ce-4844-8bdf-ec188b497213 | D104: 0.55 | E104: =VLOOKUP(C104,'Manual Reference Annotation'!B$28:B$30,1,FALSE) -> #N/A | F104: =VLOOKUP(E104,'Manual Reference Annotation'!B:C,2,FALSE) -> #N/A | G104: =IF(ISNA(E104),FALSE,TRUE) -> FALSE | H104: =VLOOKUP(C104,data_skills!A:B,1,FALSE) -> http://data.europa.eu/esco/skill/348b74cd-49ce-4844-8bdf-ec188b497213 | I104: =VLOOKUP(C104,'broaderSkills wo groups'!B:F,5,FALSE) -> #N/A
A105: DLBDSEDAV | B105: Exploratory Data Analysis and Visualization | C105: http://data.europa.eu/esco/skill/65e58886-bd1e-4c5b-8ca5-8d9b353c8aa1 | D105: 0.55 | E105: =VLOOKUP(C105,'Manual Reference Annotation'!B$28:B$30,1,FALSE) -> http://data.europa.eu/esco/skill/65e58886-bd1e-4c5b-8ca5-8d9b353c8aa1 | F105: =VLOOKUP(E105,'Manual Reference Annotation'!B:C,2,FALSE) -> data visualisation software | G105: =IF(ISNA(E105),FALSE,TRUE) -> TRUE | H105: =VLOOKUP(C105,data_skills!A:B,1,FALSE) -> http://data.europa.eu/esco/skill/65e58886-bd1e-4c5b-8ca5-8d9b353c8aa1 | I105: =VLOOKUP(C105,'broaderSkills wo groups'!B:F,5,FALSE) -> #N/A
A106: DLBDSEDAV | B106: Exploratory Data Analysis and Visualization | C106: http://data.europa.eu/esco/skill/c3e36d05-8ae8-447f-bb2b-6f9409f85389 | D106: 0.55 | E106: =VLOOKUP(C106,'Manual Reference Annotation'!B$28:B$30,1,FALSE) -> http://data.europa.eu/esco/skill/c3e36d05-8ae8-447f-bb2b-6f9409f85389 | F106: =VLOOKUP(E106,'Manual Reference Annotation'!B:C,2,FALSE) -> deliver visual presentation of data | G106: =IF(ISNA(E106),FALSE,TRUE) -> TRUE | H106: =VLOOKUP(C106,data_skills!A:B,1,FALSE) -> http://data.europa.eu/esco/skill/c3e36d05-8ae8-447f-bb2b-6f9409f85389 | I106: =VLOOKUP(C106,'broaderSkills wo groups'!B:F,5,FALSE) -> #N/A
A107: DLBDSEDAV | B107: Exploratory Data Analysis and Visualization | C107: http://data.europa.eu/esco/skill/348b74cd-49ce-4844-8bdf-ec188b497213 | D107: 0.6 | E107: =VLOOKUP(C107,'Manual Reference Annotation'!B$28:B$30,1,FALSE) -> #N/A | F107: =VLOOKUP(E107,'Manual Reference Annotation'!B:C,2,FALSE) -> #N/A | G107: =IF(ISNA(E107),FALSE,TRUE) -> FALSE | H107: =VLOOKUP(C107,data_skills!A:B,1,FALSE) -> http://data.europa.eu/esco/skill/348b74cd-49ce-4844-8bdf-ec188b497213 | I107: =VLOOKUP(C107,'broaderSkills wo groups'!B:F,5,FALSE) -> #N/A
A108: DLBDSEDAV | B108: Exploratory Data Analysis and Visualization | C108: http://data.europa.eu/esco/skill/65e58886-bd1e-4c5b-8ca5-8d9b353c8aa1 | D108: 0.6 | E108: =VLOOKUP(C108,'Manual Reference Annotation'!B$28:B$30,1,FALSE) -> http://data.europa.eu/esco/skill/65e58886-bd1e-4c5b-8ca5-8d9b353c8aa1 | F108: =VLOOKUP(E108,'Manual Reference Annotation'!B:C,2,FALSE) -> data visualisation software | G108: =IF(ISNA(E108),FALSE,TRUE) -> TRUE | H108: =VLOOKUP(C108,data_skills!A:B,1,FALSE) -> http://data.europa.eu/esco/skill/65e58886-bd1e-4c5b-8ca5-8d9b353c8aa1 | I108: =VLOOKUP(C108,'broaderSkills wo groups'!B:F,5,FALSE) -> #N/A

Sheet check if data related
A1: URI | B1: name | C1: data skill?
A2: http://data.europa.eu/esco/skill/0d6714c6-720e-4985-9791-5ab85d28da79 | B2: =VLOOKUP(A2,'ESCOX skill list'!A:D,4,FALSE) -> gather data | C2: =VLOOKUP(A2,data_skills!A:C,2,FALSE) -> gather data
A3: http://data.europa.eu/esco/skill/97bd1c21-66b2-4b7e-ad0f-e3cda590e378 | B3: =VLOOKUP(A3,'ESCOX skill list'!A:D,4,FALSE) -> data analytics | C3: =VLOOKUP(A3,data_skills!A:C,2,FALSE) -> data analytics
A4: http://data.europa.eu/esco/skill/edebd83d-35f6-4ed5-a940-6c203d178c01 | B4: =VLOOKUP(A4,'ESCOX skill list'!A:D,4,FALSE) -> data science | C4: =VLOOKUP(A4,data_skills!A:C,2,FALSE) -> data science
A5: http://data.europa.eu/esco/skill/0c15aa34-6977-4da7-b1f0-2ba6a582ef1b | B5: =VLOOKUP(A5,'ESCOX skill list'!A:D,4,FALSE) -> monitor logging operations | C5: =VLOOKUP(A5,data_skills!A:C,2,FALSE) -> #N/A
A6: http://data.europa.eu/esco/skill/ccd0a1d9-afda-43d9-b901-96344886e14d | B6: =VLOOKUP(A6,'ESCOX skill list'!A:D,4,FALSE) -> Python (computer programming) | C6: =VLOOKUP(A6,data_skills!A:C,2,FALSE) -> Python (computer programming)
A7: http://data.europa.eu/esco/skill/d0245e61-204f-48ca-911b-45e564732682 | B7: =VLOOKUP(A7,'ESCOX skill list'!A:D,4,FALSE) -> reconstruct program theory | C7: =VLOOKUP(A7,data_skills!A:C,2,FALSE) -> #N/A
A8: http://data.europa.eu/esco/skill/00b9a3aa-7070-4bb5-8020-f228a97cf42f | B8: =VLOOKUP(A8,'ESCOX skill list'!A:D,4,FALSE) -> draft scientific or academic papers and technical documentation | C8: =VLOOKUP(A8,data_skills!A:C,2,FALSE) -> draft scientific or academic papers and technical documentation
A9: http://data.europa.eu/esco/skill/02e22093-3436-46a8-8dc5-b041bc4800cc | B9: =VLOOKUP(A9,'ESCOX skill list'!A:D,4,FALSE) -> create model | C9: =VLOOKUP(A9,data_skills!A:C,2,FALSE) -> #N/A
A10: http://data.europa.eu/esco/skill/055192dc-f16c-4855-835d-19cac6ff20aa | B10: =VLOOKUP(A10,'ESCOX skill list'!A:D,4,FALSE) -> life sciences | C10: =VLOOKUP(A10,data_skills!A:C,2,FALSE) -> life sciences
A11: http://data.europa.eu/esco/skill/57b7804d-048b-4293-b8ac-a105d0468883 | B11: =VLOOKUP(A11,'ESCOX skill list'!A:D,4,FALSE) -> source criticism | C11: =VLOOKUP(A11,data_skills!A:C,2,FALSE) -> #N/A
A12: http://data.europa.eu/esco/skill/72f9d741-7696-43d2-bccb-d46f9463eecb | B12: =VLOOKUP(A12,'ESCOX skill list'!A:D,4,FALSE) -> classify books | C12: =VLOOKUP(A12,data_skills!A:C,2,FALSE) -> #N/A
A13: http://data.europa.eu/esco/skill/7a34b3d9-bd3b-4f4e-a0f6-f97439901cb7 | B13: =VLOOKUP(A13,'ESCOX skill list'!A:D,4,FALSE) -> apply scientific methods | C13: =VLOOKUP(A13,data_skills!A:C,2,FALSE) -> apply scientific methods
... A48: http://data.europa.eu/esco/skill/c3e36d05-8ae8-447f-bb2b-6f9409f85389 | B48: =VLOOKUP(A48,'ESCOX skill list'!A:D,4,FALSE) -> deliver visual presentation of data | C48: =VLOOKUP(A48,data_skills!A:C,2,FALSE) -> deliver visual presentation of data

Sheet broaderSkills wo groups
A1: conceptType | B1: conceptUri | C1: conceptLabel | D1: broaderType | E1: broaderUri | F1: broaderLabel
A2: KnowledgeSkillCompetence | B2: http://data.europa.eu/esco/skill/0005c151-5b5a-4a66-8aac-60e734beb1ab | C2: manage musical staff | D2: KnowledgeSkillCompetence | E2: http://data.europa.eu/esco/skill/75d8e5d9-bef3-418b-9011-01bff9f27207 | F2: lead others
A3: KnowledgeSkillCompetence | B3: http://data.europa.eu/esco/skill/0005c151-5b5a-4a66-8aac-60e734beb1ab | C3: manage musical staff | D3: KnowledgeSkillCompetence | E3: http://data.europa.eu/esco/skill/339ac029-066a-4985-9f9d-b3d7c8fea0bb | F3: manage staff
A4: KnowledgeSkillCompetence | B4: http://data.europa.eu/esco/skill/0007bdc2-dd15-4824-b7d6-416522c46f35 | C4: control compliance of railway vehicles regulations | D4: KnowledgeSkillCompetence | E4: http://data.europa.eu/esco/skill/23033c54-cc98-47dc-b972-4a8d1646754d | F4: inspect manufacture of rolling stock
A5: KnowledgeSkillCompetence | B5: http://data.europa.eu/esco/skill/000f1d3d-220f-4789-9c0a-cc742521fb02 | C5: Haskell | D5: KnowledgeSkillCompetence | E5: http://data.europa.eu/esco/skill/21d2f96d-35f7-4e3f-9745-c533d2dd6e97 | F5: computer programming
A6: KnowledgeSkillCompetence | B6: http://data.europa.eu/esco/skill/00298d97-3dc3-4086-a902-bce0a2fba831 | C6: lead police investigations | D6: KnowledgeSkillCompetence | E6: http://data.europa.eu/esco/skill/75d8e5d9-bef3-418b-9011-01bff9f27207 | F6: lead others
A7: KnowledgeSkillCompetence | B7: http://data.europa.eu/esco/skill/0037c821-2898-4919-b96e-7ed1cd89554c | C7: develop energy saving concepts | D7: KnowledgeSkillCompetence | E7: http://data.europa.eu/esco/skill/c2a0c52c-0b4b-4180-a918-92650ea3b458 | F7: think innovatively
A8: KnowledgeSkillCompetence | B8: http://data.europa.eu/esco/skill/004017c9-0337-4f5a-8077-798de9ef12e3 | C8: perform street interventions in social work | D8: KnowledgeSkillCompetence | E8: http://data.europa.eu/esco/skill/7d9bace0-63d0-4848-ac87-350a98082c12 | F8: participate actively in civic life
A9: KnowledgeSkillCompetence | B9: http://data.europa.eu/esco/skill/00506f28-e884-4496-800c-3477c67eb355 | C9: sport and exercise medicine | D9: KnowledgeSkillCompetence | E9: http://data.europa.eu/esco/skill/4d3f3068-9b6a-4f33-bfa5-a7b298bfd303 | F9: medical statistics
A10: KnowledgeSkillCompetence | B10: http://data.europa.eu/esco/skill/00506f28-e884-4496-800c-3477c67eb355 | C10: sport and exercise medicine | D10: KnowledgeSkillCompetence | E10: http://data.europa.eu/esco/skill/1236128d-9bb4-4d94-bc1e-40fd14824280 | F10: medicines
A11: KnowledgeSkillCompetence | B11: http://data.europa.eu/esco/skill/00831ebb-bac3-4bd1-8dae-2bca67be958d | C11: handle equipment while suspended | D11: KnowledgeSkillCompetence | E11: http://data.europa.eu/esco/skill/b6bdf202-524f-475d-b813-2aa9af005c37 | F11: move objects
A12: KnowledgeSkillCompetence | B12: http://data.europa.eu/esco/skill/0085e6bd-6829-4e8e-b302-842a7fe57ed9 | C12: teach housekeeping skills | D12: KnowledgeSkillCompetence | E12: http://data.europa.eu/esco/skill/699e7c26-6502-4e78-a823-3656ff5a5b8b | F12: instruct others
... A6461: KnowledgeSkillCompetence | B6461: http://data.europa.eu/esco/skill/fff5bc45-b506-4466-8977-4869079c1cb2 | C6461: coordinate construction activities | D6461: KnowledgeSkillCompetence | E6461: http://data.europa.eu/esco/skill/d7a67428-3afb-4bbd-932b-f6718ca489c5 | F6461: plan construction of houses

Sheet Module List to analyse
A1: Module Code | B1: Module Title | C1: Learning Outcomes | D1: Mandatory | E1: ESCOX skills (0.50) | F1: ESCOX n_skills (0.50) | G1: ESCOX skills (0.55) | H1: ESCOX n_skills (0.55) | I1: ESCOX skills (0.60) | J1: ESCOX n_skills (0.60) | K1: ESCOX skills (0.65) | L1: ESCOX n_skills (0.65)
A2: DLBDSIDS-01 | B2: Introduction to Data Science | C2: ▪ define data science and its relation to other fields. ▪ comprehend data science activities. ▪ recognize the origins of data and the challenges of working with data. ▪ understand how data science methods are integrated into business settings. ▪ grasp fundamental statistical concepts. ▪ appreciate the importance of machine learning in data science. | D2: Yes | E2: http://data.europa.eu/esco/skill/0d6714c6-720e-4985-9791-5ab85d28da79; http://data.europa.eu/esco/skill/97bd1c21-66b2-4b7e-ad0f-e3cda590e378; http://data.europa.eu/esco/skill/edebd83d-35f6-4ed5-a940-6c203d178c01 | F2: 3 | G2: http://data.europa.eu/esco/skill/97bd1c21-66b2-4b7e-ad0f-e3cda590e378; http://data.europa.eu/esco/skill/edebd83d-35f6-4ed5-a940-6c203d178c01 | H2: 2 | I2: http://data.europa.eu/esco/skill/97bd1c21-66b2-4b7e-ad0f-e3cda590e378; http://data.europa.eu/esco/skill/edebd83d-35f6-4ed5-a940-6c203d178c01 | J2: 2 | L2: 0
A3: DLBDSIPWP | B3: Introduction to Programming with Python | C3: ▪ use fundamental Python syntax. ▪ recollect common elementary data types. ▪ recognize foundational programming concepts and their realization in Python. ▪ understand error handling and logging. ▪ create working programs. ▪ list the most important libraries and packages for data science. | D3: Yes | E3: http://data.europa.eu/esco/skill/0c15aa34-6977-4da7-b1f0-2ba6a582ef1b; http://data.europa.eu/esco/skill/ccd0a1d9-afda-43d9-b901-96344886e14d; http://data.europa.eu/esco/skill/d0245e61-204f-48ca-911b-45e564732682; http://data.europa.eu/esco/skill/edebd83d-35f6-4ed5-a940-6c203d178c01 | F3: 4 | G3: http://data.europa.eu/esco/skill/0c15aa34-6977-4da7-b1f0-2ba6a582ef1b; http://data.europa.eu/esco/skill/ccd0a1d9-afda-43d9-b901-96344886e14d; http://data.europa.eu/esco/skill/edebd83d-35f6-4ed5-a940-6c203d178c01 | H3: 3 | I3: http://data.europa.eu/esco/skill/0c15aa34-6977-4da7-b1f0-2ba6a582ef1b; http://data.europa.eu/esco/skill/edebd83d-35f6-4ed5-a940-6c203d178c01 | J3: 2 | L3: 0
A4: DLBIAWITT | B4: Introduction to Academic Work for IT and Technology | C4: ▪ explain what science is and why science is needed (including in practice-based studies and professional practice). ▪ name and apply theories, methods, and models in IT and technology. ▪ find, analyze, and classify academic literature and types of sources. ▪ prepare academic papers independently. | D4: Yes | E4: http://data.europa.eu/esco/skill/00b9a3aa-7070-4bb5-8020-f228a97cf42f; http://data.europa.eu/esco/skill/02e22093-3436-46a8-8dc5-b041bc4800cc; http://data.europa.eu/esco/skill/055192dc-f16c-4855-835d-19cac6ff20aa; http://data.europa.eu/esco/skill/57b7804d-048b-4293-b8ac-a105d0468883; http://data.europa.eu/esco/skill/72f9d741-7696-43d2-bccb-d46f9463eecb; http://data.europa.eu/esco/skill/7a34b3d9-bd3b-4f4e-a0f6-f97439901cb7; http://data.europa.eu/esco/skill/81a2db2c-7e55-44d0-9cd9-74c25147d7cd; http://data.europa.eu/esco/skill/ddc3119d-1d6e-4324-9125-a3380d299ac5 | F4: 8 | G4: http://data.europa.eu/esco/skill/02e22093-3436-46a8-8dc5-b041bc4800cc; http://data.europa.eu/esco/skill/055192dc-f16c-4855-835d-19cac6ff20aa; http://data.europa.eu/esco/skill/57b7804d-048b-4293-b8ac-a105d0468883; http://data.europa.eu/esco/skill/72f9d741-7696-43d2-bccb-d46f9463eecb; http://data.europa.eu/esco/skill/7a34b3d9-bd3b-4f4e-a0f6-f97439901cb7; http://data.europa.eu/esco/skill/ddc3119d-1d6e-4324-9125-a3380d299ac5 | H4: 6 | J4: 0 | L4: 0
A5: DLBCSDMDS | B5: Database Modeling and Database Systems | C5: ▪ describe the basic concepts of the relational data model and distinguish them from each other. ▪ visually model data schemas. ▪ know SQL queries, read data from databases, change the data stock, and have experience in their use. ▪ design, create, and modify SQL queries and data schemas for SQL databases, and have experience using them. ▪ independently design database schemas and create database queries to solve concrete problems. ▪ know the most important NoSQL concepts and distinguish them from each other. | D5: Yes | E5: http://data.europa.eu/esco/skill/2f4f78ac-0246-4c59-907d-9fcb46f8fb77; http://data.europa.eu/esco/skill/3fc5a30d-d493-44ed-a2b5-ff9a50f84de3; http://data.europa.eu/esco/skill/43ae58b9-5e56-4524-b45a-b422777a0576; http://data.europa.eu/esco/skill/598de5b0-5b58-4ea7-8058-a4bc4d18c742; http://data.europa.eu/esco/skill/6c08403c-a5bb-4868-b8c2-b7d039c0e511; http://data.europa.eu/esco/skill/7369f779-4b71-4aab-8836-48b69c676eec; http://data.europa.eu/esco/skill/76ef6ed3-1658-4a1a-9593-204d799c6d0c; http://data.europa.eu/esco/skill/787cc6d2-d3e1-4e9a-8664-787ac7f1d15b; http://data.europa.eu/esco/skill/84f58e3d-8669-4d83-8c1d-5dd1e73a654f; http://data.europa.eu/esco/skill/b87f6102-5bab-4e99-a5d8-11b6be1b99c2; http://data.europa.eu/esco/skill/cb5cccc9-abe4-4b11-abe6-d27e5cd85fb1; http://data.europa.eu/esco/skill/fecf8a0d-62c4-4e71-9b03-0f4fc2ad7bf5 | F5: 12 | G5: http://data.europa.eu/esco/skill/43ae58b9-5e56-4524-b45a-b422777a0576; http://data.europa.eu/esco/skill/598de5b0-5b58-4ea7-8058-a4bc4d18c742; http://data.europa.eu/esco/skill/6c08403c-a5bb-4868-b8c2-b7d039c0e511; http://data.europa.eu/esco/skill/7369f779-4b71-4aab-8836-48b69c676eec; http://data.europa.eu/esco/skill/76ef6ed3-1658-4a1a-9593-204d799c6d0c; http://data.europa.eu/esco/skill/cb5cccc9-abe4-4b11-abe6-d27e5cd85fb1; http://data.europa.eu/esco/skill/fecf8a0d-62c4-4e71-9b03-0f4fc2ad7bf5 | H5: 7 | I5: http://data.europa.eu/esco/skill/43ae58b9-5e56-4524-b45a-b422777a0576; http://data.europa.eu/esco/skill/598de5b0-5b58-4ea7-8058-a4bc4d18c742; http://data.europa.eu/esco/skill/6c08403c-a5bb-4868-b8c2-b7d039c0e511; http://data.europa.eu/esco/skill/76ef6ed3-1658-4a1a-9593-204d799c6d0c; http://data.europa.eu/esco/skill/cb5cccc9-abe4-4b11-abe6-d27e5cd85fb1; http://data.europa.eu/esco/skill/fecf8a0d-62c4-4e71-9b03-0f4fc2ad7bf5 | J5: 6 | K5: http://data.europa.eu/esco/skill/43ae58b9-5e56-4524-b45a-b422777a0576; http://data.europa.eu/esco/skill/fecf8a0d-62c4-4e71-9b03-0f4fc2ad7bf5 | L5: 2
A6: DLBDSPBDM | B6: Project: Build a Data Mart in SQL | C6: ▪ transfer previously-acquired knowledge about database methods and approaches to practical use cases. ▪ design, architect, and implement a working data-mart solution. ▪ reason about design choices of and trade-offs between relevant implementation alternatives. ▪ critically evaluate said choices with respect to the stated design goal. ▪ describe and explain the resulting solution. | D6: Yes | E6: http://data.europa.eu/esco/skill/0d11711b-870f-4701-be93-fa175b6e4002; http://data.europa.eu/esco/skill/3ec2e4d6-7000-4905-bf1a-c5b1679416de; http://data.europa.eu/esco/skill/b87f6102-5bab-4e99-a5d8-11b6be1b99c2; http://data.europa.eu/esco/skill/bc5deb5a-5b54-4241-b52e-68389d9a1e92 | F6: 4 | G6: http://data.europa.eu/esco/skill/3ec2e4d6-7000-4905-bf1a-c5b1679416de | H6: 1 | J6: 0 | L6: 0
A7: DLBDSMLSL | B7: Machine Learning - Supervised Learning | C7: ▪ remember central notions and paradigms of machine learning. ▪ describe the key ideas of regression and pertaining regularization methods. ▪ know basic classification techniques. ▪ explain tree structured machine learning models. ▪ understand support vector machines and the related kernel approach. | D7: Yes | E7: http://data.europa.eu/esco/skill/3a2d5b45-56e4-4f5a-a55a-4a4a65afdc43; http://data.europa.eu/esco/skill/49812c2d-3a36-4be8-bd41-8c0be3db7c6d; http://data.europa.eu/esco/skill/9983816d-cc78-4d3f-9e3c-c7baa9ebc77a | F7: 3 | G7: http://data.europa.eu/esco/skill/3a2d5b45-56e4-4f5a-a55a-4a4a65afdc43 | H7: 1 | J7: 0 | L7: 0
A8: DLBCSEBI2 | B8: Project: Business Intelligence | C8: ▪ independently design a solution to a practical problem in the field of Business Intelligence in order to then implement a prototype and document the results. ▪ identify and explain typical problems and challenges in the design and practical implementation of small BI solutions. | D8: Yes | E8: http://data.europa.eu/esco/skill/143769cb-b61e-47d8-a61e-eedfbec1016c; http://data.europa.eu/esco/skill/75f650d0-9096-4b8f-bbd6-ad05ee3f6121; http://data.europa.eu/esco/skill/f9b52e2d-56a7-48ca-b04d-2fc6436fcd4f | F8: 3 | G8: http://data.europa.eu/esco/skill/143769cb-b61e-47d8-a61e-eedfbec1016c; http://data.europa.eu/esco/skill/75f650d0-9096-4b8f-bbd6-ad05ee3f6121 | H8: 2 | I8: http://data.europa.eu/esco/skill/143769cb-b61e-47d8-a61e-eedfbec1016c; http://data.europa.eu/esco/skill/75f650d0-9096-4b8f-bbd6-ad05ee3f6121 | J8: 2 | L8: 0
A9: DLBDSBDT | B9: Big Data Technologies | C9: ▪ name types and sources of data. ▪ understand text-based and binary data formats. ▪ analyze the requirements and constraints of distributed analysis systems. ▪ evaluate the applications of streaming frameworks. ▪ describe the motivation for NoSQL data stores and categorize pertaining established concepts. | D9: Yes | E9: http://data.europa.eu/esco/skill/46ec0033-3c71-415e-bcff-b065675ba2dc; http://data.europa.eu/esco/skill/76ef6ed3-1658-4a1a-9593-204d799c6d0c; http://data.europa.eu/esco/skill/83b493c8-4837-41e3-9800-cff1df06cf38; http://data.europa.eu/esco/skill/9a58cd26-58eb-4a1c-b1b6-64037fe9cfa1; http://data.europa.eu/esco/skill/a8797f21-1af0-4c5e-98ca-bf1442929363; http://data.europa.eu/esco/skill/e2d44a9b-f28c-489e-9861-b654b5ded507 | F9: 6 | G9: http://data.europa.eu/esco/skill/46ec0033-3c71-415e-bcff-b065675ba2dc; http://data.europa.eu/esco/skill/76ef6ed3-1658-4a1a-9593-204d799c6d0c; http://data.europa.eu/esco/skill/a8797f21-1af0-4c5e-98ca-bf1442929363; http://data.europa.eu/esco/skill/e2d44a9b-f28c-489e-9861-b654b5ded507 | H9: 4 | I9: http://data.europa.eu/esco/skill/46ec0033-3c71-415e-bcff-b065675ba2dc; http://data.europa.eu/esco/skill/76ef6ed3-1658-4a1a-9593-204d799c6d0c; http://data.europa.eu/esco/skill/a8797f21-1af0-4c5e-98ca-bf1442929363 | J9: 3 | K9: http://data.europa.eu/esco/skill/76ef6ed3-1658-4a1a-9593-204d799c6d0c; http://data.europa.eu/esco/skill/a8797f21-1af0-4c5e-98ca-bf1442929363 | L9: 2
A10: DLBDSCC | B10: Cloud Computing | C10: ▪ understand the fundamentals of cloud computing and cloud service models. ▪ recognize enabling technologies that underlie current cloud offerings. ▪ cite the principles of serverless computing. ▪ analyze characteristics of established cloud offerings. ▪ describe cloud options for data science and machine learning | D10: Yes | E10: http://data.europa.eu/esco/skill/0a52bed5-fd29-45fb-aba6-e32bccfda1c1; http://data.europa.eu/esco/skill/3a2d5b45-56e4-4f5a-a55a-4a4a65afdc43; http://data.europa.eu/esco/skill/83218cac-3599-417e-93d2-26013cdccd98; http://data.europa.eu/esco/skill/bd14968e-e409-45af-b362-3495ed7b10e0; http://data.europa.eu/esco/skill/edebd83d-35f6-4ed5-a940-6c203d178c01; http://data.europa.eu/esco/skill/f4cd7802-123a-4bd5-9bfa-bf915a04e969 | F10: 6 | G10: http://data.europa.eu/esco/skill/83218cac-3599-417e-93d2-26013cdccd98; http://data.europa.eu/esco/skill/edebd83d-35f6-4ed5-a940-6c203d178c01 | H10: 2 | I10: http://data.europa.eu/esco/skill/83218cac-3599-417e-93d2-26013cdccd98; http://data.europa.eu/esco/skill/edebd83d-35f6-4ed5-a940-6c203d178c01 | J10: 2 | K10: http://data.europa.eu/esco/skill/83218cac-3599-417e-93d2-26013cdccd98 | L10: 1
A11: DLBDSEDAV | B11: Exploratory Data Analysis and Visualization | C11: ▪ recognize foundational concepts of exploratory data analysis. ▪ cite principles of data visualization. ▪ identify well-established types of visualizations and their appropriate uses. ▪ describe visualization best practices. ▪ understand practical data visualization fundamentals in Python. ▪ use different approaches for effective visual communication of data science results. | D11: Yes | E11: http://data.europa.eu/esco/skill/348b74cd-49ce-4844-8bdf-ec188b497213; http://data.europa.eu/esco/skill/65e58886-bd1e-4c5b-8ca5-8d9b353c8aa1; http://data.europa.eu/esco/skill/c3e36d05-8ae8-447f-bb2b-6f9409f85389 | F11: 3 | G11: http://data.europa.eu/esco/skill/348b74cd-49ce-4844-8bdf-ec188b497213; http://data.europa.eu/esco/skill/65e58886-bd1e-4c5b-8ca5-8d9b353c8aa1; http://data.europa.eu/esco/skill/c3e36d05-8ae8-447f-bb2b-6f9409f85389 | H11: 3 | I11: http://data.europa.eu/esco/skill/348b74cd-49ce-4844-8bdf-ec188b497213; http://data.europa.eu/esco/skill/65e58886-bd1e-4c5b-8ca5-8d9b353c8aa1 | J11: 2 | L11: 0

Sheet All modules ESCOX thresholds
A1: Module Code | B1: Module Title | C1: Learning Outcomes | D1: Mandatory | E1: ESCOX skills (0.50) | F1: ESCOX n_skills (0.50) | G1: ESCOX skills (0.55) | H1: ESCOX n_skills (0.55) | I1: ESCOX skills (0.60) | J1: ESCOX n_skills (0.60) | K1: ESCOX skills (0.65) | L1: ESCOX n_skills (0.65)
A2: DLBDSIDS-01 | B2: Introduction to Data Science | C2: ▪ define data science and its relation to other fields. ▪ comprehend data science activities. ▪ recognize the origins of data and the challenges of working with data. ▪ understand how data science methods are integrated into business settings. ▪ grasp fundamental statistical concepts. ▪ appreciate the importance of machine learning in data science. | D2: Yes | E2: http://data.europa.eu/esco/skill/0d6714c6-720e-4985-9791-5ab85d28da79; http://data.europa.eu/esco/skill/97bd1c21-66b2-4b7e-ad0f-e3cda590e378; http://data.europa.eu/esco/skill/edebd83d-35f6-4ed5-a940-6c203d178c01 | F2: 3 | G2: http://data.europa.eu/esco/skill/97bd1c21-66b2-4b7e-ad0f-e3cda590e378; http://data.europa.eu/esco/skill/edebd83d-35f6-4ed5-a940-6c203d178c01 | H2: 2 | I2: http://data.europa.eu/esco/skill/97bd1c21-66b2-4b7e-ad0f-e3cda590e378; http://data.europa.eu/esco/skill/edebd83d-35f6-4ed5-a940-6c203d178c01 | J2: 2 | L2: 0
A3: DLBDSIPWP | B3: Introduction to Programming with Python | C3: ▪ use fundamental Python syntax. ▪ recollect common elementary data types. ▪ recognize foundational programming concepts and their realization in Python. ▪ understand error handling and logging. ▪ create working programs. ▪ list the most important libraries and packages for data science. | D3: Yes | E3: http://data.europa.eu/esco/skill/0c15aa34-6977-4da7-b1f0-2ba6a582ef1b; http://data.europa.eu/esco/skill/ccd0a1d9-afda-43d9-b901-96344886e14d; http://data.europa.eu/esco/skill/d0245e61-204f-48ca-911b-45e564732682; http://data.europa.eu/esco/skill/edebd83d-35f6-4ed5-a940-6c203d178c01 | F3: 4 | G3: http://data.europa.eu/esco/skill/0c15aa34-6977-4da7-b1f0-2ba6a582ef1b; http://data.europa.eu/esco/skill/ccd0a1d9-afda-43d9-b901-96344886e14d; http://data.europa.eu/esco/skill/edebd83d-35f6-4ed5-a940-6c203d178c01 | H3: 3 | I3: http://data.europa.eu/esco/skill/0c15aa34-6977-4da7-b1f0-2ba6a582ef1b; http://data.europa.eu/esco/skill/edebd83d-35f6-4ed5-a940-6c203d178c01 | J3: 2 | L3: 0
A4: DLBDSMFLA | B4: Mathematics: Linear Algebra | C4: ▪ explain fundamental notions in the domain of linear equation systems. ▪ exemplify properties of vectors and vector spaces. ▪ summarize characteristics of linear and affine mappings. ▪ identify important relations in analytical geometry. ▪ utilize different methods for matrix decomposition. | D4: Yes | E4: http://data.europa.eu/esco/skill/343de837-064c-4d69-8505-741f5a2296ed | F4: 1 | H4: 0 | J4: 0 | L4: 0
A5: DLBIAWITT | B5: Introduction to Academic Work for IT and Technology | C5: ▪ explain what science is and why science is needed (including in practice-based studies and professional practice). ▪ name and apply theories, methods, and models in IT and technology. ▪ find, analyze, and classify academic literature and types of sources. ▪ prepare academic papers independently. | D5: Yes | E5: http://data.europa.eu/esco/skill/00b9a3aa-7070-4bb5-8020-f228a97cf42f; http://data.europa.eu/esco/skill/02e22093-3436-46a8-8dc5-b041bc4800cc; http://data.europa.eu/esco/skill/055192dc-f16c-4855-835d-19cac6ff20aa; http://data.europa.eu/esco/skill/57b7804d-048b-4293-b8ac-a105d0468883; http://data.europa.eu/esco/skill/72f9d741-7696-43d2-bccb-d46f9463eecb; http://data.europa.eu/esco/skill/7a34b3d9-bd3b-4f4e-a0f6-f97439901cb7; http://data.europa.eu/esco/skill/81a2db2c-7e55-44d0-9cd9-74c25147d7cd; http://data.europa.eu/esco/skill/ddc3119d-1d6e-4324-9125-a3380d299ac5 | F5: 8 | G5: http://data.europa.eu/esco/skill/02e22093-3436-46a8-8dc5-b041bc4800cc; http://data.europa.eu/esco/skill/055192dc-f16c-4855-835d-19cac6ff20aa; http://data.europa.eu/esco/skill/57b7804d-048b-4293-b8ac-a105d0468883; http://data.europa.eu/esco/skill/72f9d741-7696-43d2-bccb-d46f9463eecb; http://data.europa.eu/esco/skill/7a34b3d9-bd3b-4f4e-a0f6-f97439901cb7; http://data.europa.eu/esco/skill/ddc3119d-1d6e-4324-9125-a3380d299ac5 | H5: 6 | J5: 0 | L5: 0
A6: DLBDSOOFPP | B6: Project: Object Oriented and Functional Programming with Python | C6: ▪ explain basic notions in object-oriented programming such as functions and classes. ▪ understand object-oriented programming concepts and their relation to software design and engineering. ▪ describe advanced function concepts in Python. ▪ recognize important ideas from functional programming. ▪ recall important libraries for functional programming in Python. | D6: Yes | E6: http://data.europa.eu/esco/skill/21d2f96d-35f7-4e3f-9745-c533d2dd6e97; http://data.europa.eu/esco/skill/3bddfd7c-ab6d-40c2-883d-5e97fb7640ba; http://data.europa.eu/esco/skill/5dd96c59-5955-474b-8cf5-e986a5b50f1a; http://data.europa.eu/esco/skill/ccd0a1d9-afda-43d9-b901-96344886e14d; http://data.europa.eu/esco/skill/d31fab87-2a7d-485c-b699-2901ca294b15 | F6: 5 | G6: http://data.europa.eu/esco/skill/21d2f96d-35f7-4e3f-9745-c533d2dd6e97; http://data.europa.eu/esco/skill/3bddfd7c-ab6d-40c2-883d-5e97fb7640ba; http://data.europa.eu/esco/skill/5dd96c59-5955-474b-8cf5-e986a5b50f1a; http://data.europa.eu/esco/skill/ccd0a1d9-afda-43d9-b901-96344886e14d; http://data.europa.eu/esco/skill/d31fab87-2a7d-485c-b699-2901ca294b15 | H6: 5 | I6: http://data.europa.eu/esco/skill/21d2f96d-35f7-4e3f-9745-c533d2dd6e97; http://data.europa.eu/esco/skill/3bddfd7c-ab6d-40c2-883d-5e97fb7640ba; http://data.europa.eu/esco/skill/d31fab87-2a7d-485c-b699-2901ca294b15 | J6: 3 | K6: http://data.europa.eu/esco/skill/d31fab87-2a7d-485c-b699-2901ca294b15 | L6: 1
A7: DLBDSMFC | B7: Mathematics: Analysis | C7: ▪ summarize the basic concepts of analysis. ▪ illustrate the terms "sequences" and "series". ▪ explain the concept of a function and determine the inverse function where possible. ▪ compute derivatives and integrals using the standard rules of differentiation and integration. ▪ explain the relationship between differentiation and integration. ▪ solve simple linear differential equations. | D7: Yes | E7: http://data.europa.eu/esco/skill/633a3637-2c6b-40ae-ac38-289eb2a62aa6 | F7: 1 | G7: http://data.europa.eu/esco/skill/633a3637-2c6b-40ae-ac38-289eb2a62aa6 | H7: 1 | J7: 0 | L7: 0
A8: DLBDSSPDS-01 | B8: Statistics: Probability and Descriptive Statistics | C8: ▪ define probability, random variable, and probability distribution. ▪ understand the concept of Bayesian statistics. ▪ grasp the definition of joint and marginal distributions. ▪ calculate expectation values and higher moments. ▪ comprehend important inequality equations and limit theorems. | D8: Yes | E8: http://data.europa.eu/esco/skill/b758675a-b03b-4e4b-897c-57ca14b1a3d0 | F8: 1 | G8: http://data.europa.eu/esco/skill/b758675a-b03b-4e4b-897c-57ca14b1a3d0 | H8: 1 | I8: http://data.europa.eu/esco/skill/b758675a-b03b-4e4b-897c-57ca14b1a3d0 | J8: 1 | L8: 0
A9: DLBCSDMDS | B9: Database Modeling and Database Systems | C9: ▪ describe the basic concepts of the relational data model and distinguish them from each other. ▪ visually model data schemas. ▪ know SQL queries, read data from databases, change the data stock, and have experience in their use. ▪ design, create, and modify SQL queries and data schemas for SQL databases, and have experience using them. ▪ independently design database schemas and create database queries to solve concrete problems. ▪ know the most important NoSQL concepts and distinguish them from each other. | D9: Yes | E9: http://data.europa.eu/esco/skill/2f4f78ac-0246-4c59-907d-9fcb46f8fb77; http://data.europa.eu/esco/skill/3fc5a30d-d493-44ed-a2b5-ff9a50f84de3; http://data.europa.eu/esco/skill/43ae58b9-5e56-4524-b45a-b422777a0576; http://data.europa.eu/esco/skill/598de5b0-5b58-4ea7-8058-a4bc4d18c742; http://data.europa.eu/esco/skill/6c08403c-a5bb-4868-b8c2-b7d039c0e511; http://data.europa.eu/esco/skill/7369f779-4b71-4aab-8836-48b69c676eec; http://data.europa.eu/esco/skill/76ef6ed3-1658-4a1a-9593-204d799c6d0c; http://data.europa.eu/esco/skill/787cc6d2-d3e1-4e9a-8664-787ac7f1d15b; http://data.europa.eu/esco/skill/84f58e3d-8669-4d83-8c1d-5dd1e73a654f; http://data.europa.eu/esco/skill/b87f6102-5bab-4e99-a5d8-11b6be1b99c2; http://data.europa.eu/esco/skill/cb5cccc9-abe4-4b11-abe6-d27e5cd85fb1; http://data.europa.eu/esco/skill/fecf8a0d-62c4-4e71-9b03-0f4fc2ad7bf5 | F9: 12 | G9: http://data.europa.eu/esco/skill/43ae58b9-5e56-4524-b45a-b422777a0576; http://data.europa.eu/esco/skill/598de5b0-5b58-4ea7-8058-a4bc4d18c742; http://data.europa.eu/esco/skill/6c08403c-a5bb-4868-b8c2-b7d039c0e511; http://data.europa.eu/esco/skill/7369f779-4b71-4aab-8836-48b69c676eec; http://data.europa.eu/esco/skill/76ef6ed3-1658-4a1a-9593-204d799c6d0c; http://data.europa.eu/esco/skill/cb5cccc9-abe4-4b11-abe6-d27e5cd85fb1; http://data.europa.eu/esco/skill/fecf8a0d-62c4-4e71-9b03-0f4fc2ad7bf5 | H9: 7 | I9: http://data.europa.eu/esco/skill/43ae58b9-5e56-4524-b45a-b422777a0576; http://data.europa.eu/esco/skill/598de5b0-5b58-4ea7-8058-a4bc4d18c742; http://data.europa.eu/esco/skill/6c08403c-a5bb-4868-b8c2-b7d039c0e511; http://data.europa.eu/esco/skill/76ef6ed3-1658-4a1a-9593-204d799c6d0c; http://data.europa.eu/esco/skill/cb5cccc9-abe4-4b11-abe6-d27e5cd85fb1; http://data.europa.eu/esco/skill/fecf8a0d-62c4-4e71-9b03-0f4fc2ad7bf5 | J9: 6 | K9: http://data.europa.eu/esco/skill/43ae58b9-5e56-4524-b45a-b422777a0576; http://data.europa.eu/esco/skill/fecf8a0d-62c4-4e71-9b03-0f4fc2ad7bf5 | L9: 2
A10: DLBCSIDPITS | B10: Introduction to Data Protection and Cyber Security | C10: ▪ explain the terms and concepts of IT security and know the typical procedures and techniques which exist in each area. ▪ cite the legal regulations on data protection and explain their implementation. ▪ discuss in-depth IT security management and suitable measures for implementation. ▪ use their overview knowledge of activities and strategies for IT security in software and system development. | D10: Yes | E10: http://data.europa.eu/esco/skill/097c6a36-f031-4d3e-b5c1-62d6ffcb430b; http://data.europa.eu/esco/skill/09f2f811-a3fb-4de3-a70f-6420a6935575; http://data.europa.eu/esco/skill/1fcce318-3212-487a-ac07-4941bc85060d; http://data.europa.eu/esco/skill/2a3a96a3-709e-4d60-81f6-d247d6933f13; http://data.europa.eu/esco/skill/8088750d-8388-4170-a76f-48354c469c44; http://data.europa.eu/esco/skill/fdeabe51-1d92-4770-acfe-eff9769b3d4f | F10: 6 | G10: http://data.europa.eu/esco/skill/097c6a36-f031-4d3e-b5c1-62d6ffcb430b; http://data.europa.eu/esco/skill/09f2f811-a3fb-4de3-a70f-6420a6935575; http://data.europa.eu/esco/skill/2a3a96a3-709e-4d60-81f6-d247d6933f13; http://data.europa.eu/esco/skill/8088750d-8388-4170-a76f-48354c469c44 | H10: 4 | I10: http://data.europa.eu/esco/skill/097c6a36-f031-4d3e-b5c1-62d6ffcb430b; http://data.europa.eu/esco/skill/09f2f811-a3fb-4de3-a70f-6420a6935575; http://data.europa.eu/esco/skill/2a3a96a3-709e-4d60-81f6-d247d6933f13; http://data.europa.eu/esco/skill/8088750d-8388-4170-a76f-48354c469c44 | J10: 4 | K10: http://data.europa.eu/esco/skill/097c6a36-f031-4d3e-b5c1-62d6ffcb430b; http://data.europa.eu/esco/skill/8088750d-8388-4170-a76f-48354c469c44 | L10: 2
A11: DLBDSPBDM | B11: Project: Build a Data Mart in SQL | C11: ▪ transfer previously-acquired knowledge about database methods and approaches to practical use cases. ▪ design, architect, and implement a working data-mart solution. ▪ reason about design choices of and trade-offs between relevant implementation alternatives. ▪ critically evaluate said choices with respect to the stated design goal. ▪ describe and explain the resulting solution. | D11: Yes | E11: http://data.europa.eu/esco/skill/0d11711b-870f-4701-be93-fa175b6e4002; http://data.europa.eu/esco/skill/3ec2e4d6-7000-4905-bf1a-c5b1679416de; http://data.europa.eu/esco/skill/b87f6102-5bab-4e99-a5d8-11b6be1b99c2; http://data.europa.eu/esco/skill/bc5deb5a-5b54-4241-b52e-68389d9a1e92 | F11: 4 | G11: http://data.europa.eu/esco/skill/3ec2e4d6-7000-4905-bf1a-c5b1679416de | H11: 1 | J11: 0 | L11: 0
A12: DLBDSSIS-01 | B12: Statistics - Inferential Statistics | C12: ▪ understand point estimation methods. ▪ apply maximum likelihood and ordinary least squares method to estimate parameters. ▪ comprehend the concept of statistical and systematic errors. ▪ employ error propagation methods. ▪ utilize Bayesian inference and non-parametric techniques. ▪ evaluate statistical tests. ▪ grasp the fundamentals of statistical decision theory. | D12: Yes | E12: http://data.europa.eu/esco/skill/68ef0e4d-5542-4e64-84f4-752cce5a3c22; http://data.europa.eu/esco/skill/81a2db2c-7e55-44d0-9cd9-74c25147d7cd; http://data.europa.eu/esco/skill/b758675a-b03b-4e4b-897c-57ca14b1a3d0; http://data.europa.eu/esco/skill/f36dff27-a70e-4c23-b2de-e2dffe84adbf | F12: 4 | H12: 0 | J12: 0 | L12: 0
A13: DLBDSMLSL | B13: Machine Learning - Supervised Learning | C13: ▪ remember central notions and paradigms of machine learning. ▪ describe the key ideas of regression and pertaining regularization methods. ▪ know basic classification techniques. ▪ explain tree structured machine learning models. ▪ understand support vector machines and the related kernel approach. | D13: Yes | E13: http://data.europa.eu/esco/skill/3a2d5b45-56e4-4f5a-a55a-4a4a65afdc43; http://data.europa.eu/esco/skill/49812c2d-3a36-4be8-bd41-8c0be3db7c6d; http://data.europa.eu/esco/skill/9983816d-cc78-4d3f-9e3c-c7baa9ebc77a | F13: 3 | G13: http://data.europa.eu/esco/skill/3a2d5b45-56e4-4f5a-a55a-4a4a65afdc43 | H13: 1 | J13: 0 | L13: 0
A14: DLBDSMLUSL | B14: Machine Learning - Unsupervised Learning and Fea- ture Engineering | C14: ▪ explain the notions of unsupervised learning and feature selection. ▪ recall commonly-applied clustering models. ▪ understand the concept and utility of dimensionality reduction and manifold learning. ▪ describe effective approaches to feature engineering. ▪ discuss the methods of automatic feature generation and selection. ▪ reflect on societal and sustainability implications of applying the learned skills to different use cases including ethical questions. | D14: Yes | E14: http://data.europa.eu/esco/skill/3a2d5b45-56e4-4f5a-a55a-4a4a65afdc43; http://data.europa.eu/esco/skill/3e2ab38a-4519-4bef-b762-a8bf4836a775; http://data.europa.eu/esco/skill/7d10fcb2-b368-48ab-996b-7c9fafcf68ed; http://data.europa.eu/esco/skill/e9575f7f-053a-439e-8074-f93df3334e92 | F14: 4 | G14: http://data.europa.eu/esco/skill/3a2d5b45-56e4-4f5a-a55a-4a4a65afdc43 | H14: 1 | J14: 0 | L14: 0
A15: DLBDSNNDL | B15: Neural Nets and Deep Learning | C15: ▪ understand the fundamental building blocks of neural networks. ▪ identify different network training approaches. ▪ create feed-forward neural networks. ▪ analyze network training and how to avoid overtraining. ▪ apply advanced network concepts to create convolutional and recurrent neural networks. ▪ reason about the influence of model design and data selection on model outcomes in terms of social and personal equity. | D15: Yes | E15: http://data.europa.eu/esco/skill/02e22093-3436-46a8-8dc5-b041bc4800cc; http://data.europa.eu/esco/skill/2f4cdc7e-d98d-4e6c-9811-3dc28255c7ff; http://data.europa.eu/esco/skill/9566c2fa-86d5-4746-8563-40cf64526539 | F15: 3 | H15: 0 | J15: 0 | L15: 0
A16: DLBCSEBI2 | B16: Project: Business Intelligence | C16: ▪ independently design a solution to a practical problem in the field of Business Intelligence in order to then implement a prototype and document the results. ▪ identify and explain typical problems and challenges in the design and practical implementation of small BI solutions. | D16: Yes | E16: http://data.europa.eu/esco/skill/143769cb-b61e-47d8-a61e-eedfbec1016c; http://data.europa.eu/esco/skill/75f650d0-9096-4b8f-bbd6-ad05ee3f6121; http://data.europa.eu/esco/skill/f9b52e2d-56a7-48ca-b04d-2fc6436fcd4f | F16: 3 | G16: http://data.europa.eu/esco/skill/143769cb-b61e-47d8-a61e-eedfbec1016c; http://data.europa.eu/esco/skill/75f650d0-9096-4b8f-bbd6-ad05ee3f6121 | H16: 2 | I16: http://data.europa.eu/esco/skill/143769cb-b61e-47d8-a61e-eedfbec1016c; http://data.europa.eu/esco/skill/75f650d0-9096-4b8f-bbd6-ad05ee3f6121 | J16: 2 | L16: 0
A17: DLBDSBDT | B17: Big Data Technologies | C17: ▪ name types and sources of data. ▪ understand text-based and binary data formats. ▪ analyze the requirements and constraints of distributed analysis systems. ▪ evaluate the applications of streaming frameworks. ▪ describe the motivation for NoSQL data stores and categorize pertaining established concepts. | D17: Yes | E17: http://data.europa.eu/esco/skill/46ec0033-3c71-415e-bcff-b065675ba2dc; http://data.europa.eu/esco/skill/76ef6ed3-1658-4a1a-9593-204d799c6d0c; http://data.europa.eu/esco/skill/83b493c8-4837-41e3-9800-cff1df06cf38; http://data.europa.eu/esco/skill/9a58cd26-58eb-4a1c-b1b6-64037fe9cfa1; http://data.europa.eu/esco/skill/a8797f21-1af0-4c5e-98ca-bf1442929363; http://data.europa.eu/esco/skill/e2d44a9b-f28c-489e-9861-b654b5ded507 | F17: 6 | G17: http://data.europa.eu/esco/skill/46ec0033-3c71-415e-bcff-b065675ba2dc; http://data.europa.eu/esco/skill/76ef6ed3-1658-4a1a-9593-204d799c6d0c; http://data.europa.eu/esco/skill/a8797f21-1af0-4c5e-98ca-bf1442929363; http://data.europa.eu/esco/skill/e2d44a9b-f28c-489e-9861-b654b5ded507 | H17: 4 | I17: http://data.europa.eu/esco/skill/46ec0033-3c71-415e-bcff-b065675ba2dc; http://data.europa.eu/esco/skill/76ef6ed3-1658-4a1a-9593-204d799c6d0c; http://data.europa.eu/esco/skill/a8797f21-1af0-4c5e-98ca-bf1442929363 | J17: 3 | K17: http://data.europa.eu/esco/skill/76ef6ed3-1658-4a1a-9593-204d799c6d0c; http://data.europa.eu/esco/skill/a8797f21-1af0-4c5e-98ca-bf1442929363 | L17: 2
A18: DLBDSCC | B18: Cloud Computing | C18: ▪ understand the fundamentals of cloud computing and cloud service models. ▪ recognize enabling technologies that underlie current cloud offerings. ▪ cite the principles of serverless computing. ▪ analyze characteristics of established cloud offerings. ▪ describe cloud options for data science and machine learning | D18: Yes | E18: http://data.europa.eu/esco/skill/0a52bed5-fd29-45fb-aba6-e32bccfda1c1; http://data.europa.eu/esco/skill/3a2d5b45-56e4-4f5a-a55a-4a4a65afdc43; http://data.europa.eu/esco/skill/83218cac-3599-417e-93d2-26013cdccd98; http://data.europa.eu/esco/skill/bd14968e-e409-45af-b362-3495ed7b10e0; http://data.europa.eu/esco/skill/edebd83d-35f6-4ed5-a940-6c203d178c01; http://data.europa.eu/esco/skill/f4cd7802-123a-4bd5-9bfa-bf915a04e969 | F18: 6 | G18: http://data.europa.eu/esco/skill/83218cac-3599-417e-93d2-26013cdccd98; http://data.europa.eu/esco/skill/edebd83d-35f6-4ed5-a940-6c203d178c01 | H18: 2 | I18: http://data.europa.eu/esco/skill/83218cac-3599-417e-93d2-26013cdccd98; http://data.europa.eu/esco/skill/edebd83d-35f6-4ed5-a940-6c203d178c01 | J18: 2 | K18: http://data.europa.eu/esco/skill/83218cac-3599-417e-93d2-26013cdccd98 | L18: 1
A19: DLBDSEDAV | B19: Exploratory Data Analysis and Visualization | C19: ▪ recognize foundational concepts of exploratory data analysis. ▪ cite principles of data visualization. ▪ identify well-established types of visualizations and their appropriate uses. ▪ describe visualization best practices. ▪ understand practical data visualization fundamentals in Python. ▪ use different approaches for effective visual communication of data science results. | D19: Yes | E19: http://data.europa.eu/esco/skill/348b74cd-49ce-4844-8bdf-ec188b497213; http://data.europa.eu/esco/skill/65e58886-bd1e-4c5b-8ca5-8d9b353c8aa1; http://data.europa.eu/esco/skill/c3e36d05-8ae8-447f-bb2b-6f9409f85389 | F19: 3 | G19: http://data.europa.eu/esco/skill/348b74cd-49ce-4844-8bdf-ec188b497213; http://data.europa.eu/esco/skill/65e58886-bd1e-4c5b-8ca5-8d9b353c8aa1; http://data.europa.eu/esco/skill/c3e36d05-8ae8-447f-bb2b-6f9409f85389 | H19: 3 | I19: http://data.europa.eu/esco/skill/348b74cd-49ce-4844-8bdf-ec188b497213; http://data.europa.eu/esco/skill/65e58886-bd1e-4c5b-8ca5-8d9b353c8aa1 | J19: 2 | L19: 0
A20: DLBDSSECDS | B20: Seminar: Ethical Considerations in Data Science | C20: ▪ contemplate ethical considerations in the field of data science. ▪ descibe how the application of data science methodology may have adverse ethical effects. ▪ reason about the ethical impacts of data science, both on a personal level and for society at large. ▪ explain how existing biases and inequalities could be amplified by technology. ▪ treat in a scientific manner a selected topic in the form of a written essay. | D20: Yes | E20: http://data.europa.eu/esco/skill/434fb032-3c05-45bd-aaf2-09468ee34d7f; http://data.europa.eu/esco/skill/e9575f7f-053a-439e-8074-f93df3334e92 | F20: 2 | G20: http://data.europa.eu/esco/skill/434fb032-3c05-45bd-aaf2-09468ee34d7f; http://data.europa.eu/esco/skill/e9575f7f-053a-439e-8074-f93df3334e92 | H20: 2 | I20: http://data.europa.eu/esco/skill/e9575f7f-053a-439e-8074-f93df3334e92 | J20: 1 | K20: http://data.europa.eu/esco/skill/e9575f7f-053a-439e-8074-f93df3334e92 | L20: 1
A21: DLBAIPNLP | B21: Project: NLP | C21: ▪ apply knowledge of NLP methods to practical problems. ▪ evaluate and apply different methods, algorithms, and approaches to solve a given problem, taking into account its constraints. ▪ recognize the benefits and shortcomings of options and decisions. ▪ implement real-world NLP applications. | D21: Yes | E21: http://data.europa.eu/esco/skill/2abb7341-11a9-4799-9aef-7f2a83de0358; http://data.europa.eu/esco/skill/7a34b3d9-bd3b-4f4e-a0f6-f97439901cb7; http://data.europa.eu/esco/skill/a32e7fb1-af9e-4c09-8ea7-72b7442e9cda; http://data.europa.eu/esco/skill/d62d2b4c-a6f8-439e-8a1b-4f29ab5f2c47; http://data.europa.eu/esco/skill/fff0e2cd-d0bd-4b02-9daf-158b79d9688a | F21: 5 | G21: http://data.europa.eu/esco/skill/2abb7341-11a9-4799-9aef-7f2a83de0358; http://data.europa.eu/esco/skill/d62d2b4c-a6f8-439e-8a1b-4f29ab5f2c47; http://data.europa.eu/esco/skill/fff0e2cd-d0bd-4b02-9daf-158b79d9688a | H21: 3 | I21: http://data.europa.eu/esco/skill/2abb7341-11a9-4799-9aef-7f2a83de0358; http://data.europa.eu/esco/skill/d62d2b4c-a6f8-439e-8a1b-4f29ab5f2c47 | J21: 2 | L21: 0
A22: DLBDSEDE1 | B22: Data Engineering | C22: ▪ understand important foundational concepts in data engineering. ▪ recognize established and commonly-employed NoSQL datastores and their salient characteristics. ▪ comprehend common architectural patterns for data processing at scale. ▪ explain the concept of containerization as a virtualization approach. ▪ analyze operational challenges in the set-up and maintenance of data pipelines. ▪ demonstrate familiarity with concepts relating to data security and protection. | D22: No | E22: http://data.europa.eu/esco/skill/1585fc98-bfe4-461f-97fc-734055a2c3ce; http://data.europa.eu/esco/skill/484d048c-a5d1-46a5-b57f-45b69c0ac552; http://data.europa.eu/esco/skill/48db96bf-3314-45c6-bad8-fdb6e20e5639; http://data.europa.eu/esco/skill/726abd5a-d23c-44b9-abb0-f22bbe95f1d3; http://data.europa.eu/esco/skill/76ef6ed3-1658-4a1a-9593-204d799c6d0c; http://data.europa.eu/esco/skill/8981d38b-fbc1-4ebe-9300-2357fb71913a; http://data.europa.eu/esco/skill/adcca622-b933-4ba3-bc43-bf371879edc3; http://data.europa.eu/esco/skill/ae4f0cc6-e0b9-47f5-bdca-2fc2e6316dce; http://data.europa.eu/esco/skill/eb65ce8e-61bf-49d1-99bb-cb699ba1005b; http://data.europa.eu/esco/skill/f9670490-8aa4-4540-b121-d440a8294aab | F22: 10 | G22: http://data.europa.eu/esco/skill/484d048c-a5d1-46a5-b57f-45b69c0ac552; http://data.europa.eu/esco/skill/48db96bf-3314-45c6-bad8-fdb6e20e5639; http://data.europa.eu/esco/skill/76ef6ed3-1658-4a1a-9593-204d799c6d0c; http://data.europa.eu/esco/skill/adcca622-b933-4ba3-bc43-bf371879edc3; http://data.europa.eu/esco/skill/ae4f0cc6-e0b9-47f5-bdca-2fc2e6316dce | H22: 5 | I22: http://data.europa.eu/esco/skill/484d048c-a5d1-46a5-b57f-45b69c0ac552; http://data.europa.eu/esco/skill/48db96bf-3314-45c6-bad8-fdb6e20e5639; http://data.europa.eu/esco/skill/76ef6ed3-1658-4a1a-9593-204d799c6d0c; http://data.europa.eu/esco/skill/adcca622-b933-4ba3-bc43-bf371879edc3; http://data.europa.eu/esco/skill/ae4f0cc6-e0b9-47f5-bdca-2fc2e6316dce | J22: 5 | K22: http://data.europa.eu/esco/skill/76ef6ed3-1658-4a1a-9593-204d799c6d0c; http://data.europa.eu/esco/skill/ae4f0cc6-e0b9-47f5-bdca-2fc2e6316dce | L22: 2
A23: DLBDSEDE2 | B23: Project: Data Engineering | C23: ▪ formulate and implement a real-world data engineering use case. ▪ select appropriate resources for the task at hand. ▪ transfer acquired specialized knowledge in data engineering to a real-world use case. ▪ derive relevant design choices from the given project setting. ▪ analyze the suitability of different solution options with respect to the project task. ▪ make apposite choices with respect to implementation alternatives. | D23: No | E23: http://data.europa.eu/esco/skill/32db65d3-5ef3-43eb-9bf8-752c9cf0b22e; http://data.europa.eu/esco/skill/48db96bf-3314-45c6-bad8-fdb6e20e5639; http://data.europa.eu/esco/skill/5cede168-97f8-47a4-89fd-8f7188c55c5d; http://data.europa.eu/esco/skill/64ebb116-acb3-44f9-ac6d-9a464e57fb64 | F23: 4 | G23: http://data.europa.eu/esco/skill/32db65d3-5ef3-43eb-9bf8-752c9cf0b22e; http://data.europa.eu/esco/skill/5cede168-97f8-47a4-89fd-8f7188c55c5d | H23: 2 | J23: 0 | L23: 0
A24: DLBDSEDA1 | B24: Advanced Data Analysis | C24: ▪ identify important design considerations for business KPIs. ▪ explain various topics in business process analytics. ▪ utilize established techniques for web data analytics. ▪ understand analytical approaches to text mining and semantic analysis. ▪ disambiguate relevant questions in social media analytics. ▪ use the techniques and methods for experimentation and testing. | D24: No | E24: http://data.europa.eu/esco/skill/0f2eee6f-2203-4cc8-9d79-854d2d5d8131; http://data.europa.eu/esco/skill/1605025e-a179-421f-8f35-5b07d182a6b2; http://data.europa.eu/esco/skill/25f0ea33-b4a2-4f31-b7b4-7d20e827b180; http://data.europa.eu/esco/skill/7a34b3d9-bd3b-4f4e-a0f6-f97439901cb7; http://data.europa.eu/esco/skill/913e7e83-b8f8-4574-b1ca-1b38f3fd974a; http://data.europa.eu/esco/skill/9e84a506-df06-4be3-874a-fa01293e3dd5; http://data.europa.eu/esco/skill/be20d05c-f6b4-4580-9fcf-f00f4baab562; http://data.europa.eu/esco/skill/e6ee5bb8-12b9-4e60-8baf-102d0c4f1da5 | F24: 8 | G24: http://data.europa.eu/esco/skill/0f2eee6f-2203-4cc8-9d79-854d2d5d8131; http://data.europa.eu/esco/skill/1605025e-a179-421f-8f35-5b07d182a6b2; http://data.europa.eu/esco/skill/9e84a506-df06-4be3-874a-fa01293e3dd5; http://data.europa.eu/esco/skill/be20d05c-f6b4-4580-9fcf-f00f4baab562; http://data.europa.eu/esco/skill/e6ee5bb8-12b9-4e60-8baf-102d0c4f1da5 | H24: 5 | I24: http://data.europa.eu/esco/skill/1605025e-a179-421f-8f35-5b07d182a6b2; http://data.europa.eu/esco/skill/9e84a506-df06-4be3-874a-fa01293e3dd5; http://data.europa.eu/esco/skill/be20d05c-f6b4-4580-9fcf-f00f4baab562 | J24: 3 | K24: http://data.europa.eu/esco/skill/1605025e-a179-421f-8f35-5b07d182a6b2; http://data.europa.eu/esco/skill/9e84a506-df06-4be3-874a-fa01293e3dd5 | L24: 2
A25: DLBDSEDA2 | B25: Project: Data Analysis | C25: ▪ formulate and implement a real-world analytical use case. ▪ analyze the suitability of different possible approaches with respect to the project task. ▪ transfer acquired specialized analytical knowledge to real-world use cases. ▪ derive relevant design choices from the given project setting. ▪ make apposite choices with respect to implementation alternatives. ▪ select appropriate resources | D25: No | E25: http://data.europa.eu/esco/skill/32db65d3-5ef3-43eb-9bf8-752c9cf0b22e; http://data.europa.eu/esco/skill/5cede168-97f8-47a4-89fd-8f7188c55c5d; http://data.europa.eu/esco/skill/64ebb116-acb3-44f9-ac6d-9a464e57fb64 | F25: 3 | G25: http://data.europa.eu/esco/skill/32db65d3-5ef3-43eb-9bf8-752c9cf0b22e; http://data.europa.eu/esco/skill/5cede168-97f8-47a4-89fd-8f7188c55c5d | H25: 2 | I25: http://data.europa.eu/esco/skill/32db65d3-5ef3-43eb-9bf8-752c9cf0b22e | J25: 1 | K25: http://data.europa.eu/esco/skill/32db65d3-5ef3-43eb-9bf8-752c9cf0b22e | L25: 1
A26: DLBDSEAIS1 | B26: Artificial Intelligence | C26: ▪ chart the historical developments in artificial intelligence. ▪ understand the approach of contemporary AI systems. ▪ comprehend the concepts behind reinforcement learning. ▪ analyze natural language using basic NLP techniques. ▪ scrutinize images and their contents. | D26: No | E26: http://data.europa.eu/esco/skill/1482a7a4-6f76-47f3-9831-177cd59c6621; http://data.europa.eu/esco/skill/e465a154-93f7-4973-9ce1-31659fe16dd2; http://data.europa.eu/esco/skill/fff0e2cd-d0bd-4b02-9daf-158b79d9688a | F26: 3 | G26: http://data.europa.eu/esco/skill/fff0e2cd-d0bd-4b02-9daf-158b79d9688a | H26: 1 | I26: http://data.europa.eu/esco/skill/fff0e2cd-d0bd-4b02-9daf-158b79d9688a | J26: 1 | L26: 0
A27: DLBDSEAIS2 | B27: Project: Artificial Intelligence | C27: ▪ determine the requirements for building an artificial intelligence system. ▪ evaluate an application for an AI system. ▪ transfer theoretically-sound and practically-proven methods and tools to an application domain. ▪ create an AI system for a chosen application. | D27: No | E27: http://data.europa.eu/esco/skill/5608d5a0-6d5e-43b7-be37-616501729bb4; http://data.europa.eu/esco/skill/70c573a8-de56-45cc-ae69-0a1073eef2b3; http://data.europa.eu/esco/skill/edd6a6bc-139c-45de-8f1a-d0ea353f45ab; http://data.europa.eu/esco/skill/fc0fbc9c-b24d-42fa-ae66-c9b4945b6bc0; http://data.europa.eu/esco/skill/fdf15b35-9028-4acb-bfd2-43f00a015cd9 | F27: 5 | G27: http://data.europa.eu/esco/skill/70c573a8-de56-45cc-ae69-0a1073eef2b3 | H27: 1 | J27: 0 | L27: 0
A28: DLBDSTSA | B28: Time Series Analysis | C28: ▪ identify the fundamental concepts of time series analysis. ▪ cite the components of time series. ▪ create simple time series models. ▪ analyze time series data with ARMA and Holt-Winter models. ▪ understand advanced topics in time series analysis. | D28: No | F28: 0 | H28: 0 | J28: 0 | L28: 0
A29: DLBPKIEKPT1_E | B29: Project: AI Excellence with Creative Prompting Techniques | C29: ▪ comprehend and apply basic prompting techniques in generative AI applications. ▪ analyze and evaluate the effectiveness of the basic prompts. ▪ apply ethical considerations to the design and use of AI for basic prompting techniques. ▪ design, implement, and refine effective prompts to real-world scenarios through hands-on exercises. ▪ showcase creative and innovative thinking in the application of prompting techniques to solve complex problems in their field of studies | D29: No | E29: http://data.europa.eu/esco/skill/31c69100-b612-4a61-8db5-fd314318854c; http://data.europa.eu/esco/skill/958559fd-7ab8-44f6-9d65-eb521dc308a5; http://data.europa.eu/esco/skill/a254408b-b8f0-4b56-8d88-777bfab7f517; http://data.europa.eu/esco/skill/b87f6102-5bab-4e99-a5d8-11b6be1b99c2; http://data.europa.eu/esco/skill/c2a0c52c-0b4b-4180-a918-92650ea3b458; http://data.europa.eu/esco/skill/e0ab7e9a-4f38-4077-bf5f-a65ec483d5ce; http://data.europa.eu/esco/skill/e44a0396-77e2-4d57-8c80-36796238f80c; http://data.europa.eu/esco/skill/e927ab40-a135-4a7a-9dfc-b57132741281 | F29: 8 | G29: http://data.europa.eu/esco/skill/958559fd-7ab8-44f6-9d65-eb521dc308a5; http://data.europa.eu/esco/skill/c2a0c52c-0b4b-4180-a918-92650ea3b458; http://data.europa.eu/esco/skill/e927ab40-a135-4a7a-9dfc-b57132741281 | H29: 3 | I29: http://data.europa.eu/esco/skill/c2a0c52c-0b4b-4180-a918-92650ea3b458 | J29: 1 | K29: http://data.europa.eu/esco/skill/c2a0c52c-0b4b-4180-a918-92650ea3b458 | L29: 1
A30: DLBDSESF1 | B30: Smart Factory | C30: ▪ understand the term Smart Factory in the context of Industry 4.0. ▪ be able to trace the development of automation to a fully autonomous, non-centrally organized production plant. ▪ understand the basic technologies and standards used to design and operate a Smart Factory. ▪ understand the essential concepts of a Smart Factory. ▪ identify and differentiate between the individual elements of a Smart Factory using different reference architectures. ▪ understand the special engineering challenges in the Smart Energy context. ▪ understand the special safety risks of digitized and networked production plants and assign concrete recommendations for action. | D30: No | E30: http://data.europa.eu/esco/skill/128f0b4c-8da7-467b-9196-7c691e067a1e; http://data.europa.eu/esco/skill/2450c3b3-e78e-435b-b84d-e05d984e71dc; http://data.europa.eu/esco/skill/42cb7669-c371-4903-9c0b-13db67b2e4bb; http://data.europa.eu/esco/skill/ec66a2f9-db12-4eec-936a-47632bfdccfb; http://data.europa.eu/esco/skill/f4a6e9f7-5cff-46c0-894c-59c20bb78694 | F30: 5 | G30: http://data.europa.eu/esco/skill/128f0b4c-8da7-467b-9196-7c691e067a1e | H30: 1 | J30: 0 | L30: 0
A31: DLBDSEAR1 | B31: Production Engineering Industry 4.0 | C31: ▪ understand the basic concepts and interrelationships of production engineering. ▪ understand current changes in manufacturing technology due to technologies such as additive manufacturing and megatrends such as cyber physical systems. ▪ assign different manufacturing processes to the main manufacturing groups according to DIN 8580. ▪ understand the basic principle of additive manufacturing processes. ▪ distinguish between different additive manufacturing processes. ▪ understand the terms Rapid Prototyping, Rapid Tooling, and Direct Manufacturing and name individual processes and application examples. ▪ understand the elements and properties of cyber-physical production plants. | D31: No | E31: http://data.europa.eu/esco/skill/05c00631-b864-4842-b47e-06710c197c7a; http://data.europa.eu/esco/skill/0ba0717c-3a7a-45a3-834c-59c554e56c72; http://data.europa.eu/esco/skill/12d2c08a-3b23-4b15-8aae-15e675f60182; http://data.europa.eu/esco/skill/3a699f1e-3803-4c1b-b6a8-6230cca92933; http://data.europa.eu/esco/skill/4fb87cb4-6442-4b5d-8bd0-eb1aa743a9ee; http://data.europa.eu/esco/skill/6078e099-7696-44a5-b3c1-452b9abe886a; http://data.europa.eu/esco/skill/ed1d8bd4-cd2a-4c64-b665-56d70651026c; http://data.europa.eu/esco/skill/f266380e-9830-44db-8f93-60a6e8b9a1b6; http://data.europa.eu/esco/skill/feceacee-d425-4e73-821a-02dfb85084db | F31: 9 | G31: http://data.europa.eu/esco/skill/05c00631-b864-4842-b47e-06710c197c7a; http://data.europa.eu/esco/skill/12d2c08a-3b23-4b15-8aae-15e675f60182; http://data.europa.eu/esco/skill/3a699f1e-3803-4c1b-b6a8-6230cca92933; http://data.europa.eu/esco/skill/6078e099-7696-44a5-b3c1-452b9abe886a; http://data.europa.eu/esco/skill/ed1d8bd4-cd2a-4c64-b665-56d70651026c; http://data.europa.eu/esco/skill/feceacee-d425-4e73-821a-02dfb85084db | H31: 6 | I31: http://data.europa.eu/esco/skill/05c00631-b864-4842-b47e-06710c197c7a; http://data.europa.eu/esco/skill/3a699f1e-3803-4c1b-b6a8-6230cca92933; http://data.europa.eu/esco/skill/6078e099-7696-44a5-b3c1-452b9abe886a; http://data.europa.eu/esco/skill/ed1d8bd4-cd2a-4c64-b665-56d70651026c | J31: 4 | K31: http://data.europa.eu/esco/skill/05c00631-b864-4842-b47e-06710c197c7a; http://data.europa.eu/esco/skill/3a699f1e-3803-4c1b-b6a8-6230cca92933; http://data.europa.eu/esco/skill/6078e099-7696-44a5-b3c1-452b9abe886a; http://data.europa.eu/esco/skill/ed1d8bd4-cd2a-4c64-b665-56d70651026c | L31: 4
A32: DLBDSEAR2 | B32: Automation and Robotics | C32: ▪ understand the basic aspects of automation. ▪ understand the different sizes and units in measurement technology. ▪ differentiate between different measurement methods. ▪ understand the basic structure of measuring equipment. ▪ select a suitable sensor based on various criteria. ▪ understand the elements of control systems. ▪ describe the behavior of control systems in the time and frequency domain. ▪ understand the basic principles of control technology. ▪ convert between different number systems and apply Boolean algebra. ▪ understand the structure of switching networks, plants, and storages. ▪ understand important elements of control systems such as signal generators and power amplifiers. ▪ design simple programmable logic controllers. ▪ understand the basic structure of industrial robots. ▪ calculate different movements and positions of jointed-arm robots. | D32: No | E32: http://data.europa.eu/esco/skill/3c42d13b-d6e4-4ed9-bdc4-991251461dc4; http://data.europa.eu/esco/skill/56a46b02-ab98-4603-8816-c9daff1a119a; http://data.europa.eu/esco/skill/7b3717e4-e963-44e0-b94f-1088a7242da0; http://data.europa.eu/esco/skill/7ffae77a-93ce-40a3-af99-fae5729e8b15; http://data.europa.eu/esco/skill/940d02e8-0199-4b5b-bba4-19547aa9b498; http://data.europa.eu/esco/skill/a181e89d-44ae-40e7-8d37-177071237c74; http://data.europa.eu/esco/skill/f4a6e9f7-5cff-46c0-894c-59c20bb78694 | F32: 7 | G32: http://data.europa.eu/esco/skill/3c42d13b-d6e4-4ed9-bdc4-991251461dc4; http://data.europa.eu/esco/skill/7ffae77a-93ce-40a3-af99-fae5729e8b15; http://data.europa.eu/esco/skill/940d02e8-0199-4b5b-bba4-19547aa9b498; http://data.europa.eu/esco/skill/a181e89d-44ae-40e7-8d37-177071237c74; http://data.europa.eu/esco/skill/f4a6e9f7-5cff-46c0-894c-59c20bb78694 | H32: 5 | I32: http://data.europa.eu/esco/skill/940d02e8-0199-4b5b-bba4-19547aa9b498; http://data.europa.eu/esco/skill/a181e89d-44ae-40e7-8d37-177071237c74; http://data.europa.eu/esco/skill/f4a6e9f7-5cff-46c0-894c-59c20bb78694 | J32: 3 | K32: http://data.europa.eu/esco/skill/940d02e8-0199-4b5b-bba4-19547aa9b498; http://data.europa.eu/esco/skill/a181e89d-44ae-40e7-8d37-177071237c74 | L32: 2
A33: DLBDSEAD1 | B33: Self-Driving Vehicles | C33: ▪ cite relevant safety standards. ▪ grasp the concepts of sensors and sensor fusion. ▪ apply computer vision techniques to detect features. ▪ evaluate images in terms of semantic segmentation. ▪ understand motion models and localization approaches. ▪ utilize motion planning techniques. | D33: No | E33: http://data.europa.eu/esco/skill/45f1ae17-c20d-40fc-9307-7d33b6ca9213; http://data.europa.eu/esco/skill/77e167dc-70e6-4408-9718-019a4b9e96d9; http://data.europa.eu/esco/skill/804b7c6b-c5af-45d4-97ac-235a89234a54; http://data.europa.eu/esco/skill/8afe68ff-b261-4fa8-ab25-bb30b0e5c292; http://data.europa.eu/esco/skill/c4180af3-befd-4bd8-9a65-6a496f9d9f15 | F33: 5 | G33: http://data.europa.eu/esco/skill/45f1ae17-c20d-40fc-9307-7d33b6ca9213 | H33: 1 | J33: 0 | L33: 0
A34: DLBDSEAD2 | B34: Seminar: Current Topics and Trends in Self-Driving Technology | C34: ▪ transfer theoretical knowledge and methods to new domains. ▪ understand recent developments in self-driving vehicles. ▪ create new insights based on detailed studies of current research and technology. | D34: No | E34: http://data.europa.eu/esco/skill/ddc3119d-1d6e-4324-9125-a3380d299ac5; http://data.europa.eu/esco/skill/fc0fbc9c-b24d-42fa-ae66-c9b4945b6bc0 | F34: 2 | G34: http://data.europa.eu/esco/skill/ddc3119d-1d6e-4324-9125-a3380d299ac5 | H34: 1 | J34: 0 | L34: 0
A35: DLBDSMTP | B35: Project: From Model to Production Environment | C35: ▪ understand the challenges of integrating a predictive model into an application or service. ▪ evaluate the constraints a project imposes on the execution of a predictive model. ▪ analyze the requirements regarding data acquisition, storage, and processing. ▪ identify the necessary monitoring components required for reliable execution of the predictive model. ▪ create and design a production environment for storing, accessing, and serving the predictive model. | D35: Yes | E35: http://data.europa.eu/esco/skill/02e22093-3436-46a8-8dc5-b041bc4800cc; http://data.europa.eu/esco/skill/38d49d88-9069-467b-b29e-3cae739bdd4d; http://data.europa.eu/esco/skill/3d03c40c-1b83-4793-8902-2523f40af59e; http://data.europa.eu/esco/skill/7a9c3fa5-a9bb-46a0-8b5b-4d87427c8b76; http://data.europa.eu/esco/skill/88564d2d-2dc9-4789-864a-f9cb73f389ec; http://data.europa.eu/esco/skill/cb15ece1-2afd-488c-852d-0b52c13409ef; http://data.europa.eu/esco/skill/dd009c14-f702-4d16-a919-8d2098205cf4; http://data.europa.eu/esco/skill/e2887d71-8ff4-4188-9926-22bdaefa7713 | F35: 8 | G35: http://data.europa.eu/esco/skill/02e22093-3436-46a8-8dc5-b041bc4800cc; http://data.europa.eu/esco/skill/38d49d88-9069-467b-b29e-3cae739bdd4d; http://data.europa.eu/esco/skill/88564d2d-2dc9-4789-864a-f9cb73f389ec; http://data.europa.eu/esco/skill/dd009c14-f702-4d16-a919-8d2098205cf4; http://data.europa.eu/esco/skill/e2887d71-8ff4-4188-9926-22bdaefa7713 | H35: 5 | I35: http://data.europa.eu/esco/skill/38d49d88-9069-467b-b29e-3cae739bdd4d; http://data.europa.eu/esco/skill/88564d2d-2dc9-4789-864a-f9cb73f389ec | J35: 2 | L35: 0
A36: DLBDSEIMB1 | B36: International Marketing | C36: ▪ understand basic aspects of international strategic marketing. ▪ analyze cultural differences and their impact on international marketing. ▪ apply selected concepts of the international marketing mix. ▪ describe the possibilities of international market research and its influence on consumer behavior. ▪ recognize the necessity of international brand controlling and quality management. ▪ reproduce theoretical knowledge using case studies. | D36: No | E36: http://data.europa.eu/esco/skill/11cbcf7f-8dc3-4c9a-9ec1-37f51b5cbc19; http://data.europa.eu/esco/skill/35ebe444-9ece-4fbc-a55d-e99ea37267ae; http://data.europa.eu/esco/skill/7ea3973c-87ea-4167-9e0f-c74f5aec26ec; http://data.europa.eu/esco/skill/a1a8e4ae-f1e3-44aa-9067-e587e69634cd; http://data.europa.eu/esco/skill/aa7eac5f-dc9d-401a-b197-c9c455d78c95; http://data.europa.eu/esco/skill/b011c8b4-76e1-4bbc-8bb9-1d205e7b618a; http://data.europa.eu/esco/skill/d3e585e9-3a73-4511-b533-90f095e5aa09; http://data.europa.eu/esco/skill/e1da04bb-4de8-4d17-af8a-75ea893fe36a | F36: 8 | G36: http://data.europa.eu/esco/skill/35ebe444-9ece-4fbc-a55d-e99ea37267ae; http://data.europa.eu/esco/skill/a1a8e4ae-f1e3-44aa-9067-e587e69634cd; http://data.europa.eu/esco/skill/aa7eac5f-dc9d-401a-b197-c9c455d78c95; http://data.europa.eu/esco/skill/b011c8b4-76e1-4bbc-8bb9-1d205e7b618a; http://data.europa.eu/esco/skill/d3e585e9-3a73-4511-b533-90f095e5aa09 | H36: 5 | I36: http://data.europa.eu/esco/skill/35ebe444-9ece-4fbc-a55d-e99ea37267ae; http://data.europa.eu/esco/skill/a1a8e4ae-f1e3-44aa-9067-e587e69634cd; http://data.europa.eu/esco/skill/aa7eac5f-dc9d-401a-b197-c9c455d78c95; http://data.europa.eu/esco/skill/b011c8b4-76e1-4bbc-8bb9-1d205e7b618a; http://data.europa.eu/esco/skill/d3e585e9-3a73-4511-b533-90f095e5aa09 | J36: 5 | K36: http://data.europa.eu/esco/skill/35ebe444-9ece-4fbc-a55d-e99ea37267ae; http://data.europa.eu/esco/skill/aa7eac5f-dc9d-401a-b197-c9c455d78c95; http://data.europa.eu/esco/skill/d3e585e9-3a73-4511-b533-90f095e5aa09 | L36: 3
A37: DLBDSEAS1 | B37: Applied Sales I | C37: ▪ understand the fundamentals of applied sales and place them in the context of the company. ▪ understand the interaction of the individual facets of applied sales. ▪ differentiate between and evaluate individual sales systems. ▪ describe current sales types and sales characteristics. ▪ oversee and classify the entire sales process from customer acquisition to customer retention. ▪ understand the basics of sales and negotiation management and apply them. ▪ name the usual sales instruments, recognize their advantages and disadvantages, and reflect on essential fields of application and possibilities. | D37: No | E37: http://data.europa.eu/esco/skill/171eee55-19b9-46d6-aded-33193ba8ccf1; http://data.europa.eu/esco/skill/450de541-797a-4da0-9fe4-a81471c8047d; http://data.europa.eu/esco/skill/555ee719-4bc2-49c9-82b2-c2c01bfe3637; http://data.europa.eu/esco/skill/7954861c-86d4-4529-afbb-2c23dab9ac74; http://data.europa.eu/esco/skill/ceda9207-797c-4d4a-b65a-5eb59084f011; http://data.europa.eu/esco/skill/ec66b111-d8d0-4516-88ba-ee0b6fe6f695; http://data.europa.eu/esco/skill/f77b73f0-8c65-4389-a3ae-3a57a73ad148 | F37: 7 | G37: http://data.europa.eu/esco/skill/171eee55-19b9-46d6-aded-33193ba8ccf1; http://data.europa.eu/esco/skill/450de541-797a-4da0-9fe4-a81471c8047d; http://data.europa.eu/esco/skill/555ee719-4bc2-49c9-82b2-c2c01bfe3637; http://data.europa.eu/esco/skill/7954861c-86d4-4529-afbb-2c23dab9ac74; http://data.europa.eu/esco/skill/ec66b111-d8d0-4516-88ba-ee0b6fe6f695 | H37: 5 | I37: http://data.europa.eu/esco/skill/450de541-797a-4da0-9fe4-a81471c8047d; http://data.europa.eu/esco/skill/7954861c-86d4-4529-afbb-2c23dab9ac74 | J37: 2 | K37: http://data.europa.eu/esco/skill/450de541-797a-4da0-9fe4-a81471c8047d; http://data.europa.eu/esco/skill/7954861c-86d4-4529-afbb-2c23dab9ac74 | L37: 2
A38: DLBDSEAS2 | B38: Applied Sales II | C38: ▪ understand the interaction and the respective areas of responsibility of marketing and sales. ▪ reflect on and classify the goals and measures within the framework of the applied sales system. ▪ assess the relevance of customer satisfaction and retention. In addition, the students will be familiar with the central design elements of CRM. ▪ reflect on and assess alternative approaches to customer loyalty and relationship management and apply them in business practice. ▪ understand the meaning of the terms customer life cycle and customer value, and develop approaches to manage them in the sense of the respective sales targets. ▪ use descriptive presentation techniques in order to convince customers and other sales partners. ▪ understand the relevance of networking and develop strategies to broaden the contact base. ▪ develop and evaluate their own market analyses and sales concepts on the basis of practical experience within the framework of the case study. | D38: No | E38: http://data.europa.eu/esco/skill/0d11711b-870f-4701-be93-fa175b6e4002; http://data.europa.eu/esco/skill/20e7c937-a5e5-4a27-bb87-ddda5826f777; http://data.europa.eu/esco/skill/21e0cad8-4eef-42be-b18b-0f8e37f0dbd0; http://data.europa.eu/esco/skill/2239694b-771a-4586-8b54-2794e361a9ae; http://data.europa.eu/esco/skill/4377dd26-a0d6-497c-9ffe-f59308d36648; http://data.europa.eu/esco/skill/450de541-797a-4da0-9fe4-a81471c8047d; http://data.europa.eu/esco/skill/4ddf5204-95f5-4be2-ad35-571e2f493ae5; http://data.europa.eu/esco/skill/4ffec20b-5bbb-47a2-bed5-eb70c4cbb572; http://data.europa.eu/esco/skill/5bbaa0e6-0fd7-4df2-9db7-34f78b40dc34; http://data.europa.eu/esco/skill/64f2c90c-4144-418e-82c6-3150e03d29a3; http://data.europa.eu/esco/skill/71746a0b-e58d-4dc4-ad03-bd84082eae21; http://data.europa.eu/esco/skill/77526b41-a770-4d4e-975e-5a595f6544fe; http://data.europa.eu/esco/skill/abe138ec-e084-47c7-abe3-e7f371f05eae; http://data.europa.eu/esco/skill/b011c8b4-76e1-4bbc-8bb9-1d205e7b618a; http://data.europa.eu/esco/skill/bb40da1a-232f-4ba1-a9f5-5283a4fb7a7a; http://data.europa.eu/esco/skill/cb668e89-6ef5-4ff3-ab4a-506010e7e70b; http://data.europa.eu/esco/skill/d0f2f8a7-d935-4a6d-8e54-dcc3e5e2cbeb; http://data.europa.eu/esco/skill/f77b73f0-8c65-4389-a3ae-3a57a73ad148; http://data.europa.eu/esco/skill/fc54bd7f-0c03-4fdd-af8c-5eb4021e716d | F38: 19 | G38: http://data.europa.eu/esco/skill/21e0cad8-4eef-42be-b18b-0f8e37f0dbd0; http://data.europa.eu/esco/skill/450de541-797a-4da0-9fe4-a81471c8047d; http://data.europa.eu/esco/skill/4ffec20b-5bbb-47a2-bed5-eb70c4cbb572; http://data.europa.eu/esco/skill/5bbaa0e6-0fd7-4df2-9db7-34f78b40dc34; http://data.europa.eu/esco/skill/71746a0b-e58d-4dc4-ad03-bd84082eae21; http://data.europa.eu/esco/skill/77526b41-a770-4d4e-975e-5a595f6544fe; http://data.europa.eu/esco/skill/b011c8b4-76e1-4bbc-8bb9-1d205e7b618a; http://data.europa.eu/esco/skill/bb40da1a-232f-4ba1-a9f5-5283a4fb7a7a; http://data.europa.eu/esco/skill/cb668e89-6ef5-4ff3-ab4a-506010e7e70b; http://data.europa.eu/esco/skill/d0f2f8a7-d935-4a6d-8e54-dcc3e5e2cbeb; http://data.europa.eu/esco/skill/fc54bd7f-0c03-4fdd-af8c-5eb4021e716d | H38: 11 | I38: http://data.europa.eu/esco/skill/21e0cad8-4eef-42be-b18b-0f8e37f0dbd0; http://data.europa.eu/esco/skill/450de541-797a-4da0-9fe4-a81471c8047d; http://data.europa.eu/esco/skill/4ffec20b-5bbb-47a2-bed5-eb70c4cbb572; http://data.europa.eu/esco/skill/5bbaa0e6-0fd7-4df2-9db7-34f78b40dc34; http://data.europa.eu/esco/skill/71746a0b-e58d-4dc4-ad03-bd84082eae21; http://data.europa.eu/esco/skill/77526b41-a770-4d4e-975e-5a595f6544fe; http://data.europa.eu/esco/skill/d0f2f8a7-d935-4a6d-8e54-dcc3e5e2cbeb; http://data.europa.eu/esco/skill/fc54bd7f-0c03-4fdd-af8c-5eb4021e716d | J38: 8 | K38: http://data.europa.eu/esco/skill/4ffec20b-5bbb-47a2-bed5-eb70c4cbb572; http://data.europa.eu/esco/skill/d0f2f8a7-d935-4a6d-8e54-dcc3e5e2cbeb | L38: 2
A39: DLBBWME_E | B39: Managerial Economics | C39: ▪ understand basic economic interrelationships and apply them to different markets. ▪ explain the importance of supply, demand and market balance. ▪ assess the determinants of consumers' willingness to pay. ▪ discuss the determinants of production decisions and identify peak entrepreneurial strategies. ▪ assess the influence of different types of markets on production and price decisions. ▪ analyse strategic interactions between companies. ▪ critically question traditional economic models on the basis of findings from information and behavioural economics. | D39: No | E39: http://data.europa.eu/esco/skill/1c460d2d-90c6-4fc9-ad49-febb6e15605a; http://data.europa.eu/esco/skill/2a0efd9a-4a60-4edc-8561-f2754d24eeb8; http://data.europa.eu/esco/skill/5faaac96-9273-4156-93fb-8b3d48cf20f4; http://data.europa.eu/esco/skill/798d427e-51b3-4cd4-8b24-1357015e9ae7; http://data.europa.eu/esco/skill/7cacd304-996d-47d1-88ef-4ddb9ce102bd; http://data.europa.eu/esco/skill/ba2c6181-b036-40b4-8f6d-51499463ccbb; http://data.europa.eu/esco/skill/bdcf429c-5ccf-4c3d-bb61-4c987573a35e; http://data.europa.eu/esco/skill/f60c9e52-95fc-4ca1-a73c-18a491153b63 | F39: 8 | G39: http://data.europa.eu/esco/skill/5faaac96-9273-4156-93fb-8b3d48cf20f4; http://data.europa.eu/esco/skill/ba2c6181-b036-40b4-8f6d-51499463ccbb; http://data.europa.eu/esco/skill/bdcf429c-5ccf-4c3d-bb61-4c987573a35e; http://data.europa.eu/esco/skill/f60c9e52-95fc-4ca1-a73c-18a491153b63 | H39: 4 | I39: http://data.europa.eu/esco/skill/5faaac96-9273-4156-93fb-8b3d48cf20f4 | J39: 1 | L39: 0
A40: DLBDSESCM1 | B40: Supply Chain Management I | C40: ▪ explain the importance of cross-company value creation processes. ▪ understand common concepts for modeling cross-company value creation processes. ▪ understand dynamic effects in supply chains and can systematize their causes and effects. ▪ explain important theoretical concepts for describing the characteristics and challenges of cross-company value creation processes. ▪ explain the approaches and problem categories commonly used in the context of supply chain management. ▪ understand important reference and/or management models for the concretization of supply chain systems. ▪ name and detail important roles and tasks in the SCM network. ▪ deal with the coordination problem of SCM and describe the common solution approaches. | D40: No | E40: http://data.europa.eu/esco/skill/1585fc98-bfe4-461f-97fc-734055a2c3ce; http://data.europa.eu/esco/skill/3812bbb9-4053-4685-aed5-af825d809501; http://data.europa.eu/esco/skill/39531b63-5c06-432f-81e3-15b551ae1310; http://data.europa.eu/esco/skill/b1ef509e-f191-405a-8419-51663b08922e; http://data.europa.eu/esco/skill/b7e57889-a84f-440c-9e60-459aa69979e9; http://data.europa.eu/esco/skill/cf579543-272b-43c8-b942-555836ae4241; http://data.europa.eu/esco/skill/f929c89e-c363-4132-a918-e021d57b307c | F40: 7 | G40: http://data.europa.eu/esco/skill/1585fc98-bfe4-461f-97fc-734055a2c3ce; http://data.europa.eu/esco/skill/b7e57889-a84f-440c-9e60-459aa69979e9; http://data.europa.eu/esco/skill/cf579543-272b-43c8-b942-555836ae4241; http://data.europa.eu/esco/skill/f929c89e-c363-4132-a918-e021d57b307c | H40: 4 | I40: http://data.europa.eu/esco/skill/cf579543-272b-43c8-b942-555836ae4241; http://data.europa.eu/esco/skill/f929c89e-c363-4132-a918-e021d57b307c | J40: 2 | K40: http://data.europa.eu/esco/skill/cf579543-272b-43c8-b942-555836ae4241 | L40: 1
A41: DLBDSESCM2 | B41: Supply Chain Management II | C41: ▪ systematically explain the strategic relevance of enterprise-wide value creation processes. ▪ understand the most important tasks and problems in the SCM core process planning. ▪ systematize the elements and interrelationships in the CPFR model in a differentiated way. ▪ be familiar with the characteristics and peculiarities of contract logistics. ▪ understand the most important tasks and problems in the SCM core process procurement. ▪ explain central elements and characteristics of a procurement strategy. ▪ understand the most important tasks and problems in the SCM core process production. ▪ explain central elements and characteristics of a modern production strategy. ▪ understand the most important tasks and problems in the SCM core process distribution. ▪ explain central elements and characteristics of the so-called ECR concept. | D41: No | E41: http://data.europa.eu/esco/skill/12c7b323-d870-4f5b-9d7d-d9f525206d77; http://data.europa.eu/esco/skill/24ccd586-3c38-4f60-ac70-8f984ca13449; http://data.europa.eu/esco/skill/29cd7e7b-215c-483a-b67a-6bdad0647de9; http://data.europa.eu/esco/skill/378caeec-10a0-4162-b75c-ab374a42e93d; http://data.europa.eu/esco/skill/5d00929a-7124-488a-91c1-324bd75bf8ba; http://data.europa.eu/esco/skill/798d427e-51b3-4cd4-8b24-1357015e9ae7; http://data.europa.eu/esco/skill/a6532ae5-efc4-4ca4-b172-c11471940d09 | F41: 7 | G41: http://data.europa.eu/esco/skill/12c7b323-d870-4f5b-9d7d-d9f525206d77; http://data.europa.eu/esco/skill/29cd7e7b-215c-483a-b67a-6bdad0647de9; http://data.europa.eu/esco/skill/378caeec-10a0-4162-b75c-ab374a42e93d; http://data.europa.eu/esco/skill/798d427e-51b3-4cd4-8b24-1357015e9ae7; http://data.europa.eu/esco/skill/a6532ae5-efc4-4ca4-b172-c11471940d09 | H41: 5 | I41: http://data.europa.eu/esco/skill/12c7b323-d870-4f5b-9d7d-d9f525206d77; http://data.europa.eu/esco/skill/29cd7e7b-215c-483a-b67a-6bdad0647de9; http://data.europa.eu/esco/skill/378caeec-10a0-4162-b75c-ab374a42e93d; http://data.europa.eu/esco/skill/798d427e-51b3-4cd4-8b24-1357015e9ae7; http://data.europa.eu/esco/skill/a6532ae5-efc4-4ca4-b172-c11471940d09 | J41: 5 | K41: http://data.europa.eu/esco/skill/29cd7e7b-215c-483a-b67a-6bdad0647de9; http://data.europa.eu/esco/skill/378caeec-10a0-4162-b75c-ab374a42e93d | L41: 2
A42: DLBAIBEBIDV | B42: Business Intelligence and Data Visualization | C42: ▪ grasp the key underlying principles and fundamentals of business intelligence and data visualization. ▪ understand and distinguish between the methodologies and applications of business intelligence and data analytics. ▪ leverage various business intelligence tools and techniques to generate data-driven results. ▪ troubleshoot and resolve typical business challenges using data visualization tools and business intelligence strategies. ▪ comprehend and investigate the limitations associated with different data types and visualization tools. | D42: No | E42: http://data.europa.eu/esco/skill/0d6714c6-720e-4985-9791-5ab85d28da79; http://data.europa.eu/esco/skill/143769cb-b61e-47d8-a61e-eedfbec1016c; http://data.europa.eu/esco/skill/348b74cd-49ce-4844-8bdf-ec188b497213; http://data.europa.eu/esco/skill/633a3637-2c6b-40ae-ac38-289eb2a62aa6; http://data.europa.eu/esco/skill/65e58886-bd1e-4c5b-8ca5-8d9b353c8aa1; http://data.europa.eu/esco/skill/97bd1c21-66b2-4b7e-ad0f-e3cda590e378; http://data.europa.eu/esco/skill/c3e36d05-8ae8-447f-bb2b-6f9409f85389; http://data.europa.eu/esco/skill/f0a84d52-91fd-45ec-9fe9-e363d9318b9e; http://data.europa.eu/esco/skill/fecf8a0d-62c4-4e71-9b03-0f4fc2ad7bf5 | F42: 9 | G42: http://data.europa.eu/esco/skill/0d6714c6-720e-4985-9791-5ab85d28da79; http://data.europa.eu/esco/skill/143769cb-b61e-47d8-a61e-eedfbec1016c; http://data.europa.eu/esco/skill/348b74cd-49ce-4844-8bdf-ec188b497213; http://data.europa.eu/esco/skill/633a3637-2c6b-40ae-ac38-289eb2a62aa6; http://data.europa.eu/esco/skill/65e58886-bd1e-4c5b-8ca5-8d9b353c8aa1; http://data.europa.eu/esco/skill/97bd1c21-66b2-4b7e-ad0f-e3cda590e378; http://data.europa.eu/esco/skill/c3e36d05-8ae8-447f-bb2b-6f9409f85389 | H42: 7 | I42: http://data.europa.eu/esco/skill/143769cb-b61e-47d8-a61e-eedfbec1016c; http://data.europa.eu/esco/skill/348b74cd-49ce-4844-8bdf-ec188b497213; http://data.europa.eu/esco/skill/65e58886-bd1e-4c5b-8ca5-8d9b353c8aa1; http://data.europa.eu/esco/skill/97bd1c21-66b2-4b7e-ad0f-e3cda590e378; http://data.europa.eu/esco/skill/c3e36d05-8ae8-447f-bb2b-6f9409f85389 | J42: 5 | K42: http://data.europa.eu/esco/skill/143769cb-b61e-47d8-a61e-eedfbec1016c; http://data.europa.eu/esco/skill/65e58886-bd1e-4c5b-8ca5-8d9b353c8aa1; http://data.europa.eu/esco/skill/97bd1c21-66b2-4b7e-ad0f-e3cda590e378 | L42: 3
A43: DLBCSAPM | B43: Project: Agile Project Management | C43: ▪ explain the differences between agile and plan-driven project management. ▪ explain agile principles. ▪ work together in an agile manner according to the values defined in Scrum. ▪ apply the activities defined in Scrum. ▪ take responsibility for the roles defined in Scrum. ▪ create and maintain the artefacts defined in Scrum. ▪ consider the increasing relevance of international, intercultural and virtual collaboration in projects. | D43: Yes | E43: http://data.europa.eu/esco/skill/199f7919-5114-41b6-b6a5-41e0e4896ec1; http://data.europa.eu/esco/skill/1fcce318-3212-487a-ac07-4941bc85060d; http://data.europa.eu/esco/skill/2f4d68be-6e9f-46fa-9398-0573e900b5e3; http://data.europa.eu/esco/skill/7d23c508-c007-4221-bb84-0c9a479b8ea6; http://data.europa.eu/esco/skill/8ff015a0-98ea-4d80-a23e-1f68110a919e; http://data.europa.eu/esco/skill/c3687b34-fe53-4db2-ad1b-5055a6c5b6fd; http://data.europa.eu/esco/skill/dba46f87-0831-49cd-a1c7-340a653c0221 | F43: 7 | G43: http://data.europa.eu/esco/skill/199f7919-5114-41b6-b6a5-41e0e4896ec1; http://data.europa.eu/esco/skill/2f4d68be-6e9f-46fa-9398-0573e900b5e3; http://data.europa.eu/esco/skill/7d23c508-c007-4221-bb84-0c9a479b8ea6; http://data.europa.eu/esco/skill/8ff015a0-98ea-4d80-a23e-1f68110a919e; http://data.europa.eu/esco/skill/c3687b34-fe53-4db2-ad1b-5055a6c5b6fd; http://data.europa.eu/esco/skill/dba46f87-0831-49cd-a1c7-340a653c0221 | H43: 6 | I43: http://data.europa.eu/esco/skill/7d23c508-c007-4221-bb84-0c9a479b8ea6; http://data.europa.eu/esco/skill/dba46f87-0831-49cd-a1c7-340a653c0221 | J43: 2 | K43: http://data.europa.eu/esco/skill/dba46f87-0831-49cd-a1c7-340a653c0221 | L43: 1
A44: DLBDSCIBDSC | B44: Internship: Bachelor Data Science | C44: ▪ transfer theoretical knowledge to practical problems. ▪ independently address and manage practical challenges; to reflect on their success, depending on the tasks undertaken. ▪ better assess the scope, significance, and limitations of theoretical concepts in light of practical demands. ▪ work on a project collaboratively and in an intercultural environment while complying with ethical data-handling practices. ▪ work with established data formats and apply widely-used techniques for data preparation. ▪ discuss the fundamental aspects of data quality and apply data quality-ensuring measures. ▪ apply agile approaches in all phases of a Data Science project, including business and data understanding, data preparation, model training, evaluation, and deploying models into a production environment. | D44: No | E44: http://data.europa.eu/esco/skill/07889c08-7220-47c8-96f7-6068fbea00dc; http://data.europa.eu/esco/skill/0a9acb6b-1139-4be9-b431-3a80a959f2f4; http://data.europa.eu/esco/skill/0d6714c6-720e-4985-9791-5ab85d28da79; http://data.europa.eu/esco/skill/12c7b323-d870-4f5b-9d7d-d9f525206d77; http://data.europa.eu/esco/skill/457c2e47-07e6-4073-827e-e1c21f3e5869; http://data.europa.eu/esco/skill/53103efa-a525-4a5b-81e5-282c4331e72c; http://data.europa.eu/esco/skill/7a34b3d9-bd3b-4f4e-a0f6-f97439901cb7; http://data.europa.eu/esco/skill/c10d5d87-36cf-42f5-8a12-e560fb5f4af8; http://data.europa.eu/esco/skill/cc7370dd-69fa-4c67-a96f-d4d135d38700; http://data.europa.eu/esco/skill/e9575f7f-053a-439e-8074-f93df3334e92; http://data.europa.eu/esco/skill/f1f5093b-0b26-4d59-984b-0531c6ccf205; http://data.europa.eu/esco/skill/f8e5f1fd-82ee-45c0-b179-399d8e9a22aa; http://data.europa.eu/esco/skill/fc0fbc9c-b24d-42fa-ae66-c9b4945b6bc0 | F44: 13 | G44: http://data.europa.eu/esco/skill/07889c08-7220-47c8-96f7-6068fbea00dc; http://data.europa.eu/esco/skill/0a9acb6b-1139-4be9-b431-3a80a959f2f4; http://data.europa.eu/esco/skill/0d6714c6-720e-4985-9791-5ab85d28da79; http://data.europa.eu/esco/skill/12c7b323-d870-4f5b-9d7d-d9f525206d77; http://data.europa.eu/esco/skill/457c2e47-07e6-4073-827e-e1c21f3e5869; http://data.europa.eu/esco/skill/53103efa-a525-4a5b-81e5-282c4331e72c; http://data.europa.eu/esco/skill/7a34b3d9-bd3b-4f4e-a0f6-f97439901cb7; http://data.europa.eu/esco/skill/c10d5d87-36cf-42f5-8a12-e560fb5f4af8; http://data.europa.eu/esco/skill/cc7370dd-69fa-4c67-a96f-d4d135d38700; http://data.europa.eu/esco/skill/e9575f7f-053a-439e-8074-f93df3334e92; http://data.europa.eu/esco/skill/f1f5093b-0b26-4d59-984b-0531c6ccf205 | H44: 11 | I44: http://data.europa.eu/esco/skill/07889c08-7220-47c8-96f7-6068fbea00dc; http://data.europa.eu/esco/skill/0a9acb6b-1139-4be9-b431-3a80a959f2f4; http://data.europa.eu/esco/skill/457c2e47-07e6-4073-827e-e1c21f3e5869; http://data.europa.eu/esco/skill/c10d5d87-36cf-42f5-8a12-e560fb5f4af8; http://data.europa.eu/esco/skill/cc7370dd-69fa-4c67-a96f-d4d135d38700; http://data.europa.eu/esco/skill/e9575f7f-053a-439e-8074-f93df3334e92; http://data.europa.eu/esco/skill/f1f5093b-0b26-4d59-984b-0531c6ccf205 | J44: 7 | K44: http://data.europa.eu/esco/skill/cc7370dd-69fa-4c67-a96f-d4d135d38700; http://data.europa.eu/esco/skill/e9575f7f-053a-439e-8074-f93df3334e92; http://data.europa.eu/esco/skill/f1f5093b-0b26-4d59-984b-0531c6ccf205 | L44: 3
A45: DLBCSCW | B45: Collaborative Work | C45: ▪ design their own learning processes both self-directed and collaborative with analog and digital media. ▪ initiate face-to-face and virtual cooperation and select suitable methods for shaping collaboration even in an intercultural context and across disciplinary boundaries. ▪ assess different forms of communication in relation to the goals and requirements of different situations and to reflect on their own communication and argumentation behavior in order to be able to shape conducive collaboration also in an interdisciplinary context. ▪ recognize social diversity including cultural and professional differences as a value, and to name and apply tools to deal with them constructively. ▪ explain conflict potentials and the role of emotions in conflicts and to describe the use of systemic methods in the target- and solution-oriented handling of conflicts. ▪ analyze one's own resources, present methods of self-leadership and self-motivation, and derive appropriate strategies. | D45: No | E45: http://data.europa.eu/esco/skill/0ee94c0a-3716-494a-95a2-dcbab9e58be2; http://data.europa.eu/esco/skill/15d76317-c71a-4fa2-aadc-2ecc34e627b7; http://data.europa.eu/esco/skill/18e644ff-cd44-4818-a379-ef2ccf28713e; http://data.europa.eu/esco/skill/4b5d4fe3-4280-47c0-b1d2-ab08ace85557; http://data.europa.eu/esco/skill/75d8e5d9-bef3-418b-9011-01bff9f27207; http://data.europa.eu/esco/skill/96de2e86-e287-41f2-88ab-15a2343afc6f; http://data.europa.eu/esco/skill/9bf266a6-188b-4d17-a22f-2f266d76832b; http://data.europa.eu/esco/skill/a88da605-095f-4a4f-be1c-d1444df8228a; http://data.europa.eu/esco/skill/aa56a80c-b4d5-495c-9c15-70b5a7933911; http://data.europa.eu/esco/skill/b17f4305-741a-4a1c-8fe8-6f11cb3d5c0a; http://data.europa.eu/esco/skill/b99aa3b8-0066-46b2-a027-30afae444ad8; http://data.europa.eu/esco/skill/cee44f3a-c99a-43d4-83b9-a630424e637e; http://data.europa.eu/esco/skill/d56e2c2f-3e01-4b76-a7bb-ecb6d430172f; http://data.europa.eu/esco/skill/d7e4a9fa-cfc2-45f9-96eb-13dc6e48c86c; http://data.europa.eu/esco/skill/e2d44a9b-f28c-489e-9861-b654b5ded507; http://data.europa.eu/esco/skill/f69722f4-7e34-4aaa-ba5a-7bf621421085; http://data.europa.eu/esco/skill/f7b071bf-4882-4cfc-ae0a-7e0e0ab94c61 | F45: 17 | G45: http://data.europa.eu/esco/skill/0ee94c0a-3716-494a-95a2-dcbab9e58be2; http://data.europa.eu/esco/skill/15d76317-c71a-4fa2-aadc-2ecc34e627b7; http://data.europa.eu/esco/skill/4b5d4fe3-4280-47c0-b1d2-ab08ace85557; http://data.europa.eu/esco/skill/75d8e5d9-bef3-418b-9011-01bff9f27207; http://data.europa.eu/esco/skill/96de2e86-e287-41f2-88ab-15a2343afc6f; http://data.europa.eu/esco/skill/a88da605-095f-4a4f-be1c-d1444df8228a; http://data.europa.eu/esco/skill/b17f4305-741a-4a1c-8fe8-6f11cb3d5c0a; http://data.europa.eu/esco/skill/f69722f4-7e34-4aaa-ba5a-7bf621421085; http://data.europa.eu/esco/skill/f7b071bf-4882-4cfc-ae0a-7e0e0ab94c61 | H45: 9 | I45: http://data.europa.eu/esco/skill/0ee94c0a-3716-494a-95a2-dcbab9e58be2; http://data.europa.eu/esco/skill/4b5d4fe3-4280-47c0-b1d2-ab08ace85557; http://data.europa.eu/esco/skill/a88da605-095f-4a4f-be1c-d1444df8228a; http://data.europa.eu/esco/skill/f69722f4-7e34-4aaa-ba5a-7bf621421085 | J45: 4 | K45: http://data.europa.eu/esco/skill/a88da605-095f-4a4f-be1c-d1444df8228a | L45: 1
A46: DLBCSIDM | B46: Intercultural and Ethical Decision-Making | C46: ▪ explain the most important terms in the areas of interculturality, diversity, and ethics. ▪ distinguish different explanatory patterns of culture. ▪ understand culture at different levels. ▪ plan processes of intercultural learning and working. ▪ understand the interdependencies of culture and ethics. ▪ independently work on a case study on intercultural competence. | D46: No | E46: http://data.europa.eu/esco/skill/2f4f78ac-0246-4c59-907d-9fcb46f8fb77; http://data.europa.eu/esco/skill/56e30a60-0a87-4631-85ea-c69bc8bd0519; http://data.europa.eu/esco/skill/c10d5d87-36cf-42f5-8a12-e560fb5f4af8; http://data.europa.eu/esco/skill/cef5c0f8-1e40-4c09-b6a7-aa7811849e5d; http://data.europa.eu/esco/skill/e3ef4981-2cba-4b34-b273-728c3a33d04f | F46: 5 | G46: http://data.europa.eu/esco/skill/56e30a60-0a87-4631-85ea-c69bc8bd0519; http://data.europa.eu/esco/skill/c10d5d87-36cf-42f5-8a12-e560fb5f4af8; http://data.europa.eu/esco/skill/cef5c0f8-1e40-4c09-b6a7-aa7811849e5d; http://data.europa.eu/esco/skill/e3ef4981-2cba-4b34-b273-728c3a33d04f | H46: 4 | I46: http://data.europa.eu/esco/skill/c10d5d87-36cf-42f5-8a12-e560fb5f4af8; http://data.europa.eu/esco/skill/e3ef4981-2cba-4b34-b273-728c3a33d04f | J46: 2 | L46: 0
A47: DLBCSEBI1 | B47: Business Intelligence | C47: ▪ explain the motivation, use cases, and basics of Business Intelligence. ▪ identify and explain techniques and methods for providing and modeling data, as well as types of data relevant to BI, differentiating between them. ▪ explain techniques and methods for the generation and storage of information and independently select suitable methods on the basis of concrete requirements. | D47: No | E47: http://data.europa.eu/esco/skill/143769cb-b61e-47d8-a61e-eedfbec1016c; http://data.europa.eu/esco/skill/172020d1-e151-445b-8173-e2a5fb16fe51; http://data.europa.eu/esco/skill/7a34b3d9-bd3b-4f4e-a0f6-f97439901cb7; http://data.europa.eu/esco/skill/e2d44a9b-f28c-489e-9861-b654b5ded507; http://data.europa.eu/esco/skill/fecf8a0d-62c4-4e71-9b03-0f4fc2ad7bf5 | F47: 5 | G47: http://data.europa.eu/esco/skill/143769cb-b61e-47d8-a61e-eedfbec1016c; http://data.europa.eu/esco/skill/172020d1-e151-445b-8173-e2a5fb16fe51; http://data.europa.eu/esco/skill/e2d44a9b-f28c-489e-9861-b654b5ded507; http://data.europa.eu/esco/skill/fecf8a0d-62c4-4e71-9b03-0f4fc2ad7bf5 | H47: 4 | I47: http://data.europa.eu/esco/skill/143769cb-b61e-47d8-a61e-eedfbec1016c; http://data.europa.eu/esco/skill/fecf8a0d-62c4-4e71-9b03-0f4fc2ad7bf5 | J47: 2 | K47: http://data.europa.eu/esco/skill/143769cb-b61e-47d8-a61e-eedfbec1016c; http://data.europa.eu/esco/skill/fecf8a0d-62c4-4e71-9b03-0f4fc2ad7bf5 | L47: 2
A48: DLBDSDQDW | B48: Data Quality and Data Wrangling | C48: ▪ discuss the fundamental aspects of data quality. ▪ describe common approaches to data quality management. ▪ use various methods to gather data from websites and other public data sources. ▪ work with established data formats. ▪ explain widely-used techniques for data preparation. | D48: No | E48: http://data.europa.eu/esco/skill/07889c08-7220-47c8-96f7-6068fbea00dc; http://data.europa.eu/esco/skill/1605025e-a179-421f-8f35-5b07d182a6b2; http://data.europa.eu/esco/skill/4f5c1208-62fd-4e5a-a51e-306c06947e11; http://data.europa.eu/esco/skill/a9a52adf-0bf3-4dee-aec3-4fdeb950538e; http://data.europa.eu/esco/skill/cc7370dd-69fa-4c67-a96f-d4d135d38700 | F48: 5 | G48: http://data.europa.eu/esco/skill/07889c08-7220-47c8-96f7-6068fbea00dc; http://data.europa.eu/esco/skill/1605025e-a179-421f-8f35-5b07d182a6b2; http://data.europa.eu/esco/skill/cc7370dd-69fa-4c67-a96f-d4d135d38700 | H48: 3 | I48: http://data.europa.eu/esco/skill/07889c08-7220-47c8-96f7-6068fbea00dc; http://data.europa.eu/esco/skill/cc7370dd-69fa-4c67-a96f-d4d135d38700 | J48: 2 | K48: http://data.europa.eu/esco/skill/cc7370dd-69fa-4c67-a96f-d4d135d38700 | L48: 1
A49: DLBDSDSSE | B49: Data Science Software Engineering | C49: ▪ understand the concept of project management approaches. ▪ apply agile approaches in software development. ▪ create automated software tests. ▪ understand various software development paradigms. ▪ evaluate the necessary steps to bring models into a production environment. | D49: No | E49: http://data.europa.eu/esco/skill/24c200e5-be20-4370-a137-ab53797f3a17; http://data.europa.eu/esco/skill/6a322874-e32f-4cd8-9683-badce67a7f73; http://data.europa.eu/esco/skill/7111b95d-0ce3-441a-9d92-4c75d05c4388; http://data.europa.eu/esco/skill/dba46f87-0831-49cd-a1c7-340a653c0221; http://data.europa.eu/esco/skill/e2887d71-8ff4-4188-9926-22bdaefa7713 | F49: 5 | G49: http://data.europa.eu/esco/skill/24c200e5-be20-4370-a137-ab53797f3a17; http://data.europa.eu/esco/skill/6a322874-e32f-4cd8-9683-badce67a7f73; http://data.europa.eu/esco/skill/7111b95d-0ce3-441a-9d92-4c75d05c4388; http://data.europa.eu/esco/skill/dba46f87-0831-49cd-a1c7-340a653c0221; http://data.europa.eu/esco/skill/e2887d71-8ff4-4188-9926-22bdaefa7713 | H49: 5 | I49: http://data.europa.eu/esco/skill/24c200e5-be20-4370-a137-ab53797f3a17; http://data.europa.eu/esco/skill/6a322874-e32f-4cd8-9683-badce67a7f73; http://data.europa.eu/esco/skill/7111b95d-0ce3-441a-9d92-4c75d05c4388; http://data.europa.eu/esco/skill/dba46f87-0831-49cd-a1c7-340a653c0221; http://data.europa.eu/esco/skill/e2887d71-8ff4-4188-9926-22bdaefa7713 | J49: 5 | K49: http://data.europa.eu/esco/skill/6a322874-e32f-4cd8-9683-badce67a7f73; http://data.europa.eu/esco/skill/7111b95d-0ce3-441a-9d92-4c75d05c4388; http://data.europa.eu/esco/skill/dba46f87-0831-49cd-a1c7-340a653c0221 | L49: 3
A50: DLBDSME | B50: Model Engineering | C50: ▪ understand common data science methodologies. ▪ create benchmark models. ▪ analyze models with respect to their interpretability. ▪ apply model validation techniques. ▪ recall established model combination techniques. | D50: No | E50: http://data.europa.eu/esco/skill/48db96bf-3314-45c6-bad8-fdb6e20e5639; http://data.europa.eu/esco/skill/a044a90e-be8b-446e-9703-e42cc34c3551 | F50: 2 | G50: http://data.europa.eu/esco/skill/48db96bf-3314-45c6-bad8-fdb6e20e5639 | H50: 1 | J50: 0 | L50: 0
A51: DLBBT01 | B51: Bachelor Thesis | C51: ▪ work on a problem from their major field of study by applying the specialist and methodological skills they have acquired during their studies. ▪ independently analyze selected tasks with scientific methods, critically evaluate them, and develop appropriate solutions under the guidance of an academic supervisor. ▪ record and analyze existing (research) literature appropriate to the topic of their bachelor's thesis. ▪ prepare a detailed written elaboration in compliance with scientific methods.▪ present a problem from their field of study using academic presentation and communication techniques. ▪ reflect on the scientific and methodological approach chosen in their bachelor's thesis. ▪ demonstrate that they can actively answer subject-related questions from the subject experts (reviewers of the bachelor’s thesis). | D51: Yes | E51: http://data.europa.eu/esco/skill/15d76317-c71a-4fa2-aadc-2ecc34e627b7; http://data.europa.eu/esco/skill/4f6e68b2-85c8-446e-a96d-b306ec7e0091; http://data.europa.eu/esco/skill/7d4a4dc4-9324-4975-905d-ff1140f95acc; http://data.europa.eu/esco/skill/7dd94ad3-13d6-43fe-8b94-51fcbf67ced9; http://data.europa.eu/esco/skill/833289fa-3646-4010-9d9e-93ba8c9ef2d8 | F51: 5 | G51: http://data.europa.eu/esco/skill/15d76317-c71a-4fa2-aadc-2ecc34e627b7; http://data.europa.eu/esco/skill/7d4a4dc4-9324-4975-905d-ff1140f95acc; http://data.europa.eu/esco/skill/7dd94ad3-13d6-43fe-8b94-51fcbf67ced9; http://data.europa.eu/esco/skill/833289fa-3646-4010-9d9e-93ba8c9ef2d8 | H51: 4 | I51: http://data.europa.eu/esco/skill/15d76317-c71a-4fa2-aadc-2ecc34e627b7 | J51: 1 | K51: http://data.europa.eu/esco/skill/15d76317-c71a-4fa2-aadc-2ecc34e627b7 | L51: 1

Sheet ESCOX skill list
A1: conceptUri | B1: skillType | C1: reuseLevel | D1: preferredLabel | E1: altLabels | F1: hiddenLabels | G1: status | H1: modifiedDate | I1: scopeNote | J1: definition | K1: inScheme | L1: description
A2: http://data.europa.eu/esco/skill/0005c151-5b5a-4a66-8aac-60e734beb1ab | B2: skill/competence | C2: sector-specific | D2: manage musical staff | E2: manage music staff coordinate duties of musical staff direct musical staff manage staff of music | G2: released | H2: 2023-11-30T15:53:37.136Z | K2: http://data.europa.eu/esco/concept-scheme/skills, http://data.europa.eu/esco/concept-scheme/member-skills | L2: Assign and manage staff tasks in areas such as scoring, arranging, copying music and vocal coaching.
A3: http://data.europa.eu/esco/skill/00064735-8fad-454b-90c7-ed858cc993f2 | B3: skill/competence | C3: occupation-specific | D3: supervise correctional procedures | E3: manage prison procedures monitor correctional procedures oversee prison procedures oversee correctional procedures manage correctional procedures monitor prison procedures | G3: released | H3: 2023-11-30T15:04:00.689Z | K3: http://data.europa.eu/esco/concept-scheme/skills, http://data.europa.eu/esco/concept-scheme/member-skills | L3: Supervise the operations of a correctional facility or other correctional procedures, ensuring that they are compliant with legal regulations, and ensure that the staff complies with regulations, and aim to improve the facility's efficiency and safety.
A4: http://data.europa.eu/esco/skill/000709ed-2be5-4193-b056-45a97698d828 | B4: skill/competence | C4: sector-specific | D4: apply anti-oppressive practices | E4: make use of anti-oppressive practices use anti-oppressive practices apply non-oppressive practices apply anti-oppresive practice identify oppression in societies and groups apply an anti-oppressive practice act in a non-oppressive way | G4: released | H4: 2023-11-28T10:45:53.54Z | K4: http://data.europa.eu/esco/concept-scheme/skills, http://data.europa.eu/esco/concept-scheme/member-skills | L4: Identify oppression in societies, economies, cultures, and groups, acting as a professional in an non-oppressive way, enabling service users to take action to improve their lives and enabling citizens to change their environment in accordance with their own interests.
A5: http://data.europa.eu/esco/skill/0007bdc2-dd15-4824-b7d6-416522c46f35 | B5: skill/competence | C5: sector-specific | D5: control compliance of railway vehicles regulations | E5: checking compliance with rolling stock regulations control compliance of regulations of rolling stock conduct controls of compliance of railway vehicles regulations compliance controls of railway vehicles regulations ensuring compliance with railway vehicles regulations inspection of compliance with rolling stock regulations monitoring of compliance with rolling stock regulations monitoring of compliance with railway vehicles regulations | G5: released | H5: 2023-11-30T16:29:18.273Z | K5: http://data.europa.eu/esco/concept-scheme/skills, http://data.europa.eu/esco/concept-scheme/member-skills | L5: Inspect rolling stock, components and systems to ensure compliance with standards and specifications.
A6: http://data.europa.eu/esco/skill/00090cc1-1f27-439e-a4e0-19a87a501bfc | B6: skill/competence | C6: cross-sector | D6: identify available services | E6: determine available services classify available services classify rehabilitation services analyse rehabilitation services establish rehabilitation services establish available services determine rehabilitation services analyse available services | G6: released | H6: 2023-11-28T10:38:49.206Z | K6: http://data.europa.eu/esco/concept-scheme/skills, http://data.europa.eu/esco/concept-scheme/member-skills | L6: Identify the different services available for an offender during probation in order to help in the rehabilitation and re-integration process, as well as advising the offenders as to how they can identify services available to them.
A7: http://data.europa.eu/esco/skill/000bb1e4-89f0-4b86-be05-05ece3641724 | B7: skill/competence | C7: cross-sector | D7: perform toxicological studies | E7: carry out toxicological studies apply toxicological testing methods perform toxicological study perform toxicological tests | G7: released | H7: 2023-11-30T15:10:42.752Z | K7: http://data.europa.eu/esco/concept-scheme/skills, http://data.europa.eu/esco/concept-scheme/member-skills | L7: Perform tests to detect poisons or drug misuse and help to monitor therapy by using chemical reagents, enzymes, radioisotopes and antibodies to detect abnormal chemical concentrations in the body.
A8: http://data.europa.eu/esco/skill/000c94d2-2a2e-4545-993c-6df8cb5b0316 | B8: skill/competence | C8: occupation-specific | D8: ensure coquille uniformity | E8: ensuring coquille is uniform make sure coquille is uniform check that coquille is uniform ensuring of coquille uniformity ensuring uniformity of coquille ensure uniformity of coquille ensure coquille is uniform checking that coquille is uniform | G8: released | H8: 2023-11-30T16:49:26.078Z | K8: http://data.europa.eu/esco/concept-scheme/skills, http://data.europa.eu/esco/concept-scheme/member-skills | L8: Oversee uniformity of coquilles; use casting equipment and tools such as welding machines.
A9: http://data.europa.eu/esco/skill/000f1d3d-220f-4789-9c0a-cc742521fb02 | B9: knowledge | C9: sector-specific | D9: Haskell | E9: Haskell techniques | G9: released | H9: 2023-11-30T16:13:21.77Z | K9: http://data.europa.eu/esco/concept-scheme/skills, http://data.europa.eu/esco/concept-scheme/member-skills, http://data.europa.eu/esco/concept-scheme/6c930acd-c104-4ece-acf7-f44fd7333036 | L9: The techniques and principles of software development, such as analysis, algorithms, coding, testing and compiling of programming paradigms in Haskell.
A10: http://data.europa.eu/esco/skill/001115fb-569f-4ee6-8381-c6807ef2527f | B10: skill/competence | C10: transversal | D10: show initiative | E10: initiate action be a driving force give impetus take the initiative show sense of initiative show active initiative demonstrate sense of initiative | F10: active participation activity initiative great initiative self starter | G10: released | H10: 2021-09-02T16:37:00.315Z | K10: http://data.europa.eu/esco/concept-scheme/skills, http://data.europa.eu/esco/concept-scheme/member-skills, http://data.europa.eu/esco/concept-scheme/skill-transversal-groups | L10: Be proactive and take the first step in an action without waiting for what others say or do.
A11: http://data.europa.eu/esco/skill/001d46db-035e-4b92-83a3-ed8771e0c123 | B11: skill/competence | C11: sector-specific | D11: train staff to reduce food waste | E11: teach students food waste reduction practices educate staff on food waste reduction educate workers on food recycling methods inform staff on food waste reduction practices | G11: released | H11: 2021-01-20T14:31:01.524Z | K11: http://data.europa.eu/esco/concept-scheme/skills, http://data.europa.eu/esco/concept-scheme/green, http://data.europa.eu/esco/concept-scheme/member-skills | L11: Establish new trainings and staff development provisions to support staff knowledge in food waste prevention and food recycling practices. Ensure that staff understands methods of and tools for food recycling, e.g., separating waste.
A12: http://data.europa.eu/esco/skill/0023e7a5-43da-4b68-bee3-726ef21f986d | B12: skill/competence | C12: cross-sector | D12: apply diplomatic principles | E12: administer diplomatic principles implement diplomatic principles utilise diplomacy principles administer diplomacy principles use diplomatic principles use diplomacy principles utilise diplomatic principles implement diplomacy principles | G12: released | H12: 2023-11-28T10:36:15.443Z | K12: http://data.europa.eu/esco/concept-scheme/skills, http://data.europa.eu/esco/concept-scheme/member-skills | L12: Apply the processes involved in the creation of international treaties by conducting negotiations between representatives of different countries, protecting the home government's interests, and facilitating compromise.
A13: http://data.europa.eu/esco/skill/00298d97-3dc3-4086-a902-bce0a2fba831 | B13: skill/competence | C13: sector-specific | D13: lead police investigations | E13: manage police investigations oversee police investigations supervise police enquiries oversee police enquiries supervise police investigations manage police enquiries | G13: released | H13: 2023-11-30T15:58:51.376Z | K13: http://data.europa.eu/esco/concept-scheme/skills, http://data.europa.eu/esco/concept-scheme/member-skills | L13: Lead investigations in police cases, which involves establishing an investigation strategy, contacting experts, being able to use different methods and points of view, and leading investigative staff.
A14: http://data.europa.eu/esco/skill/002b2e58-35ab-460c-be97-ca2f585fd990 | B14: skill/competence | C14: sector-specific | D14: handle fish harvesting waste | E14: dispose of waste from fish harvesting fish harvesting waste handling dispose of fish harvesting waste fish harvesting waste disposing | G14: released | H14: 2023-11-30T16:14:30.732Z | K14: http://data.europa.eu/esco/concept-scheme/skills, http://data.europa.eu/esco/concept-scheme/member-skills | L14: Dispose of waste, blood and inferior quality fish according to site waste management procedures.
A15: http://data.europa.eu/esco/skill/0037c821-2898-4919-b96e-7ed1cd89554c | B15: skill/competence | C15: cross-sector | D15: develop energy saving concepts | E15: develop concepts for energy saving create energy saving concepts energy saving concepts creating creating energy saving concepts creating concepts for energy saving energy saving concepts developing create concepts for energy saving | G15: released | H15: 2023-11-30T16:47:09.526Z | K15: http://data.europa.eu/esco/concept-scheme/skills, http://data.europa.eu/esco/concept-scheme/green, http://data.europa.eu/esco/concept-scheme/member-skills | L15: Use current research results and collaborate with experts to optimise or develop concepts, equipment, and production processes which require a lesser amount of energy such as new insulation practices and materials.
A16: http://data.europa.eu/esco/skill/004017c9-0337-4f5a-8077-798de9ef12e3 | B16: skill/competence | C16: sector-specific | D16: perform street interventions in social work | E16: conduct outreach activites carry out street interventions in social work perform street-intervention in social-work perform street intervention in social-work perform street-intervention in social work do street interventions in social work | G16: released | H16: 2023-11-30T15:11:30.413Z | K16: http://data.europa.eu/esco/concept-scheme/skills, http://data.europa.eu/esco/concept-scheme/member-skills | L16: Conduct outreach activities by providing direct information or counselling services to individuals in their neighbourhood or in the streets, usually targeted at youth or homeless people.
A17: http://data.europa.eu/esco/skill/004f1e68-9ca2-4f3f-92d9-e7d7ff6b9330 | B17: skill/competence | C17: sector-specific | D17: work with soloists | E17: collaborate with soloists communicate with solo artists work with a soloist | G17: released | H17: 2023-11-30T14:52:04.558Z | K17: http://data.europa.eu/esco/concept-scheme/skills, http://data.europa.eu/esco/concept-scheme/member-skills | L17: Communicate with solo artists and concert masters to discuss and prepare for performances.
A18: http://data.europa.eu/esco/skill/00506f28-e884-4496-800c-3477c67eb355 | B18: knowledge | C18: cross-sector | D18: sport and exercise medicine | E18: sports medicine sports injury medicine sports injury treatment exercise and sports medicine | G18: released | H18: 2023-11-28T10:35:15.768Z | K18: http://data.europa.eu/esco/concept-scheme/skills, http://data.europa.eu/esco/concept-scheme/member-skills | L18: Prevention and treatement of injuries or conditions resulted from a physical activity or sport.
A19: http://data.europa.eu/esco/skill/0058526a-11e9-40a1-ab33-7c5ffdf5da05 | B19: skill/competence | C19: sector-specific | D19: conduct research on flora | E19: perform research on flora run research on flora flora research research on flora carry out research on flora | G19: released | H19: 2025-07-25T11:15:00.857Z | K19: http://data.europa.eu/esco/concept-scheme/skills, http://data.europa.eu/esco/concept-scheme/member-skills | L19: Collect and analyse data about plants in order to discover their basic aspects such as origin, anatomy, and function.
A20: http://data.europa.eu/esco/skill/00735755-adc6-4ea0-b034-b8caff339c9f | B20: skill/competence | C20: cross-sector | D20: install heat pump | E20: installation of heat pumps commissioning heat pumps heat pump installing heat pump commissioning installation of heat pump commissioning heat pump commissioning of heat pumps heat pump installation commissioning of heat pump commission heat pumps commission heat pump | G20: released | H20: 2023-11-30T16:02:47.092Z | K20: http://data.europa.eu/esco/concept-scheme/skills, http://data.europa.eu/esco/concept-scheme/green, http://data.europa.eu/esco/concept-scheme/member-skills | L20: Install heat pumps, which use the physical properties of substances called refrigerants to extract heat from an environment and release it to a warmer environment, counter to spontaneous heat flow. Create the necessary openings and install the indoors and outdoors parts of the heat pump. Connect electricity and any ducts, and configure the heat pump.
A21: http://data.europa.eu/esco/skill/0082c13b-5866-4542-bc4f-722a4ae9530e | B21: skill/competence | C21: sector-specific | D21: design biomass installations | E21: design biomass energy system design biomass installation determine construction boundaries for biomass energy systems design biomass system calculate capacity indicators for biomass installations | G21: released | H21: 2024-02-26T09:06:09.511Z | K21: http://data.europa.eu/esco/concept-scheme/skills, http://data.europa.eu/esco/concept-scheme/green, http://data.europa.eu/esco/concept-scheme/member-skills | L21: Design the biomass energy system. Determine construction boundaries such as needed space and weight. Calculate indicators such as capacity, flow, and temperatures. Make detailed descriptions and drawings of the design.
A22: http://data.europa.eu/esco/skill/00831ebb-bac3-4bd1-8dae-2bca67be958d | B22: skill/competence | C22: occupation-specific | D22: handle equipment while suspended | E22: equipment handling while suspended use climbing equipment using climbing equipment while on a rope using climbing equipment use climbing equipment while on a rope | G22: released | H22: 2023-11-30T16:15:46.521Z | K22: http://data.europa.eu/esco/concept-scheme/skills, http://data.europa.eu/esco/concept-scheme/member-skills | L22: Safely operate hand equipment while suspended on a rope. Take on a secure and stable position before starting the operation. After finishing, store the equipment safely, usually by attaching it to a belt buckle.
... A53: http://data.europa.eu/esco/skill/0132ac4f-ffac-4396-8b56-052fde0c9d73 | B53: knowledge | C53: sector-specific | D53: types of barley | E53: categories of barley kinds of barley strains of barley varieties of barley barley types | G53: released | H53: 2023-11-30T14:57:44.02Z | K53: http://data.europa.eu/esco/concept-scheme/skills, http://data.europa.eu/esco/concept-scheme/member-skills | L53: The different types of barley; their characteristics, and quality.
A54: http://data.europa.eu/esco/skill/013441c1-1f13-47e9-80c4-9a53e8e1bc05 | B54: knowledge | C54: sector-specific | D54: KDevelop | E54: kdevplatform KDevelop platform | F54: KDevelop 4.7.0 KDevelop 4.6.0 KDevelop 5.0.0 KDevelop 4.0.0 | G54: released | H54: 2023-06-08T15:25:12.058Z | K54: http://data.europa.eu/esco/concept-scheme/skills, http://data.europa.eu/esco/concept-scheme/member-skills, http://data.europa.eu/esco/concept-scheme/6c930acd-c104-4ece-acf7-f44fd7333036 | L54: The computer program KDevelop is a suite of software development tools for writing programs, such as compiler, debugger, code editor, code highlights, packaged in a unified user interface. It is developed by the software community KDE.
A55: http://data.europa.eu/esco/skill/0138fdc7-edbb-485c-9aa9-544f723eb62f | B55: skill/competence | C55: sector-specific | D55: purchase vehicle parts | E55: carrying out parts purchasing complete parts purchasing carry out parts purchases make parts purchasing oversee parts purchasing carry out parts purchasing carry out part purchasing undertake parts purchasing | G55: released | H55: 2020-06-30T08:41:54.136Z | K55: http://data.europa.eu/esco/concept-scheme/skills, http://data.europa.eu/esco/concept-scheme/member-skills | L55: Order specific parts required for maintenance and repair of a wide variety of vehicles.
A56: http://data.europa.eu/esco/skill/013a64b9-5e74-4f7f-af5b-9ec76715238b | B56: skill/competence | C56: cross-sector | D56: inspect offshore constructions | E56: examine offshore constructions evaluate offshore constructions check offshore constructions assess offshore constructions | G56: released | H56: 2025-07-25T11:15:00.857Z | K56: http://data.europa.eu/esco/concept-scheme/skills, http://data.europa.eu/esco/concept-scheme/member-skills | L56: Conduct regular inspections during and after the construction of offshore facilities such as oil platforms to ensure risk minimisation and compliance with regulations.
A57: http://data.europa.eu/esco/skill/0156865e-5010-4908-8e0f-ce3aebc2d136 | B57: skill/competence | C57: occupation-specific | D57: adjust envelope cutting settings | E57: modify envelope cutting settings change envelope cutting settings adapt envelope cutting settings tweak envelope cutting settings | G57: released | H57: 2023-11-30T16:18:14.909Z | K57: http://data.europa.eu/esco/concept-scheme/skills, http://data.europa.eu/esco/concept-scheme/member-skills | L57: Make sure that the right window cutting and patching standard are used. Prepare this by gumming on the blank with a dry patch and on the window material during its conveyance. Adjust on the basis of window, gum, and patch position and level of evenness.
A58: http://data.europa.eu/esco/skill/0157feec-52c2-4764-b83d-2d017ce8e49d | B58: skill/competence | C58: sector-specific | D58: prepare oils | E58: prepare oil arrange oil select and mix oil arrange oils assemble oils assemble oil | G58: released | H58: 2023-11-30T15:09:08.216Z | K58: http://data.europa.eu/esco/concept-scheme/skills, http://data.europa.eu/esco/concept-scheme/member-skills | L58: Select the appropriate oils for the client, mix and blend them in order to create individualised compounds with specific needs and ratios for clients, keeping records of applied treatments and the blends used during the therapy.
A59: http://data.europa.eu/esco/skill/015b0162-6dd3-4d46-bbfd-325086155dd5 | B59: skill/competence | C59: sector-specific | D59: purchase supplies | E59: acquire supplies pay for supplies gain supplies purchase DIY supplies purchase of supplies supplies purchasing purchasing supplies buy supplies | G59: released | H59: 2025-02-27T12:45:08.961Z | K59: http://data.europa.eu/esco/concept-scheme/skills, http://data.europa.eu/esco/concept-scheme/member-skills | L59: Purchase and replenish supplies; make sure that all required goods are available in stock.
A60: http://data.europa.eu/esco/skill/015cd017-b146-4c9d-ab10-5dfca451c30a | B60: skill/competence | C60: sector-specific | D60: pursue excellence in the creation of food products | E60: look for excellence in the creation of food products pursue excellence in the creation of a food product aim for excellence in the creation of food products seek excellence in the creation of food products | G60: released | H60: 2023-11-28T10:50:07.376Z | K60: http://data.europa.eu/esco/concept-scheme/skills, http://data.europa.eu/esco/concept-scheme/member-skills | L60: Try to develop food products in their most qualitative form possible.
A61: http://data.europa.eu/esco/skill/0162b701-6bb4-400a-b557-7996053d7daf | B61: skill/competence | C61: sector-specific | D61: maintain personal hygiene standards when cleaning | E61: keep up personal hygiene standards when cleaning sustain personal hygiene standards when cleaning maintain personal hygiene standard when cleaning maintain personal hygiene when cleaning | G61: released | H61: 2023-11-30T15:55:38.825Z | K61: http://data.europa.eu/esco/concept-scheme/skills, http://data.europa.eu/esco/concept-scheme/member-skills | L61: Make sure to keep yourself clean and tidy and wear protective equipment when performing cleaning activities, as required by the health and safety procedures of the task or the organisation.
A62: http://data.europa.eu/esco/skill/0165e6c7-14d9-47f6-a882-565f8da14526 | B62: knowledge | C62: occupation-specific | D62: water skiing | E62: waterski | G62: released | H62: 2023-10-31T17:05:37.122Z | K62: http://data.europa.eu/esco/concept-scheme/skills, http://data.europa.eu/esco/concept-scheme/member-skills | L62: The techniques and rules for the practice of water skiing. Knowledge of the equipment needed for this high-speed water surface sport such as the tow rope, boat, wetsuits, and the ski boards.
A63: http://data.europa.eu/esco/skill/0167ee96-f478-4383-afe6-aabf387da5b3 | B63: skill/competence | C63: cross-sector | D63: liaise with typists | E63: collaborate with typists liaise with typist liaising with typists cooperate with typists work together with typists | G63: released | H63: 2024-01-09T14:25:41.682Z | K63: http://data.europa.eu/esco/concept-scheme/skills, http://data.europa.eu/esco/concept-scheme/member-skills | L63: Give instructions to typists about the addressees, the appropriate format, the number of copies required, etc. for them to type the final documents.
A64: http://data.europa.eu/esco/skill/016cee6c-9e95-466c-bd51-d63327751aa2 | B64: skill/competence | C64: sector-specific | D64: assess railway operations | E64: conduct review of railway performance conduct study on railway operations and performance analyse railway operations conduct analysis of railway operations appraise railway operations evaluate railway operations review railway operations conduct evaluation of railway performance | G64: released | H64: 2023-11-30T16:24:13.621Z | K64: http://data.europa.eu/esco/concept-scheme/skills, http://data.europa.eu/esco/concept-scheme/member-skills | L64: Review and study existing railroad equipment, facilities, systems and processes in order to improve railway safety and efficiency, increase quality, and reduce costs.
A65: http://data.europa.eu/esco/skill/016e7bf4-fe86-4a1f-ace1-54e5b697293d | B65: skill/competence | C65: occupation-specific | D65: practise extreme sports | E65: practising extreme sports practise extreme sport engage in extreme sports participate in extreme sports play extreme sports practice extreme sports | G65: released | H65: 2016-12-20T19:41:34Z | K65: http://data.europa.eu/esco/concept-scheme/skills, http://data.europa.eu/esco/concept-scheme/member-skills | L65: Practise action sports considered to have a high level of inherent danger and involving speed, height, a high level of physical exertion, and highly specialized gear.
A66: http://data.europa.eu/esco/skill/0171653e-c8e9-4c24-bb86-a4b6fe038f25 | B66: skill/competence | C66: transversal | D66: adopt ways to foster biodiversity and animal welfare | E66: concretely support biodiversity and animal welfare implement environmental choices in your own eating habit adopt a sustainable eating habit take sustainability issues into account in consumption choices take animal welfare into account when buying food products promoting organic and biological food consumption | F66: think about biodiversity eat bio aim for a vegan diet | G66: released | H66: 2021-09-13T12:37:55.414Z | K66: http://data.europa.eu/esco/concept-scheme/skills, http://data.europa.eu/esco/concept-scheme/green, http://data.europa.eu/esco/concept-scheme/member-skills, http://data.europa.eu/esco/concept-scheme/skill-transversal-groups | L66: Engage in behaviours that help maintaining stable ecosystems and combatting mass extinction, for example by making conscious dietary choices that support organic food production and animal welfare.
A67: http://data.europa.eu/esco/skill/0174a9e6-bf12-4ac3-bfc3-0a5469410f18 | B67: skill/competence | C67: occupation-specific | D67: provide chaperone for children on set | E67: arrange chaperone for children on set providing chaperone for children on set provide chaperone for child on set organise chaperone for children on set offer chaperone for children on set | G67: released | H67: 2023-11-30T15:06:53.54Z | K67: http://data.europa.eu/esco/concept-scheme/skills, http://data.europa.eu/esco/concept-scheme/member-skills | L67: Make sure there is always a chaperone present on the set when recruiting underage children to perform in a motion picture.
A68: http://data.europa.eu/esco/skill/01755f08-4df4-4cf0-8d22-08f94cad68b5 | B68: skill/competence | C68: cross-sector | D68: organise labour | E68: worker organising organise workers organize labor organising labour workers organising labour organising organising workers | G68: released | H68: 2016-12-20T17:23:17Z | K68: http://data.europa.eu/esco/concept-scheme/skills, http://data.europa.eu/esco/concept-scheme/member-skills | L68: Organise, allocate and coordinate members of the team. Organise production programmes and plan the production and sales. Purchase materials and equipment. Manage stocks.
A69: http://data.europa.eu/esco/skill/017738e7-7d12-4e87-a580-8523405bab96 | B69: skill/competence | C69: sector-specific | D69: use glass engraving tools | E69: work with glass engraving tools glass engraving with tools glass engraving tools using working with glass engraving tools use engraving tools on glass using glass engraving tools | G69: released | H69: 2023-11-30T14:56:16.943Z | K69: http://data.europa.eu/esco/concept-scheme/skills, http://data.europa.eu/esco/concept-scheme/member-skills | L69: Use engraving tools which use steel, stone or copper wheels according to the kind of glass or glassware.
A70: http://data.europa.eu/esco/skill/017d3b78-ebfa-431d-acc5-8050e9b0fdc8 | B70: skill/competence | C70: sector-specific | D70: operate wrecking ball | E70: control wrecking ball operation of wrecking ball demolish structure with wrecking ball wrecking ball control demolition with wrecking ball wrecking ball operation | G70: released | H70: 2023-11-30T15:32:54.775Z | K70: http://data.europa.eu/esco/concept-scheme/skills, http://data.europa.eu/esco/concept-scheme/member-skills | L70: Use a wrecking ball to demolish a structure or parts of it. Hoist the wrecking ball into the air with a crane. Drop the ball or swing it in a controlled manner to hit the structure. Prevent misses as the weight and momentum of the ball may destabilise the crane.
A71: http://data.europa.eu/esco/skill/018164df-2814-4926-bdf7-398d86b9dfe6 | B71: skill/competence | C71: cross-sector | D71: evaluate garment quality | E71: estimate wearing apparel quality evaluate quality of clothing evaluate quality of garments evaluate wearing apparel quality evaluate quality of wearing apparel estimate clothing quality inspect clothing quality evaluate clothing quality inspect garment quality estimate garment quality | G71: released | H71: 2023-11-30T16:50:33.272Z | K71: http://data.europa.eu/esco/concept-scheme/skills, http://data.europa.eu/esco/concept-scheme/member-skills | L71: Evaluating stitching, construction, attachments, fasteners, embellishments, shading within the garment; evaluating pattern continuity-, matching; evaluating tapes and linings.
A72: http://data.europa.eu/esco/skill/01819474-b960-4b8f-b020-2da26518d43a | B72: skill/competence | C72: occupation-specific | D72: apply for refunds | E72: refund applications undertake refunds apply for a refund administer refunds implement refunds make refunds | G72: released | H72: 2023-11-30T16:23:24.77Z | K72: http://data.europa.eu/esco/concept-scheme/skills, http://data.europa.eu/esco/concept-scheme/member-skills | L72: Make inquiries at the supplier in order to return, exchange or refund goods.
A73: http://data.europa.eu/esco/skill/01895f13-1989-4756-80d6-9b9ee19ddb32 | B73: skill/competence | C73: sector-specific | D73: perform a feasibility study for building management systems | E73: conduct a viability analysis for facility management systems carry out bms feasibility study execute a feasibility investigation for building management systems undertake an assessment of building management system feasibility | G73: released | H73: 2024-03-01T09:56:50.064Z | K73: http://data.europa.eu/esco/concept-scheme/skills, http://data.europa.eu/esco/concept-scheme/green, http://data.europa.eu/esco/concept-scheme/member-skills | L73: Perform the evaluation and assessment of the potential of a building management system. Realise a standardised study to determine the energy saving contribution, costs and restrictions, and conduct research to support the process of decision making.
A74: http://data.europa.eu/esco/skill/0189f448-179e-47cc-9716-c5c3ac4b1aec | B74: knowledge | C74: sector-specific | D74: Absorb (learning management systems) | E74: Absorb | G74: released | H74: 2022-07-05T14:34:21.232Z | K74: http://data.europa.eu/esco/concept-scheme/skills, http://data.europa.eu/esco/concept-scheme/member-skills, http://data.europa.eu/esco/concept-scheme/6c930acd-c104-4ece-acf7-f44fd7333036 | L74: The learning system Absorb is an e-learning platform for creating, administrating and delivering e-learning education courses or training programs for secondary school students.
A75: http://data.europa.eu/esco/skill/0194a8eb-c262-411a-ad3f-f3d587630562 | B75: skill/competence | C75: occupation-specific | D75: peform small vessel administrative duties | E75: fulfil administrative duties on a small vessel perform small vessel administrative duties performing administrative duties on a small vessel perform administrative duties on a small vessel performing small vessel administrative duties fulfil small vessel administrative duties fulfilling administrative duties on a small vessel fulfilling small vessel administrative duties | G75: released | H75: 2016-12-20T21:29:15Z | K75: http://data.europa.eu/esco/concept-scheme/skills, http://data.europa.eu/esco/concept-scheme/member-skills | L75: Fulfil administrative and labour requirements. Plan provisioning, receipt and stowage. Release the ship in accordance with current regulations.
A76: http://data.europa.eu/esco/skill/0196d283-9b1a-43a5-b219-43580c7cf560 | B76: knowledge | C76: sector-specific | D76: cosmetics ingredients | E76: ingredients of cosmetics a cosmetics ingredient cosmetics raw materials cosmetics elements cosmetics additives | G76: released | H76: 2023-11-30T16:42:44.887Z | K76: http://data.europa.eu/esco/concept-scheme/skills, http://data.europa.eu/esco/concept-scheme/member-skills | L76: A variety of sources cosmetics are composed of ranging from crushed insects to rust.
A77: http://data.europa.eu/esco/skill/01a6e6ae-32d5-440a-bdb3-c9ed8a1f57c0 | B77: knowledge | C77: occupation-specific | D77: human dynamics as part of hospitality security | E77: hospitality security human dynamics human dynamics as part of security in hospitality behavioural insight for customers' security human behaviour as part of a security programme | G77: released | H77: 2023-11-30T16:06:59.884Z | K77: http://data.europa.eu/esco/concept-scheme/skills, http://data.europa.eu/esco/concept-scheme/member-skills | L77: The characteristics of human behaviour and human interaction and dynamics to ensure their security in hospitality establishment.
A78: http://data.europa.eu/esco/skill/01c03003-516d-43c6-8477-45c472413521 | B78: skill/competence | C78: cross-sector | D78: advise on construction materials | E78: provide advice on construction materials giving of advice on construction materials advise about construction materials advise regarding construction materials giving advice on construction materials give advice on construction materials | G78: released | H78: 2023-11-30T16:20:48.674Z | I78: It includes building stone, sand, bricks, clay and gravel. | K78: http://data.europa.eu/esco/concept-scheme/skills, http://data.europa.eu/esco/concept-scheme/member-skills | L78: Provide advice on and test a wide range of construction materials.
A79: http://data.europa.eu/esco/skill/01c4bbed-0449-44c9-9c05-48c30ffdcc22 | B79: skill/competence | C79: sector-specific | D79: maintain rotating equipment | E79: mend revolving equipment reconstruct revolving equipment overhaul revolving equipment overhaul rotating equipment replace revolving equipment mend rotating equipment reconstruct rotating equipment replace rotating equipment maintain revolving equipment | G79: released | H79: 2023-11-28T16:54:40.373Z | K79: http://data.europa.eu/esco/concept-scheme/skills, http://data.europa.eu/esco/concept-scheme/member-skills | L79: Perform routine maintenance on rotating equipment to ensure that it is clean and in safe, working order.
A80: http://data.europa.eu/esco/skill/01d269d9-b058-4d6c-82a0-3779af9a124b | B80: skill/competence | C80: cross-sector | D80: develop blockchain innovative architectures | E80: build innovative blockchain architectures | G80: released | H80: 2023-11-29T16:35:26.138Z | K80: http://data.europa.eu/esco/concept-scheme/skills, http://data.europa.eu/esco/concept-scheme/member-skills, http://data.europa.eu/esco/concept-scheme/6c930acd-c104-4ece-acf7-f44fd7333036 | L80: Develop new blockchain architectures that address properties and priorities as they are needed by specific applications. Argue the advantages and shortcomings of such new architectures with respect to existing ones.
A81: http://data.europa.eu/esco/skill/01d3d692-dcba-4544-82d2-fc27726bdbbc | B81: skill/competence | C81: occupation-specific | D81: pump products for storage | E81: pump goods for storage pump merchandise for storage pump artefacts for storage pump items for storage | G81: released | H81: 2023-11-30T15:06:10.264Z | K81: http://data.europa.eu/esco/concept-scheme/skills, http://data.europa.eu/esco/concept-scheme/member-skills | L81: Store tanks or other equipment to process bleached paper pulp for further steps in the paper-making procedure.
A82: http://data.europa.eu/esco/skill/01d80f57-3906-44e9-8592-fd1bd8a35808 | B82: knowledge | C82: sector-specific | D82: medico-biological and medical sciences related to dentistry | E82: medico-biological and medical principles relevant for dentistry medico-biological and medical aspects of dentistry dentistry-related medico-biological and medical sciences dentistry medico-biological and medical sciences | G82: released | H82: 2025-06-19T08:51:06.542Z | K82: http://data.europa.eu/esco/concept-scheme/skills, http://data.europa.eu/esco/concept-scheme/member-skills | L82: The behavioral component and the social environment which impact the health of humans, in respect to dentistry.
A83: http://data.europa.eu/esco/skill/01e5d2e2-d368-4fb9-9be9-9923146482c4 | B83: skill/competence | C83: sector-specific | D83: attend to detail in casting processes | E83: attend to casting processes detail attend to casting process details attention to detail in casting processes | G83: released | H83: 2023-11-30T16:25:46.558Z | K83: http://data.europa.eu/esco/concept-scheme/skills, http://data.europa.eu/esco/concept-scheme/member-skills | L83: Attend in the metal processing casting work to specificities and details concerning the quality of the casting and moulds.
A84: http://data.europa.eu/esco/skill/01e66e1c-97d9-4829-bee1-f3ab649161e8 | B84: knowledge | C84: cross-sector | D84: biomedical science | E84: principles of natural sciences applied to medicine | G84: released | H84: 2023-11-30T16:26:20.41Z | K84: http://data.europa.eu/esco/concept-scheme/skills, http://data.europa.eu/esco/concept-scheme/member-skills | L84: The principles of the natural sciences applied to medicine. Medical sciences such as medical microbiology and clinical virology apply biology principles for medical knowledge and invention.
A85: http://data.europa.eu/esco/skill/01e7dee7-3ff1-4807-acad-058dbed91aba | B85: skill/competence | C85: sector-specific | D85: keep up to date on product knowledge | E85: keep posted on product knowledge | G85: released | H85: 2023-11-30T16:01:41.287Z | K85: http://data.europa.eu/esco/concept-scheme/skills, http://data.europa.eu/esco/concept-scheme/member-skills | L85: Gather the latest information on developments related to the existing or supported products, methods or techniques.
A86: http://data.europa.eu/esco/skill/01f10952-cb59-4347-9aee-d4fbc51c870a | B86: skill/competence | C86: transversal | D86: write Hungarian | E86: correspond in written Hungarian show competency in written Hungarian | G86: released | H86: 2025-01-27T11:13:37.824Z | K86: http://data.europa.eu/esco/concept-scheme/skills, http://data.europa.eu/esco/concept-scheme/member-skills, http://data.europa.eu/esco/concept-scheme/skill-language-groups | L86: Compose written texts in Hungarian.
A87: http://data.europa.eu/esco/skill/01f91b5b-3e2f-40a2-ab88-bc8113c0ab37 | B87: skill/competence | C87: sector-specific | D87: monitor drilling fluid | E87: monitoring drilling fluid monitor mud monitoring of mud drilling mud monitoring monitoring mud monitoring drilling fluids drilling fluid monitoring monitoring of drilling mud monitoring drilling mud monitoring of drilling fluid drilling fluids monitoring monitor drilling mud mud monitoring | G87: released | H87: 2023-11-30T15:34:22.784Z | K87: http://data.europa.eu/esco/concept-scheme/skills, http://data.europa.eu/esco/concept-scheme/member-skills | L87: Monitor and maintain the drilling fluids, or "mud". Add different chemicals to the fluid to perform various function in well operations: keep the drill bit cool, provide hydrostatic pressure, etc.
A88: http://data.europa.eu/esco/skill/01faf296-e037-494c-bb1c-65bda5aed750 | B88: skill/competence | C88: sector-specific | D88: develop efficiency plans for maritime shipping | E88: produce maritime shipping efficiency plans produce and implement plans to ensure maritime efficiency develop efficiency plans for shipping oversee planning for maritime efficiency produce efficiency plans for maritime shipping ensure maritime efficiency through planning oversee maritime shipping efficiency plans develop maritime shipping efficiency plans implement maritime efficiency plans | G88: released | H88: 2023-11-30T16:45:35.382Z | K88: http://data.europa.eu/esco/concept-scheme/skills, http://data.europa.eu/esco/concept-scheme/member-skills | L88: Arrange the most efficient use of cargo space and vessel movement; monitor the number of available cranes and dock space; and assess the physical condition of ships and impact of cargo weight on the stability of ships.
A89: http://data.europa.eu/esco/skill/01fec851-b5f4-419b-940a-3b4c835adfa8 | B89: skill/competence | C89: cross-sector | D89: tend packaging machines | E89: watch packaging machines mind packaging machines tend packaging machinery take care of packaging machines look after packaging machines tend a packaging machines | G89: released | H89: 2023-11-30T14:58:41.778Z | K89: http://data.europa.eu/esco/concept-scheme/skills, http://data.europa.eu/esco/concept-scheme/member-skills | L89: Tend packaging machines such as filling, labelling, and sealing machines. Stock and sort products to be processed according to specifications. Replenish packaging supplies as required, such as boxes, cartons, wrapping paper, plastic sheet, glue, ink, or labels.
A90: http://data.europa.eu/esco/skill/01ffbbf3-0c62-45e0-92d9-01a86dc7c81d | B90: skill/competence | C90: occupation-specific | D90: advise on clay products handling | E90: instruct on clay products handling instructing on handling of clay products instruct on clay product handling instructing on clay product handling advising on handling of clay products | G90: released | H90: 2023-11-30T16:19:16.077Z | K90: http://data.europa.eu/esco/concept-scheme/skills, http://data.europa.eu/esco/concept-scheme/member-skills | L90: Advise other workers on the covering of end-products with tarpaulin.
... A122: http://data.europa.eu/esco/skill/02bbd0fb-b108-49a8-9c48-5b0c447d3fdf | B122: skill/competence | C122: occupation-specific | D122: calculate stairs rise and run | E122: stairs rise and run calculation stair rise and run assessment calculate staircase rise and run staircase rise and run assessment calculation of stair rise and run assessment of stair rise and run calculations for stair rise and run calculate staircase dimensions staircase rise and run calculation calculate stair rise and run measurements calculating stair rise and run calculate staircase rise and run measurements | G122: released | H122: 2024-02-09T17:29:10.678Z | K122: http://data.europa.eu/esco/concept-scheme/skills, http://data.europa.eu/esco/concept-scheme/member-skills | L122: Calculate the appropriate measures for the rise and run of each stair, taking into account the total height and depth of the stairs, any floor covering, and the range of stair measurements that allow comfortable use.
A123: http://data.europa.eu/esco/skill/02bf9522-bd6e-4482-be03-1827483be21a | B123: knowledge | C123: sector-specific | D123: first aid for animals | E123: characteristics of animal emergency treatment principles of first aid for animals basic emergency treatment for animals basic knowledge of first aid provision to animals basic animal first aid animal first aid principles basic animal emergency treatment basic 1st aid for animals aims of animal first aid | G123: released | H123: 2024-02-09T17:29:15.235Z | I123: It includes safe working considerations, animal assessment and handling. Principles and aims of first aid treatment, common conditions and injuries, and appropriate first aid response. | K123: http://data.europa.eu/esco/concept-scheme/skills, http://data.europa.eu/esco/concept-scheme/member-skills | L123: Animal emergency treatment, including the principles and aims of the provision of first aid treatment to animals.
A124: http://data.europa.eu/esco/skill/02c1a369-f1e7-4f8e-8882-d7ded57f9cf4 | B124: skill/competence | C124: sector-specific | D124: empathise with outdoor groups | E124: understand participants of outdoor activities empathise with groups empathize with outdoor groups empathise with participants of outdoor sports | G124: released | H124: 2016-12-20T17:39:39Z | K124: http://data.europa.eu/esco/concept-scheme/skills, http://data.europa.eu/esco/concept-scheme/member-skills | L124: Identify the outdoor activities permitted or suited in an outdoor setting based on the group's needs.
A125: http://data.europa.eu/esco/skill/02c462b7-b93b-44a7-ba3a-9d3b7a163f51 | B125: skill/competence | C125: sector-specific | D125: provide context to news stories | E125: offer context to news stories situate news stories provide context to news story contextualize news stories providing context to news stories | G125: released | H125: 2024-02-09T17:29:13.7Z | K125: http://data.europa.eu/esco/concept-scheme/skills, http://data.europa.eu/esco/concept-scheme/member-skills | L125: Provide substantial context to national or international news stories to explain things in more detail.
A126: http://data.europa.eu/esco/skill/02c71cde-f513-43da-8952-0974763c7568 | B126: skill/competence | C126: sector-specific | D126: interpret circuit diagrams | E126: understand circuit schematics interpret electrical circuit diagrams understand circuit blueprints read circuit diagrams interpret elementary diagrams read diagrams of circuits | G126: released | H126: 2023-02-23T20:38:00.78Z | K126: http://data.europa.eu/esco/concept-scheme/skills, http://data.europa.eu/esco/concept-scheme/member-skills | L126: Read and comprehend circuit diagrams showing the connections between the devices, such as power and signal connections.
A127: http://data.europa.eu/esco/skill/02c7caf4-4e8b-4745-8917-dbbd3af17c28 | B127: skill/competence | C127: sector-specific | D127: draw up artistic production | E127: drawing up artistic production document artistic production draw up artistic productions write down artistic production register artistic production record artistic production | G127: released | H127: 2024-02-09T17:29:11.47Z | K127: http://data.europa.eu/esco/concept-scheme/skills, http://data.europa.eu/esco/concept-scheme/member-skills | L127: File and document a production in all its phases right after the performance period so that it can be reproduced and all relevant information remains accessible.
A128: http://data.europa.eu/esco/skill/02d5c52b-e7f9-4d8c-adc2-d0332f49535b | B128: skill/competence | C128: occupation-specific | D128: install passenger service units | E128: attach passenger service units place PSUs adjust passenger service units for use prepare passenger service units for use fix passenger service units install aircraft components situated above passenger seats install PSUs put into operation PSUs mount passenger service units | G128: released | H128: 2024-02-09T17:29:12.952Z | K128: http://data.europa.eu/esco/concept-scheme/skills, http://data.europa.eu/esco/concept-scheme/member-skills | L128: Install PSUs in ceiling of an aircraft by using hand and power tools.
A129: http://data.europa.eu/esco/skill/02d68c2b-1722-4440-8e25-376650e123c8 | B129: skill/competence | C129: transversal | D129: understand written Korean | E129: read Korean comprehend written Korean make sense of written Korean interpret written Korean understand Korean writing | G129: released | H129: 2025-01-27T15:17:56.551Z | K129: http://data.europa.eu/esco/concept-scheme/skills, http://data.europa.eu/esco/concept-scheme/member-skills, http://data.europa.eu/esco/concept-scheme/skill-language-groups | L129: Read and comprehend written texts in Korean.
A130: http://data.europa.eu/esco/skill/02e0b3e9-c9e0-4063-983b-b5a7697e0f78 | B130: skill/competence | C130: sector-specific | D130: keep records of bridge investigation findings | E130: keep written records of bridge investigation findings produce written records of bridge investigations record the findings of bridge investigations in writing keep records of the findings of bridge investigations maintain records of bridge investigations maintain records of the findings of bridge investigations ensure written records of the findings of bridge investigations are maintained keep records of bridge investigations maintain records of bridge investigation findings ensure findings of bridge investigations are recorded in writing | G130: released | H130: 2025-02-27T12:45:08.961Z | K130: http://data.europa.eu/esco/concept-scheme/skills, http://data.europa.eu/esco/concept-scheme/member-skills | L130: Register the results of bridge investigations and send them to the appropriate authorities.
A131: http://data.europa.eu/esco/skill/02e1ca57-0715-438b-886d-f0f938ac3efc | B131: knowledge | C131: occupation-specific | D131: sand blasting machine parts | E131: sand blasting machine components sand blasting machine pieces blasting abrasive machine pieces sand blasting machine units sand blasting machine elements blasting abrasive machine elements blasting abrasive machine units blasting abrasive machine components | G131: released | H131: 2024-02-09T17:29:14.494Z | K131: http://data.europa.eu/esco/concept-scheme/skills, http://data.europa.eu/esco/concept-scheme/member-skills | L131: The various parts of a type of sand blasting machinery, their qualities and applications, such as a treadle, blast nozzle, dust collecter, filter, abrasive materials and others.
A132: http://data.europa.eu/esco/skill/02e22093-3436-46a8-8dc5-b041bc4800cc | B132: skill/competence | C132: occupation-specific | D132: create model | E132: create models construct model design model creating model make model build model | G132: released | H132: 2024-02-09T17:29:11.47Z | K132: http://data.europa.eu/esco/concept-scheme/skills, http://data.europa.eu/esco/concept-scheme/member-skills | L132: Create sketches, drawing, three-dimensional models, and models in other media in preparation for a work of art.
A133: http://data.europa.eu/esco/skill/02e235f4-a30a-412a-a06e-1c471ad28678 | B133: skill/competence | C133: sector-specific | D133: follow procedures to control substances hazardous to health | E133: follow control of health procedures for hazardous substances ensure safe use of substances hazardous to health follow control of substances hazardous to health procedures comply with guidelines for use of hazardous substances follow health procedures for the control of hazardous substances | G133: released | H133: 2025-07-25T11:15:00.857Z | K133: http://data.europa.eu/esco/concept-scheme/skills, http://data.europa.eu/esco/concept-scheme/member-skills | L133: Adhere to the Control of Substances Hazardous to Health (COSHH) procedures for activities that involve hazardous substances, such as bacteria, allergens, waste oil, paint or brake fluids that result in illness or injury.
A134: http://data.europa.eu/esco/skill/02eeea19-76db-4d19-bb8b-a649c0fbe796 | B134: skill/competence | C134: sector-specific | D134: assess visual impact of displays | E134: check visual impact of displays assess the visual impact of a display assess the visual impact of displays appraise visual impact of displays test visual impact of displays judge visual impact of displays assessing the visual impact of displays | G134: released | H134: 2024-02-09T17:29:12.952Z | K134: http://data.europa.eu/esco/concept-scheme/skills, http://data.europa.eu/esco/concept-scheme/member-skills | L134: Analyse feedback from customers and co-workers on the visual impact of displays and showcases. Implement changes where needed.
